{"name": "Early Dynastic Cuneiform", "start": 74880, "end": 75087, "coverage": "all", "cps": {"74880": {"name": "CUNEIFORM SIGN AB TIMES NUN TENU"}, "74881": {"name": "CUNEIFORM SIGN AB TIMES SHU2"}, "74882": {"name": "CUNEIFORM SIGN AD TIMES ESH2"}, "74883": {"name": "CUNEIFORM SIGN BAD TIMES DISH TENU"}, "74884": {"name": "CUNEIFORM SIGN BAHAR2 TIMES AB2"}, "74885": {"name": "CUNEIFORM SIGN BAHAR2 TIMES NI"}, "74886": {"name": "CUNEIFORM SIGN BAHAR2 TIMES ZA"}, "74887": {"name": "CUNEIFORM SIGN BU OVER BU TIMES NA2"}, "74888": {"name": "CUNEIFORM SIGN DA TIMES TAK4"}, "74889": {"name": "CUNEIFORM SIGN DAG TIMES KUR"}, "74890": {"name": "CUNEIFORM SIGN DIM TIMES IGI"}, "74891": {"name": "CUNEIFORM SIGN DIM TIMES U U U"}, "74892": {"name": "CUNEIFORM SIGN DIM2 TIMES UD"}, "74893": {"name": "CUNEIFORM SIGN DUG TIMES ANSHE"}, "74894": {"name": "CUNEIFORM SIGN DUG TIMES ASH"}, "74895": {"name": "CUNEIFORM SIGN DUG TIMES ASH AT LEFT"}, "74896": {"name": "CUNEIFORM SIGN DUG TIMES DIN"}, "74897": {"name": "CUNEIFORM SIGN DUG TIMES DUN"}, "74898": {"name": "CUNEIFORM SIGN DUG TIMES ERIN2"}, "74899": {"name": "CUNEIFORM SIGN DUG TIMES GA"}, "74900": {"name": "CUNEIFORM SIGN DUG TIMES GI"}, "74901": {"name": "CUNEIFORM SIGN DUG TIMES GIR2 GUNU"}, "74902": {"name": "CUNEIFORM SIGN DUG TIMES GISH"}, "74903": {"name": "CUNEIFORM SIGN DUG TIMES HA"}, "74904": {"name": "CUNEIFORM SIGN DUG TIMES HI"}, "74905": {"name": "CUNEIFORM SIGN DUG TIMES IGI GUNU"}, "74906": {"name": "CUNEIFORM SIGN DUG TIMES KASKAL"}, "74907": {"name": "CUNEIFORM SIGN DUG TIMES KUR"}, "74908": {"name": "CUNEIFORM SIGN DUG TIMES KUSHU2"}, "74909": {"name": "CUNEIFORM SIGN DUG TIMES KUSHU2 PLUS KASKAL"}, "74910": {"name": "CUNEIFORM SIGN DUG TIMES LAK-020"}, "74911": {"name": "CUNEIFORM SIGN DUG TIMES LAM"}, "74912": {"name": "CUNEIFORM SIGN DUG TIMES LAM TIMES KUR"}, "74913": {"name": "CUNEIFORM SIGN DUG TIMES LUH PLUS GISH"}, "74914": {"name": "CUNEIFORM SIGN DUG TIMES MASH"}, "74915": {"name": "CUNEIFORM SIGN DUG TIMES MES"}, "74916": {"name": "CUNEIFORM SIGN DUG TIMES MI"}, "74917": {"name": "CUNEIFORM SIGN DUG TIMES NI"}, "74918": {"name": "CUNEIFORM SIGN DUG TIMES PI"}, "74919": {"name": "CUNEIFORM SIGN DUG TIMES SHE"}, "74920": {"name": "CUNEIFORM SIGN DUG TIMES SI GUNU"}, "74921": {"name": "CUNEIFORM SIGN E2 TIMES KUR"}, "74922": {"name": "CUNEIFORM SIGN E2 TIMES PAP"}, "74923": {"name": "CUNEIFORM SIGN ERIN2 X"}, "74924": {"name": "CUNEIFORM SIGN ESH2 CROSSING ESH2"}, "74925": {"name": "CUNEIFORM SIGN EZEN SHESHIG TIMES ASH"}, "74926": {"name": "CUNEIFORM SIGN EZEN SHESHIG TIMES HI"}, "74927": {"name": "CUNEIFORM SIGN EZEN SHESHIG TIMES IGI GUNU"}, "74928": {"name": "CUNEIFORM SIGN EZEN SHESHIG TIMES LA"}, "74929": {"name": "CUNEIFORM SIGN EZEN SHESHIG TIMES LAL"}, "74930": {"name": "CUNEIFORM SIGN EZEN SHESHIG TIMES ME"}, "74931": {"name": "CUNEIFORM SIGN EZEN SHESHIG TIMES MES"}, "74932": {"name": "CUNEIFORM SIGN EZEN SHESHIG TIMES SU"}, "74933": {"name": "CUNEIFORM SIGN EZEN TIMES SU"}, "74934": {"name": "CUNEIFORM SIGN GA2 TIMES BAHAR2"}, "74935": {"name": "CUNEIFORM SIGN GA2 TIMES DIM GUNU"}, "74936": {"name": "CUNEIFORM SIGN GA2 TIMES DUG TIMES IGI GUNU"}, "74937": {"name": "CUNEIFORM SIGN GA2 TIMES DUG TIMES KASKAL"}, "74938": {"name": "CUNEIFORM SIGN GA2 TIMES EREN"}, "74939": {"name": "CUNEIFORM SIGN GA2 TIMES GA"}, "74940": {"name": "CUNEIFORM SIGN GA2 TIMES GAR PLUS DI"}, "74941": {"name": "CUNEIFORM SIGN GA2 TIMES GAR PLUS NE"}, "74942": {"name": "CUNEIFORM SIGN GA2 TIMES HA PLUS A"}, "74943": {"name": "CUNEIFORM SIGN GA2 TIMES KUSHU2 PLUS KASKAL"}, "74944": {"name": "CUNEIFORM SIGN GA2 TIMES LAM"}, "74945": {"name": "CUNEIFORM SIGN GA2 TIMES LAM TIMES KUR"}, "74946": {"name": "CUNEIFORM SIGN GA2 TIMES LUH"}, "74947": {"name": "CUNEIFORM SIGN GA2 TIMES MUSH"}, "74948": {"name": "CUNEIFORM SIGN GA2 TIMES NE"}, "74949": {"name": "CUNEIFORM SIGN GA2 TIMES NE PLUS E2"}, "74950": {"name": "CUNEIFORM SIGN GA2 TIMES NE PLUS GI"}, "74951": {"name": "CUNEIFORM SIGN GA2 TIMES SHIM"}, "74952": {"name": "CUNEIFORM SIGN GA2 TIMES ZIZ2"}, "74953": {"name": "CUNEIFORM SIGN GABA ROTATED NINETY DEGREES"}, "74954": {"name": "CUNEIFORM SIGN GESHTIN TIMES U"}, "74955": {"name": "CUNEIFORM SIGN GISH TIMES GISH CROSSING GISH"}, "74956": {"name": "CUNEIFORM SIGN GU2 TIMES IGI GUNU"}, "74957": {"name": "CUNEIFORM SIGN GUD PLUS GISH TIMES TAK4"}, "74958": {"name": "CUNEIFORM SIGN HA TENU GUNU"}, "74959": {"name": "CUNEIFORM SIGN HI TIMES ASH OVER HI TIMES ASH"}, "74960": {"name": "CUNEIFORM SIGN KA TIMES BU"}, "74961": {"name": "CUNEIFORM SIGN KA TIMES KA"}, "74962": {"name": "CUNEIFORM SIGN KA TIMES U U U"}, "74963": {"name": "CUNEIFORM SIGN KA TIMES UR"}, "74964": {"name": "CUNEIFORM SIGN LAGAB TIMES ZU OVER ZU"}, "74965": {"name": "CUNEIFORM SIGN LAK-003"}, "74966": {"name": "CUNEIFORM SIGN LAK-021"}, "74967": {"name": "CUNEIFORM SIGN LAK-025"}, "74968": {"name": "CUNEIFORM SIGN LAK-030"}, "74969": {"name": "CUNEIFORM SIGN LAK-050"}, "74970": {"name": "CUNEIFORM SIGN LAK-051"}, "74971": {"name": "CUNEIFORM SIGN LAK-062"}, "74972": {"name": "CUNEIFORM SIGN LAK-079 OVER LAK-079 GUNU"}, "74973": {"name": "CUNEIFORM SIGN LAK-080"}, "74974": {"name": "CUNEIFORM SIGN LAK-081 OVER LAK-081"}, "74975": {"name": "CUNEIFORM SIGN LAK-092"}, "74976": {"name": "CUNEIFORM SIGN LAK-130"}, "74977": {"name": "CUNEIFORM SIGN LAK-142"}, "74978": {"name": "CUNEIFORM SIGN LAK-210"}, "74979": {"name": "CUNEIFORM SIGN LAK-219"}, "74980": {"name": "CUNEIFORM SIGN LAK-220"}, "74981": {"name": "CUNEIFORM SIGN LAK-225"}, "74982": {"name": "CUNEIFORM SIGN LAK-228"}, "74983": {"name": "CUNEIFORM SIGN LAK-238"}, "74984": {"name": "CUNEIFORM SIGN LAK-265"}, "74985": {"name": "CUNEIFORM SIGN LAK-266"}, "74986": {"name": "CUNEIFORM SIGN LAK-343"}, "74987": {"name": "CUNEIFORM SIGN LAK-347"}, "74988": {"name": "CUNEIFORM SIGN LAK-348"}, "74989": {"name": "CUNEIFORM SIGN LAK-383"}, "74990": {"name": "CUNEIFORM SIGN LAK-384"}, "74991": {"name": "CUNEIFORM SIGN LAK-390"}, "74992": {"name": "CUNEIFORM SIGN LAK-441"}, "74993": {"name": "CUNEIFORM SIGN LAK-449"}, "74994": {"name": "CUNEIFORM SIGN LAK-449 TIMES GU"}, "74995": {"name": "CUNEIFORM SIGN LAK-449 TIMES IGI"}, "74996": {"name": "CUNEIFORM SIGN LAK-449 TIMES PAP PLUS LU3"}, "74997": {"name": "CUNEIFORM SIGN LAK-449 TIMES PAP PLUS PAP PLUS LU3"}, "74998": {"name": "CUNEIFORM SIGN LAK-449 TIMES U2 PLUS BA"}, "74999": {"name": "CUNEIFORM SIGN LAK-450"}, "75000": {"name": "CUNEIFORM SIGN LAK-457"}, "75001": {"name": "CUNEIFORM SIGN LAK-470"}, "75002": {"name": "CUNEIFORM SIGN LAK-483"}, "75003": {"name": "CUNEIFORM SIGN LAK-490"}, "75004": {"name": "CUNEIFORM SIGN LAK-492"}, "75005": {"name": "CUNEIFORM SIGN LAK-493"}, "75006": {"name": "CUNEIFORM SIGN LAK-495"}, "75007": {"name": "CUNEIFORM SIGN LAK-550"}, "75008": {"name": "CUNEIFORM SIGN LAK-608"}, "75009": {"name": "CUNEIFORM SIGN LAK-617"}, "75010": {"name": "CUNEIFORM SIGN LAK-617 TIMES ASH"}, "75011": {"name": "CUNEIFORM SIGN LAK-617 TIMES BAD"}, "75012": {"name": "CUNEIFORM SIGN LAK-617 TIMES DUN3 GUNU GUNU"}, "75013": {"name": "CUNEIFORM SIGN LAK-617 TIMES KU3"}, "75014": {"name": "CUNEIFORM SIGN LAK-617 TIMES LA"}, "75015": {"name": "CUNEIFORM SIGN LAK-617 TIMES TAR"}, "75016": {"name": "CUNEIFORM SIGN LAK-617 TIMES TE"}, "75017": {"name": "CUNEIFORM SIGN LAK-617 TIMES U2"}, "75018": {"name": "CUNEIFORM SIGN LAK-617 TIMES UD"}, "75019": {"name": "CUNEIFORM SIGN LAK-617 TIMES URUDA"}, "75020": {"name": "CUNEIFORM SIGN LAK-636"}, "75021": {"name": "CUNEIFORM SIGN LAK-648"}, "75022": {"name": "CUNEIFORM SIGN LAK-648 TIMES DUB"}, "75023": {"name": "CUNEIFORM SIGN LAK-648 TIMES GA"}, "75024": {"name": "CUNEIFORM SIGN LAK-648 TIMES IGI"}, "75025": {"name": "CUNEIFORM SIGN LAK-648 TIMES IGI GUNU"}, "75026": {"name": "CUNEIFORM SIGN LAK-648 TIMES NI"}, "75027": {"name": "CUNEIFORM SIGN LAK-648 TIMES PAP PLUS PAP PLUS LU3"}, "75028": {"name": "CUNEIFORM SIGN LAK-648 TIMES SHESH PLUS KI"}, "75029": {"name": "CUNEIFORM SIGN LAK-648 TIMES UD"}, "75030": {"name": "CUNEIFORM SIGN LAK-648 TIMES URUDA"}, "75031": {"name": "CUNEIFORM SIGN LAK-724"}, "75032": {"name": "CUNEIFORM SIGN LAK-749"}, "75033": {"name": "CUNEIFORM SIGN LU2 GUNU TIMES ASH"}, "75034": {"name": "CUNEIFORM SIGN LU2 TIMES DISH"}, "75035": {"name": "CUNEIFORM SIGN LU2 TIMES HAL"}, "75036": {"name": "CUNEIFORM SIGN LU2 TIMES PAP"}, "75037": {"name": "CUNEIFORM SIGN LU2 TIMES PAP PLUS PAP PLUS LU3"}, "75038": {"name": "CUNEIFORM SIGN LU2 TIMES TAK4"}, "75039": {"name": "CUNEIFORM SIGN MI PLUS ZA7"}, "75040": {"name": "CUNEIFORM SIGN MUSH OVER MUSH TIMES GA"}, "75041": {"name": "CUNEIFORM SIGN MUSH OVER MUSH TIMES KAK"}, "75042": {"name": "CUNEIFORM SIGN NINDA2 TIMES DIM GUNU"}, "75043": {"name": "CUNEIFORM SIGN NINDA2 TIMES GISH"}, "75044": {"name": "CUNEIFORM SIGN NINDA2 TIMES GUL"}, "75045": {"name": "CUNEIFORM SIGN NINDA2 TIMES HI"}, "75046": {"name": "CUNEIFORM SIGN NINDA2 TIMES KESH2"}, "75047": {"name": "CUNEIFORM SIGN NINDA2 TIMES LAK-050"}, "75048": {"name": "CUNEIFORM SIGN NINDA2 TIMES MASH"}, "75049": {"name": "CUNEIFORM SIGN NINDA2 TIMES PAP PLUS PAP"}, "75050": {"name": "CUNEIFORM SIGN NINDA2 TIMES U"}, "75051": {"name": "CUNEIFORM SIGN NINDA2 TIMES U PLUS U"}, "75052": {"name": "CUNEIFORM SIGN NINDA2 TIMES URUDA"}, "75053": {"name": "CUNEIFORM SIGN SAG GUNU TIMES HA"}, "75054": {"name": "CUNEIFORM SIGN SAG TIMES EN"}, "75055": {"name": "CUNEIFORM SIGN SAG TIMES SHE AT LEFT"}, "75056": {"name": "CUNEIFORM SIGN SAG TIMES TAK4"}, "75057": {"name": "CUNEIFORM SIGN SHA6 TENU"}, "75058": {"name": "CUNEIFORM SIGN SHE OVER SHE"}, "75059": {"name": "CUNEIFORM SIGN SHE PLUS HUB2"}, "75060": {"name": "CUNEIFORM SIGN SHE PLUS NAM2"}, "75061": {"name": "CUNEIFORM SIGN SHE PLUS SAR"}, "75062": {"name": "CUNEIFORM SIGN SHU2 PLUS DUG TIMES NI"}, "75063": {"name": "CUNEIFORM SIGN SHU2 PLUS E2 TIMES AN"}, "75064": {"name": "CUNEIFORM SIGN SI TIMES TAK4"}, "75065": {"name": "CUNEIFORM SIGN TAK4 PLUS SAG"}, "75066": {"name": "CUNEIFORM SIGN TUM TIMES GAN2 TENU"}, "75067": {"name": "CUNEIFORM SIGN TUM TIMES THREE DISH"}, "75068": {"name": "CUNEIFORM SIGN UR2 INVERTED"}, "75069": {"name": "CUNEIFORM SIGN UR2 TIMES UD"}, "75070": {"name": "CUNEIFORM SIGN URU TIMES DARA3"}, "75071": {"name": "CUNEIFORM SIGN URU TIMES LAK-668"}, "75072": {"name": "CUNEIFORM SIGN URU TIMES LU3"}, "75073": {"name": "CUNEIFORM SIGN ZA7"}, "75074": {"name": "CUNEIFORM SIGN ZU OVER ZU PLUS SAR"}, "75075": {"name": "CUNEIFORM SIGN ZU5 TIMES THREE DISH TENU"}}, "age": "8.0", "fonts": ["Sans Cuneiform"]}