{"name": "Latin Extended-A", "start": 256, "end": 383, "coverage": "all", "cps": {"256": {"name": "LATIN CAPITAL LETTER A WITH MACRON", "fonts": ["Tinos", "Sans", "Sans Display", "Sans CJK SC", "Sans CJK TC", "Serif", "Sans CJK JP", "Arimo", "Sans Mono", "Sans CJK HK", "Sans CJK JP", "Serif Display", "Cousine", "Sans CJK KR"]}, "257": {"name": "LATIN SMALL LETTER A WITH MACRON", "fonts": ["Tinos", "Sans", "Sans Display", "Sans CJK SC", "Sans CJK TC", "Serif", "Sans CJK JP", "Arimo", "Sans Mono", "Sans CJK HK", "Sans CJK JP", "Serif Display", "Cousine", "Sans CJK KR"]}, "258": {"name": "LATIN CAPITAL LETTER A WITH BREVE", "fonts": ["Tinos", "Sans", "Sans Display", "Sans CJK SC", "Sans CJK TC", "Serif", "Sans CJK JP", "Arimo", "Sans Mono", "Sans CJK HK", "Sans CJK JP", "Serif Display", "Cousine", "Sans CJK KR"]}, "259": {"name": "LATIN SMALL LETTER A WITH BREVE", "fonts": ["Tinos", "Sans", "Sans Display", "Sans CJK SC", "Sans CJK TC", "Serif", "Sans CJK JP", "Arimo", "Sans Mono", "Sans CJK HK", "Sans CJK JP", "Serif Display", "Cousine", "Sans CJK KR"]}, "260": {"name": "LATIN CAPITAL LETTER A WITH OGONEK", "fonts": ["Tinos", "Sans", "Sans Display", "Serif", "Arimo", "Sans Mono", "Serif Display", "Cousine"]}, "261": {"name": "LATIN SMALL LETTER A WITH OGONEK", "fonts": ["Tinos", "Sans", "Sans Display", "Serif", "Arimo", "Sans Mono", "Serif Display", "Cousine"]}, "262": {"name": "LATIN CAPITAL LETTER C WITH ACUTE", "fonts": ["Tinos", "Sans", "Sans Display", "Serif", "Arimo", "Sans Mono", "Serif Display", "Cousine"]}, "263": {"name": "LATIN SMALL LETTER C WITH ACUTE", "fonts": ["Tinos", "Sans", "Sans Display", "Serif", "Arimo", "Sans Mono", "Serif Display", "Cousine"]}, "264": {"name": "LATIN CAPITAL LETTER C WITH CIRCUMFLEX", "fonts": ["Tinos", "Sans", "Sans Display", "Serif", "Arimo", "Sans Mono", "Serif Display", "Cousine"]}, "265": {"name": "LATIN SMALL LETTER C WITH CIRCUMFLEX", "fonts": ["Tinos", "Sans", "Sans Display", "Serif", "Arimo", "Sans Mono", "Serif Display", "Cousine"]}, "266": {"name": "LATIN CAPITAL LETTER C WITH DOT ABOVE", "fonts": ["Tinos", "Sans", "Sans Display", "Serif", "Arimo", "Sans Mono", "Serif Display", "Cousine"]}, "267": {"name": "LATIN SMALL LETTER C WITH DOT ABOVE", "fonts": ["Tinos", "Sans", "Sans Display", "Serif", "Arimo", "Sans Mono", "Serif Display", "Cousine"]}, "268": {"name": "LATIN CAPITAL LETTER C WITH CARON", "fonts": ["Tinos", "Sans", "Sans Display", "Serif", "Arimo", "Sans Mono", "Serif Display", "Cousine"]}, "269": {"name": "LATIN SMALL LETTER C WITH CARON", "fonts": ["Tinos", "Sans", "Sans Display", "Serif", "Arimo", "Sans Mono", "Serif Display", "Cousine"]}, "270": {"name": "LATIN CAPITAL LETTER D WITH CARON", "fonts": ["Tinos", "Sans", "Sans Display", "Serif", "Arimo", "Sans Mono", "Serif Display", "Cousine"]}, "271": {"name": "LATIN SMALL LETTER D WITH CARON", "fonts": ["Tinos", "Sans", "Sans Display", "Serif", "Arimo", "Sans Mono", "Serif Display", "Cousine"]}, "272": {"name": "LATIN CAPITAL LETTER D WITH STROKE", "fonts": ["Tinos", "Sans", "Sans Display", "Sans CJK SC", "Sans CJK TC", "Serif", "Sans CJK JP", "Arimo", "Sans Mono", "Sans CJK HK", "Sans CJK JP", "Serif Display", "Cousine", "Sans CJK KR"]}, "273": {"name": "LATIN SMALL LETTER D WITH STROKE", "fonts": ["Tinos", "Sans", "Sans Display", "Sans CJK SC", "Sans CJK TC", "Serif", "Sans CJK JP", "Arimo", "Sans Mono", "Sans CJK HK", "Sans CJK JP", "Serif Display", "Cousine", "Sans CJK KR"]}, "274": {"name": "LATIN CAPITAL LETTER E WITH MACRON", "fonts": ["Tinos", "Sans", "Sans Display", "Sans CJK SC", "Sans CJK TC", "Serif", "Sans CJK JP", "Arimo", "Sans Mono", "Sans CJK HK", "Sans CJK JP", "Serif Display", "Cousine", "Sans CJK KR"]}, "275": {"name": "LATIN SMALL LETTER E WITH MACRON", "fonts": ["Tinos", "Sans", "Sans Display", "Sans CJK SC", "Sans CJK TC", "Serif", "Sans CJK JP", "Arimo", "Sans Mono", "Sans CJK HK", "Sans CJK JP", "Serif Display", "Cousine", "Sans CJK KR"]}, "276": {"name": "LATIN CAPITAL LETTER E WITH BREVE", "fonts": ["Tinos", "Sans", "Sans Display", "Serif", "Arimo", "Sans Mono", "Serif Display", "Cousine"]}, "277": {"name": "LATIN SMALL LETTER E WITH BREVE", "fonts": ["Tinos", "Sans", "Sans Display", "Serif", "Arimo", "Sans Mono", "Serif Display", "Cousine"]}, "278": {"name": "LATIN CAPITAL LETTER E WITH DOT ABOVE", "fonts": ["Tinos", "Sans", "Sans Display", "Serif", "Arimo", "Sans Mono", "Serif Display", "Cousine"]}, "279": {"name": "LATIN SMALL LETTER E WITH DOT ABOVE", "fonts": ["Tinos", "Sans", "Sans Display", "Serif", "Arimo", "Sans Mono", "Serif Display", "Cousine"]}, "280": {"name": "LATIN CAPITAL LETTER E WITH OGONEK", "fonts": ["Tinos", "Sans", "Sans Display", "Serif", "Arimo", "Sans Mono", "Serif Display", "Cousine"]}, "281": {"name": "LATIN SMALL LETTER E WITH OGONEK", "fonts": ["Tinos", "Sans", "Sans Display", "Serif", "Arimo", "Sans Mono", "Serif Display", "Cousine"]}, "282": {"name": "LATIN CAPITAL LETTER E WITH CARON", "fonts": ["Tinos", "Sans", "Sans Display", "Sans CJK SC", "Sans CJK TC", "Serif", "Sans CJK JP", "Arimo", "Sans Mono", "Sans CJK HK", "Sans CJK JP", "Serif Display", "Cousine", "Sans CJK KR"]}, "283": {"name": "LATIN SMALL LETTER E WITH CARON", "fonts": ["Tinos", "Sans", "Sans Display", "Sans CJK SC", "Sans CJK TC", "Serif", "Sans CJK JP", "Arimo", "Sans Mono", "Sans CJK HK", "Sans CJK JP", "Serif Display", "Cousine", "Sans CJK KR"]}, "284": {"name": "LATIN CAPITAL LETTER G WITH CIRCUMFLEX", "fonts": ["Tinos", "Sans", "Sans Display", "Serif", "Arimo", "Sans Mono", "Serif Display", "Cousine"]}, "285": {"name": "LATIN SMALL LETTER G WITH CIRCUMFLEX", "fonts": ["Tinos", "Sans", "Sans Display", "Serif", "Arimo", "Sans Mono", "Serif Display", "Cousine"]}, "286": {"name": "LATIN CAPITAL LETTER G WITH BREVE", "fonts": ["Tinos", "Sans", "Sans Display", "Serif", "Arimo", "Sans Mono", "Serif Display", "Cousine"]}, "287": {"name": "LATIN SMALL LETTER G WITH BREVE", "fonts": ["Tinos", "Sans", "Sans Display", "Serif", "Arimo", "Sans Mono", "Serif Display", "Cousine"]}, "288": {"name": "LATIN CAPITAL LETTER G WITH DOT ABOVE", "fonts": ["Tinos", "Sans", "Sans Display", "Serif", "Arimo", "Sans Mono", "Serif Display", "Cousine"]}, "289": {"name": "LATIN SMALL LETTER G WITH DOT ABOVE", "fonts": ["Tinos", "Sans", "Sans Display", "Serif", "Arimo", "Sans Mono", "Serif Display", "Cousine"]}, "290": {"name": "LATIN CAPITAL LETTER G WITH CEDILLA", "fonts": ["Tinos", "Sans", "Sans Display", "Serif", "Arimo", "Sans Mono", "Serif Display", "Cousine"]}, "291": {"name": "LATIN SMALL LETTER G WITH CEDILLA", "fonts": ["Tinos", "Sans", "Sans Display", "Serif", "Arimo", "Sans Mono", "Serif Display", "Cousine"]}, "292": {"name": "LATIN CAPITAL LETTER H WITH CIRCUMFLEX", "fonts": ["Tinos", "Sans", "Sans Display", "Serif", "Arimo", "Sans Mono", "Serif Display", "Cousine"]}, "293": {"name": "LATIN SMALL LETTER H WITH CIRCUMFLEX", "fonts": ["Tinos", "Sans", "Sans Display", "Serif", "Arimo", "Sans Mono", "Serif Display", "Cousine"]}, "294": {"name": "LATIN CAPITAL LETTER H WITH STROKE", "fonts": ["Tinos", "Sans", "Sans Display", "Serif", "Arimo", "Sans Mono", "Serif Display", "Cousine"]}, "295": {"name": "LATIN SMALL LETTER H WITH STROKE", "fonts": ["Tinos", "Sans", "Sans Display", "Serif", "Arimo", "Sans Mono", "Serif Display", "Cousine"]}, "296": {"name": "LATIN CAPITAL LETTER I WITH TILDE", "fonts": ["Tinos", "Sans", "Sans Display", "Sans CJK SC", "Sans CJK TC", "Serif", "Sans CJK JP", "Arimo", "Sans Mono", "Sans CJK HK", "Sans CJK JP", "Serif Display", "Cousine", "Sans CJK KR"]}, "297": {"name": "LATIN SMALL LETTER I WITH TILDE", "fonts": ["Tinos", "Sans", "Sans Display", "Sans CJK SC", "Sans CJK TC", "Serif", "Sans CJK JP", "Arimo", "Sans Mono", "Sans CJK HK", "Sans CJK JP", "Serif Display", "Cousine", "Sans CJK KR"]}, "298": {"name": "LATIN CAPITAL LETTER I WITH MACRON", "fonts": ["Tinos", "Sans", "Sans Display", "Sans CJK SC", "Sans CJK TC", "Serif", "Sans CJK JP", "Arimo", "Sans Mono", "Sans CJK HK", "Sans CJK JP", "Serif Display", "Cousine", "Sans CJK KR"]}, "299": {"name": "LATIN SMALL LETTER I WITH MACRON", "fonts": ["Tinos", "Sans", "Sans Display", "Sans CJK SC", "Sans CJK TC", "Serif", "Sans CJK JP", "Arimo", "Sans Mono", "Sans CJK HK", "Sans CJK JP", "Serif Display", "Cousine", "Sans CJK KR"]}, "300": {"name": "LATIN CAPITAL LETTER I WITH BREVE", "fonts": ["Tinos", "Sans", "Sans Display", "Serif", "Arimo", "Sans Mono", "Serif Display", "Cousine"]}, "301": {"name": "LATIN SMALL LETTER I WITH BREVE", "fonts": ["Tinos", "Sans", "Sans Display", "Serif", "Arimo", "Sans Mono", "Serif Display", "Cousine"]}, "302": {"name": "LATIN CAPITAL LETTER I WITH OGONEK", "fonts": ["Tinos", "Sans", "Sans Display", "Serif", "Arimo", "Sans Mono", "Serif Display", "Cousine"]}, "303": {"name": "LATIN SMALL LETTER I WITH OGONEK", "fonts": ["Tinos", "Sans", "Sans Display", "Serif", "Arimo", "Sans Mono", "Serif Display", "Cousine"]}, "304": {"name": "LATIN CAPITAL LETTER I WITH DOT ABOVE", "fonts": ["Tinos", "Sans", "Sans Display", "Serif", "Arimo", "Sans Mono", "Serif Display", "Cousine"]}, "305": {"name": "LATIN SMALL LETTER DOTLESS I", "fonts": ["Tinos", "Sans", "Sans Display", "Serif", "Arimo", "Sans Mono", "Sans CanAborig", "Serif Display", "Cousine"]}, "306": {"name": "LATIN CAPITAL LIGATURE IJ", "fonts": ["Tinos", "Sans", "Sans Display", "Serif", "Arimo", "Sans Mono", "Serif Display", "Cousine"]}, "307": {"name": "LATIN SMALL LIGATURE IJ", "fonts": ["Tinos", "Sans", "Sans Display", "Serif", "Arimo", "Sans Mono", "Serif Display", "Cousine"]}, "308": {"name": "LATIN CAPITAL LETTER J WITH CIRCUMFLEX", "fonts": ["Tinos", "Sans", "Sans Display", "Serif", "Arimo", "Sans Mono", "Serif Display", "Cousine"]}, "309": {"name": "LATIN SMALL LETTER J WITH CIRCUMFLEX", "fonts": ["Tinos", "Sans", "Sans Display", "Serif", "Arimo", "Sans Mono", "Serif Display", "Cousine"]}, "310": {"name": "LATIN CAPITAL LETTER K WITH CEDILLA", "fonts": ["Tinos", "Sans", "Sans Display", "Serif", "Arimo", "Sans Mono", "Serif Display", "Cousine"]}, "311": {"name": "LATIN SMALL LETTER K WITH CEDILLA", "fonts": ["Tinos", "Sans", "Sans Display", "Serif", "Arimo", "Sans Mono", "Serif Display", "Cousine"]}, "312": {"name": "LATIN SMALL LETTER KRA", "fonts": ["Tinos", "Sans", "Sans Display", "Serif", "Arimo", "Sans Mono", "Serif Display", "Cousine"]}, "313": {"name": "LATIN CAPITAL LETTER L WITH ACUTE", "fonts": ["Tinos", "Sans", "Sans Display", "Serif", "Arimo", "Sans Mono", "Serif Display", "Cousine"]}, "314": {"name": "LATIN SMALL LETTER L WITH ACUTE", "fonts": ["Tinos", "Sans", "Sans Display", "Serif", "Arimo", "Sans Mono", "Serif Display", "Cousine"]}, "315": {"name": "LATIN CAPITAL LETTER L WITH CEDILLA", "fonts": ["Tinos", "Sans", "Sans Display", "Serif", "Arimo", "Sans Mono", "Serif Display", "Cousine"]}, "316": {"name": "LATIN SMALL LETTER L WITH CEDILLA", "fonts": ["Tinos", "Sans", "Sans Display", "Serif", "Arimo", "Sans Mono", "Serif Display", "Cousine"]}, "317": {"name": "LATIN CAPITAL LETTER L WITH CARON", "fonts": ["Tinos", "Sans", "Sans Display", "Serif", "Arimo", "Sans Mono", "Serif Display", "Cousine"]}, "318": {"name": "LATIN SMALL LETTER L WITH CARON", "fonts": ["Tinos", "Sans", "Sans Display", "Serif", "Arimo", "Sans Mono", "Serif Display", "Cousine"]}, "319": {"name": "LATIN CAPITAL LETTER L WITH MIDDLE DOT", "fonts": ["Tinos", "Sans", "Sans Display", "Serif", "Arimo", "Sans Mono", "Serif Display", "Cousine"]}, "320": {"name": "LATIN SMALL LETTER L WITH MIDDLE DOT", "fonts": ["Tinos", "Sans", "Sans Display", "Serif", "Arimo", "Sans Mono", "Serif Display", "Cousine"]}, "321": {"name": "LATIN CAPITAL LETTER L WITH STROKE", "fonts": ["Tinos", "Sans", "Sans Display", "Serif", "Arimo", "Sans Mono", "Serif Display", "Cousine"]}, "322": {"name": "LATIN SMALL LETTER L WITH STROKE", "fonts": ["Tinos", "Sans", "Sans Display", "Serif", "Arimo", "Sans Mono", "Serif Display", "Cousine"]}, "323": {"name": "LATIN CAPITAL LETTER N WITH ACUTE", "fonts": ["Tinos", "Sans", "Sans Display", "Sans CJK SC", "Sans CJK TC", "Serif", "Sans CJK JP", "Arimo", "Sans Mono", "Sans CJK HK", "Sans CJK JP", "Serif Display", "Cousine", "Sans CJK KR"]}, "324": {"name": "LATIN SMALL LETTER N WITH ACUTE", "fonts": ["Tinos", "Sans", "Sans Display", "Sans CJK SC", "Sans CJK TC", "Serif", "Sans CJK JP", "Arimo", "Sans Mono", "Sans CJK HK", "Sans CJK JP", "Serif Display", "Cousine", "Sans CJK KR"]}, "325": {"name": "LATIN CAPITAL LETTER N WITH CEDILLA", "fonts": ["Tinos", "Sans", "Sans Display", "Serif", "Arimo", "Sans Mono", "Serif Display", "Cousine"]}, "326": {"name": "LATIN SMALL LETTER N WITH CEDILLA", "fonts": ["Tinos", "Sans", "Sans Display", "Serif", "Arimo", "Sans Mono", "Serif Display", "Cousine"]}, "327": {"name": "LATIN CAPITAL LETTER N WITH CARON", "fonts": ["Tinos", "Sans", "Sans Display", "Sans CJK SC", "Sans CJK TC", "Serif", "Sans CJK JP", "Arimo", "Sans Mono", "Sans CJK HK", "Sans CJK JP", "Serif Display", "Cousine", "Sans CJK KR"]}, "328": {"name": "LATIN SMALL LETTER N WITH CARON", "fonts": ["Tinos", "Sans", "Sans Display", "Sans CJK SC", "Sans CJK TC", "Serif", "Sans CJK JP", "Arimo", "Sans Mono", "Sans CJK HK", "Sans CJK JP", "Serif Display", "Cousine", "Sans CJK KR"]}, "329": {"name": "LATIN SMALL LETTER N PRECEDED BY APOSTROPHE", "fonts": ["Tinos", "Sans", "Sans Display", "Serif", "Arimo", "Sans Mono", "Serif Display", "Cousine"]}, "330": {"name": "LATIN CAPITAL LETTER ENG", "fonts": ["Tinos", "Sans", "Sans Display", "Serif", "Arimo", "Sans Mono", "Serif Display", "Cousine"]}, "331": {"name": "LATIN SMALL LETTER ENG", "fonts": ["Tinos", "Sans", "Sans Display", "Serif", "Arimo", "Sans Mono", "Serif Display", "Cousine"]}, "332": {"name": "LATIN CAPITAL LETTER O WITH MACRON", "fonts": ["Tinos", "Sans", "Sans Display", "Sans CJK SC", "Sans CJK TC", "Serif", "Sans CJK JP", "Arimo", "Sans Mono", "Sans CJK HK", "Sans CJK JP", "Serif Display", "Cousine", "Sans CJK KR"]}, "333": {"name": "LATIN SMALL LETTER O WITH MACRON", "fonts": ["Tinos", "Sans", "Sans Display", "Sans CJK SC", "Sans CJK TC", "Serif", "Sans CJK JP", "Arimo", "Sans Mono", "Sans CJK HK", "Sans CJK JP", "Serif Display", "Cousine", "Sans CJK KR"]}, "334": {"name": "LATIN CAPITAL LETTER O WITH BREVE", "fonts": ["Tinos", "Sans", "Sans Display", "Sans CJK SC", "Sans CJK TC", "Serif", "Sans CJK JP", "Arimo", "Sans Mono", "Sans CJK HK", "Sans CJK JP", "Serif Display", "Cousine", "Sans CJK KR"]}, "335": {"name": "LATIN SMALL LETTER O WITH BREVE", "fonts": ["Tinos", "Sans", "Sans Display", "Sans CJK SC", "Sans CJK TC", "Serif", "Sans CJK JP", "Arimo", "Sans Mono", "Sans CJK HK", "Sans CJK JP", "Serif Display", "Cousine", "Sans CJK KR"]}, "336": {"name": "LATIN CAPITAL LETTER O WITH DOUBLE ACUTE", "fonts": ["Tinos", "Sans", "Sans Display", "Serif", "Arimo", "Sans Mono", "Serif Display", "Cousine"]}, "337": {"name": "LATIN SMALL LETTER O WITH DOUBLE ACUTE", "fonts": ["Tinos", "Sans", "Sans Display", "Serif", "Arimo", "Sans Mono", "Serif Display", "Cousine"]}, "338": {"name": "LATIN CAPITAL LIGATURE OE", "fonts": ["Tinos", "Sans", "Sans Display", "Sans CJK SC", "Sans CJK TC", "Serif", "Sans CJK JP", "Arimo", "Sans Mono", "Sans CJK HK", "Sans CJK JP", "Serif Display", "Cousine", "Sans CJK KR"]}, "339": {"name": "LATIN SMALL LIGATURE OE", "fonts": ["Tinos", "Sans", "Sans Display", "Sans CJK SC", "Sans CJK TC", "Serif", "Sans CJK JP", "Arimo", "Sans Mono", "Sans CJK HK", "Sans CJK JP", "Serif Display", "Cousine", "Sans CJK KR"]}, "340": {"name": "LATIN CAPITAL LETTER R WITH ACUTE", "fonts": ["Tinos", "Sans", "Sans Display", "Serif", "Arimo", "Sans Mono", "Serif Display", "Cousine"]}, "341": {"name": "LATIN SMALL LETTER R WITH ACUTE", "fonts": ["Tinos", "Sans", "Sans Display", "Serif", "Arimo", "Sans Mono", "Serif Display", "Cousine"]}, "342": {"name": "LATIN CAPITAL LETTER R WITH CEDILLA", "fonts": ["Tinos", "Sans", "Sans Display", "Serif", "Arimo", "Sans Mono", "Serif Display", "Cousine"]}, "343": {"name": "LATIN SMALL LETTER R WITH CEDILLA", "fonts": ["Tinos", "Sans", "Sans Display", "Serif", "Arimo", "Sans Mono", "Serif Display", "Cousine"]}, "344": {"name": "LATIN CAPITAL LETTER R WITH CARON", "fonts": ["Tinos", "Sans", "Sans Display", "Serif", "Arimo", "Sans Mono", "Serif Display", "Cousine"]}, "345": {"name": "LATIN SMALL LETTER R WITH CARON", "fonts": ["Tinos", "Sans", "Sans Display", "Serif", "Arimo", "Sans Mono", "Serif Display", "Cousine"]}, "346": {"name": "LATIN CAPITAL LETTER S WITH ACUTE", "fonts": ["Tinos", "Sans", "Sans Display", "Serif", "Arimo", "Sans Mono", "Serif Display", "Cousine"]}, "347": {"name": "LATIN SMALL LETTER S WITH ACUTE", "fonts": ["Tinos", "Sans", "Sans Display", "Serif", "Arimo", "Sans Mono", "Serif Display", "Cousine"]}, "348": {"name": "LATIN CAPITAL LETTER S WITH CIRCUMFLEX", "fonts": ["Tinos", "Sans", "Sans Display", "Serif", "Arimo", "Sans Mono", "Serif Display", "Cousine"]}, "349": {"name": "LATIN SMALL LETTER S WITH CIRCUMFLEX", "fonts": ["Tinos", "Sans", "Sans Display", "Serif", "Arimo", "Sans Mono", "Serif Display", "Cousine"]}, "350": {"name": "LATIN CAPITAL LETTER S WITH CEDILLA", "fonts": ["Tinos", "Sans", "Sans Display", "Serif", "Arimo", "Sans Mono", "Serif Display", "Cousine"]}, "351": {"name": "LATIN SMALL LETTER S WITH CEDILLA", "fonts": ["Tinos", "Sans", "Sans Display", "Serif", "Arimo", "Sans Mono", "Serif Display", "Cousine"]}, "352": {"name": "LATIN CAPITAL LETTER S WITH CARON", "fonts": ["Tinos", "Sans", "Sans Display", "Serif", "Arimo", "Sans Mono", "Serif Display", "Cousine"]}, "353": {"name": "LATIN SMALL LETTER S WITH CARON", "fonts": ["Tinos", "Sans", "Sans Display", "Serif", "Arimo", "Sans Mono", "Serif Display", "Cousine"]}, "354": {"name": "LATIN CAPITAL LETTER T WITH CEDILLA", "fonts": ["Tinos", "Sans", "Sans Display", "Serif", "Arimo", "Sans Mono", "Serif Display", "Cousine"]}, "355": {"name": "LATIN SMALL LETTER T WITH CEDILLA", "fonts": ["Tinos", "Sans", "Sans Display", "Serif", "Arimo", "Sans Mono", "Serif Display", "Cousine"]}, "356": {"name": "LATIN CAPITAL LETTER T WITH CARON", "fonts": ["Tinos", "Sans", "Sans Display", "Serif", "Arimo", "Sans Mono", "Serif Display", "Cousine"]}, "357": {"name": "LATIN SMALL LETTER T WITH CARON", "fonts": ["Tinos", "Sans", "Sans Display", "Serif", "Arimo", "Sans Mono", "Serif Display", "Cousine"]}, "358": {"name": "LATIN CAPITAL LETTER T WITH STROKE", "fonts": ["Tinos", "Sans", "Sans Display", "Serif", "Arimo", "Sans Mono", "Serif Display", "Cousine"]}, "359": {"name": "LATIN SMALL LETTER T WITH STROKE", "fonts": ["Tinos", "Sans", "Sans Display", "Serif", "Arimo", "Sans Mono", "Serif Display", "Cousine"]}, "360": {"name": "LATIN CAPITAL LETTER U WITH TILDE", "fonts": ["Tinos", "Sans", "Sans Display", "Sans CJK SC", "Sans CJK TC", "Serif", "Sans CJK JP", "Arimo", "Sans Mono", "Sans CJK HK", "Sans CJK JP", "Serif Display", "Cousine", "Sans CJK KR"]}, "361": {"name": "LATIN SMALL LETTER U WITH TILDE", "fonts": ["Tinos", "Sans", "Sans Display", "Sans CJK SC", "Sans CJK TC", "Serif", "Sans CJK JP", "Arimo", "Sans Mono", "Sans CJK HK", "Sans CJK JP", "Serif Display", "Cousine", "Sans CJK KR"]}, "362": {"name": "LATIN CAPITAL LETTER U WITH MACRON", "fonts": ["Tinos", "Sans", "Sans Display", "Sans CJK SC", "Sans CJK TC", "Serif", "Sans CJK JP", "Arimo", "Sans Mono", "Sans CJK HK", "Sans CJK JP", "Serif Display", "Cousine", "Sans CJK KR"]}, "363": {"name": "LATIN SMALL LETTER U WITH MACRON", "fonts": ["Tinos", "Sans", "Sans Display", "Sans CJK SC", "Sans CJK TC", "Serif", "Sans CJK JP", "Arimo", "Sans Mono", "Sans CJK HK", "Sans CJK JP", "Serif Display", "Cousine", "Sans CJK KR"]}, "364": {"name": "LATIN CAPITAL LETTER U WITH BREVE", "fonts": ["Tinos", "Sans", "Sans Display", "Sans CJK SC", "Sans CJK TC", "Serif", "Sans CJK JP", "Arimo", "Sans Mono", "Sans CJK HK", "Sans CJK JP", "Serif Display", "Cousine", "Sans CJK KR"]}, "365": {"name": "LATIN SMALL LETTER U WITH BREVE", "fonts": ["Tinos", "Sans", "Sans Display", "Sans CJK SC", "Sans CJK TC", "Serif", "Sans CJK JP", "Arimo", "Sans Mono", "Sans CJK HK", "Sans CJK JP", "Serif Display", "Cousine", "Sans CJK KR"]}, "366": {"name": "LATIN CAPITAL LETTER U WITH RING ABOVE", "fonts": ["Tinos", "Sans", "Sans Display", "Serif", "Arimo", "Sans Mono", "Serif Display", "Cousine"]}, "367": {"name": "LATIN SMALL LETTER U WITH RING ABOVE", "fonts": ["Tinos", "Sans", "Sans Display", "Serif", "Arimo", "Sans Mono", "Serif Display", "Cousine"]}, "368": {"name": "LATIN CAPITAL LETTER U WITH DOUBLE ACUTE", "fonts": ["Tinos", "Sans", "Sans Display", "Serif", "Arimo", "Sans Mono", "Serif Display", "Cousine"]}, "369": {"name": "LATIN SMALL LETTER U WITH DOUBLE ACUTE", "fonts": ["Tinos", "Sans", "Sans Display", "Serif", "Arimo", "Sans Mono", "Serif Display", "Cousine"]}, "370": {"name": "LATIN CAPITAL LETTER U WITH OGONEK", "fonts": ["Tinos", "Sans", "Sans Display", "Serif", "Arimo", "Sans Mono", "Serif Display", "Cousine"]}, "371": {"name": "LATIN SMALL LETTER U WITH OGONEK", "fonts": ["Tinos", "Sans", "Sans Display", "Serif", "Arimo", "Sans Mono", "Serif Display", "Cousine"]}, "372": {"name": "LATIN CAPITAL LETTER W WITH CIRCUMFLEX", "fonts": ["Tinos", "Sans", "Sans Display", "Serif", "Arimo", "Sans Mono", "Serif Display", "Cousine"]}, "373": {"name": "LATIN SMALL LETTER W WITH CIRCUMFLEX", "fonts": ["Tinos", "Sans", "Sans Display", "Serif", "Arimo", "Sans Mono", "Serif Display", "Cousine"]}, "374": {"name": "LATIN CAPITAL LETTER Y WITH CIRCUMFLEX", "fonts": ["Tinos", "Sans", "Sans Display", "Serif", "Arimo", "Sans Mono", "Serif Display", "Cousine"]}, "375": {"name": "LATIN SMALL LETTER Y WITH CIRCUMFLEX", "fonts": ["Tinos", "Sans", "Sans Display", "Serif", "Arimo", "Sans Mono", "Serif Display", "Cousine"]}, "376": {"name": "LATIN CAPITAL LETTER Y WITH DIAERESIS", "fonts": ["Tinos", "Sans", "Sans Display", "Serif", "Arimo", "Sans Mono", "Serif Display", "Cousine"]}, "377": {"name": "LATIN CAPITAL LETTER Z WITH ACUTE", "fonts": ["Tinos", "Sans", "Sans Display", "Serif", "Arimo", "Sans Mono", "Serif Display", "Cousine"]}, "378": {"name": "LATIN SMALL LETTER Z WITH ACUTE", "fonts": ["Tinos", "Sans", "Sans Display", "Serif", "Arimo", "Sans Mono", "Serif Display", "Cousine"]}, "379": {"name": "LATIN CAPITAL LETTER Z WITH DOT ABOVE", "fonts": ["Tinos", "Sans", "Sans Display", "Serif", "Arimo", "Sans Mono", "Serif Display", "Cousine"]}, "380": {"name": "LATIN SMALL LETTER Z WITH DOT ABOVE", "fonts": ["Tinos", "Sans", "Sans Display", "Serif", "Arimo", "Sans Mono", "Serif Display", "Cousine"]}, "381": {"name": "LATIN CAPITAL LETTER Z WITH CARON", "fonts": ["Tinos", "Sans", "Sans Display", "Serif", "Arimo", "Sans Mono", "Serif Display", "Cousine"]}, "382": {"name": "LATIN SMALL LETTER Z WITH CARON", "fonts": ["Tinos", "Sans", "Sans Display", "Serif", "Arimo", "Sans Mono", "Serif Display", "Cousine"]}, "383": {"name": "LATIN SMALL LETTER LONG S", "fonts": ["Tinos", "Sans", "Sans Display", "Serif", "Arimo", "Sans Mono", "Serif Display", "Cousine"]}}, "age": "1.1"}