{"name": "Latin Extended-A", "start": 256, "end": 383, "coverage": "all", "cps": {"256": {"name": "LATIN CAPITAL LETTER A WITH MACRON", "fonts": ["Sans", "Sans CJK HK", "Sans CJK JP", "Sans CJK KR", "Sans CJK SC", "Sans CJK TC", "Sans Display", "Sans Mono", "Serif", "Serif Display", "Arimo", "Cousine", "Tinos"]}, "257": {"name": "LATIN SMALL LETTER A WITH MACRON", "fonts": ["Sans", "Sans CJK HK", "Sans CJK JP", "Sans CJK KR", "Sans CJK SC", "Sans CJK TC", "Sans Display", "Sans Mono", "Serif", "Serif Display", "Arimo", "Cousine", "Tinos"]}, "258": {"name": "LATIN CAPITAL LETTER A WITH BREVE", "fonts": ["Sans", "Sans CJK HK", "Sans CJK JP", "Sans CJK KR", "Sans CJK SC", "Sans CJK TC", "Sans Display", "Sans Mono", "Serif", "Serif Display", "Arimo", "Cousine", "Tinos"]}, "259": {"name": "LATIN SMALL LETTER A WITH BREVE", "fonts": ["Sans", "Sans CJK HK", "Sans CJK JP", "Sans CJK KR", "Sans CJK SC", "Sans CJK TC", "Sans Display", "Sans Mono", "Serif", "Serif Display", "Arimo", "Cousine", "Tinos"]}, "260": {"name": "LATIN CAPITAL LETTER A WITH OGONEK", "fonts": ["Sans", "Sans Display", "Sans Mono", "Serif", "Serif Display", "Arimo", "Cousine", "Tinos"]}, "261": {"name": "LATIN SMALL LETTER A WITH OGONEK", "fonts": ["Sans", "Sans Display", "Sans Mono", "Serif", "Serif Display", "Arimo", "Cousine", "Tinos"]}, "262": {"name": "LATIN CAPITAL LETTER C WITH ACUTE", "fonts": ["Sans", "Sans Display", "Sans Mono", "Serif", "Serif Display", "Arimo", "Cousine", "Tinos"]}, "263": {"name": "LATIN SMALL LETTER C WITH ACUTE", "fonts": ["Sans", "Sans Display", "Sans Mono", "Serif", "Serif Display", "Arimo", "Cousine", "Tinos"]}, "264": {"name": "LATIN CAPITAL LETTER C WITH CIRCUMFLEX", "fonts": ["Sans", "Sans Display", "Sans Mono", "Serif", "Serif Display", "Arimo", "Cousine", "Tinos"]}, "265": {"name": "LATIN SMALL LETTER C WITH CIRCUMFLEX", "fonts": ["Sans", "Sans Display", "Sans Mono", "Serif", "Serif Display", "Arimo", "Cousine", "Tinos"]}, "266": {"name": "LATIN CAPITAL LETTER C WITH DOT ABOVE", "fonts": ["Sans", "Sans Display", "Sans Mono", "Serif", "Serif Display", "Arimo", "Cousine", "Tinos"]}, "267": {"name": "LATIN SMALL LETTER C WITH DOT ABOVE", "fonts": ["Sans", "Sans Display", "Sans Mono", "Serif", "Serif Display", "Arimo", "Cousine", "Tinos"]}, "268": {"name": "LATIN CAPITAL LETTER C WITH CARON", "fonts": ["Sans", "Sans Display", "Sans Mono", "Serif", "Serif Display", "Arimo", "Cousine", "Tinos"]}, "269": {"name": "LATIN SMALL LETTER C WITH CARON", "fonts": ["Sans", "Sans Display", "Sans Mono", "Serif", "Serif Display", "Arimo", "Cousine", "Tinos"]}, "270": {"name": "LATIN CAPITAL LETTER D WITH CARON", "fonts": ["Sans", "Sans Display", "Sans Mono", "Serif", "Serif Display", "Arimo", "Cousine", "Tinos"]}, "271": {"name": "LATIN SMALL LETTER D WITH CARON", "fonts": ["Sans", "Sans Display", "Sans Mono", "Serif", "Serif Display", "Arimo", "Cousine", "Tinos"]}, "272": {"name": "LATIN CAPITAL LETTER D WITH STROKE", "fonts": ["Sans", "Sans CJK HK", "Sans CJK JP", "Sans CJK KR", "Sans CJK SC", "Sans CJK TC", "Sans Display", "Sans Mono", "Serif", "Serif Display", "Arimo", "Cousine", "Tinos"]}, "273": {"name": "LATIN SMALL LETTER D WITH STROKE", "fonts": ["Sans", "Sans CJK HK", "Sans CJK JP", "Sans CJK KR", "Sans CJK SC", "Sans CJK TC", "Sans Display", "Sans Mono", "Serif", "Serif Display", "Arimo", "Cousine", "Tinos"]}, "274": {"name": "LATIN CAPITAL LETTER E WITH MACRON", "fonts": ["Sans", "Sans CJK HK", "Sans CJK JP", "Sans CJK KR", "Sans CJK SC", "Sans CJK TC", "Sans Display", "Sans Mono", "Serif", "Serif Display", "Arimo", "Cousine", "Tinos"]}, "275": {"name": "LATIN SMALL LETTER E WITH MACRON", "fonts": ["Sans", "Sans CJK HK", "Sans CJK JP", "Sans CJK KR", "Sans CJK SC", "Sans CJK TC", "Sans Display", "Sans Mono", "Serif", "Serif Display", "Arimo", "Cousine", "Tinos"]}, "276": {"name": "LATIN CAPITAL LETTER E WITH BREVE", "fonts": ["Sans", "Sans Display", "Sans Mono", "Serif", "Serif Display", "Arimo", "Cousine", "Tinos"]}, "277": {"name": "LATIN SMALL LETTER E WITH BREVE", "fonts": ["Sans", "Sans Display", "Sans Mono", "Serif", "Serif Display", "Arimo", "Cousine", "Tinos"]}, "278": {"name": "LATIN CAPITAL LETTER E WITH DOT ABOVE", "fonts": ["Sans", "Sans Display", "Sans Mono", "Serif", "Serif Display", "Arimo", "Cousine", "Tinos"]}, "279": {"name": "LATIN SMALL LETTER E WITH DOT ABOVE", "fonts": ["Sans", "Sans Display", "Sans Mono", "Serif", "Serif Display", "Arimo", "Cousine", "Tinos"]}, "280": {"name": "LATIN CAPITAL LETTER E WITH OGONEK", "fonts": ["Sans", "Sans Display", "Sans Mono", "Serif", "Serif Display", "Arimo", "Cousine", "Tinos"]}, "281": {"name": "LATIN SMALL LETTER E WITH OGONEK", "fonts": ["Sans", "Sans Display", "Sans Mono", "Serif", "Serif Display", "Arimo", "Cousine", "Tinos"]}, "282": {"name": "LATIN CAPITAL LETTER E WITH CARON", "fonts": ["Sans", "Sans CJK HK", "Sans CJK JP", "Sans CJK KR", "Sans CJK SC", "Sans CJK TC", "Sans Display", "Sans Mono", "Serif", "Serif Display", "Arimo", "Cousine", "Tinos"]}, "283": {"name": "LATIN SMALL LETTER E WITH CARON", "fonts": ["Sans", "Sans CJK HK", "Sans CJK JP", "Sans CJK KR", "Sans CJK SC", "Sans CJK TC", "Sans Display", "Sans Mono", "Serif", "Serif Display", "Arimo", "Cousine", "Tinos"]}, "284": {"name": "LATIN CAPITAL LETTER G WITH CIRCUMFLEX", "fonts": ["Sans", "Sans Display", "Sans Mono", "Serif", "Serif Display", "Arimo", "Cousine", "Tinos"]}, "285": {"name": "LATIN SMALL LETTER G WITH CIRCUMFLEX", "fonts": ["Sans", "Sans Display", "Sans Mono", "Serif", "Serif Display", "Arimo", "Cousine", "Tinos"]}, "286": {"name": "LATIN CAPITAL LETTER G WITH BREVE", "fonts": ["Sans", "Sans Display", "Sans Mono", "Serif", "Serif Display", "Arimo", "Cousine", "Tinos"]}, "287": {"name": "LATIN SMALL LETTER G WITH BREVE", "fonts": ["Sans", "Sans Display", "Sans Mono", "Serif", "Serif Display", "Arimo", "Cousine", "Tinos"]}, "288": {"name": "LATIN CAPITAL LETTER G WITH DOT ABOVE", "fonts": ["Sans", "Sans Display", "Sans Mono", "Serif", "Serif Display", "Arimo", "Cousine", "Tinos"]}, "289": {"name": "LATIN SMALL LETTER G WITH DOT ABOVE", "fonts": ["Sans", "Sans Display", "Sans Mono", "Serif", "Serif Display", "Arimo", "Cousine", "Tinos"]}, "290": {"name": "LATIN CAPITAL LETTER G WITH CEDILLA", "fonts": ["Sans", "Sans Display", "Sans Mono", "Serif", "Serif Display", "Arimo", "Cousine", "Tinos"]}, "291": {"name": "LATIN SMALL LETTER G WITH CEDILLA", "fonts": ["Sans", "Sans Display", "Sans Mono", "Serif", "Serif Display", "Arimo", "Cousine", "Tinos"]}, "292": {"name": "LATIN CAPITAL LETTER H WITH CIRCUMFLEX", "fonts": ["Sans", "Sans Display", "Sans Mono", "Serif", "Serif Display", "Arimo", "Cousine", "Tinos"]}, "293": {"name": "LATIN SMALL LETTER H WITH CIRCUMFLEX", "fonts": ["Sans", "Sans Display", "Sans Mono", "Serif", "Serif Display", "Arimo", "Cousine", "Tinos"]}, "294": {"name": "LATIN CAPITAL LETTER H WITH STROKE", "fonts": ["Sans", "Sans Display", "Sans Mono", "Serif", "Serif Display", "Arimo", "Cousine", "Tinos"]}, "295": {"name": "LATIN SMALL LETTER H WITH STROKE", "fonts": ["Sans", "Sans Display", "Sans Mono", "Serif", "Serif Display", "Arimo", "Cousine", "Tinos"]}, "296": {"name": "LATIN CAPITAL LETTER I WITH TILDE", "fonts": ["Sans", "Sans CJK HK", "Sans CJK JP", "Sans CJK KR", "Sans CJK SC", "Sans CJK TC", "Sans Display", "Sans Mono", "Serif", "Serif Display", "Arimo", "Cousine", "Tinos"]}, "297": {"name": "LATIN SMALL LETTER I WITH TILDE", "fonts": ["Sans", "Sans CJK HK", "Sans CJK JP", "Sans CJK KR", "Sans CJK SC", "Sans CJK TC", "Sans Display", "Sans Mono", "Serif", "Serif Display", "Arimo", "Cousine", "Tinos"]}, "298": {"name": "LATIN CAPITAL LETTER I WITH MACRON", "fonts": ["Sans", "Sans CJK HK", "Sans CJK JP", "Sans CJK KR", "Sans CJK SC", "Sans CJK TC", "Sans Display", "Sans Mono", "Serif", "Serif Display", "Arimo", "Cousine", "Tinos"]}, "299": {"name": "LATIN SMALL LETTER I WITH MACRON", "fonts": ["Sans", "Sans CJK HK", "Sans CJK JP", "Sans CJK KR", "Sans CJK SC", "Sans CJK TC", "Sans Display", "Sans Mono", "Serif", "Serif Display", "Arimo", "Cousine", "Tinos"]}, "300": {"name": "LATIN CAPITAL LETTER I WITH BREVE", "fonts": ["Sans", "Sans Display", "Sans Mono", "Serif", "Serif Display", "Arimo", "Cousine", "Tinos"]}, "301": {"name": "LATIN SMALL LETTER I WITH BREVE", "fonts": ["Sans", "Sans Display", "Sans Mono", "Serif", "Serif Display", "Arimo", "Cousine", "Tinos"]}, "302": {"name": "LATIN CAPITAL LETTER I WITH OGONEK", "fonts": ["Sans", "Sans Display", "Sans Mono", "Serif", "Serif Display", "Arimo", "Cousine", "Tinos"]}, "303": {"name": "LATIN SMALL LETTER I WITH OGONEK", "fonts": ["Sans", "Sans Display", "Sans Mono", "Serif", "Serif Display", "Arimo", "Cousine", "Tinos"]}, "304": {"name": "LATIN CAPITAL LETTER I WITH DOT ABOVE", "fonts": ["Sans", "Sans Display", "Sans Mono", "Serif", "Serif Display", "Arimo", "Cousine", "Tinos"]}, "305": {"name": "LATIN SMALL LETTER DOTLESS I", "fonts": ["Sans", "Sans CanAborig", "Sans Display", "Sans Mono", "Serif", "Serif Display", "Arimo", "Cousine", "Tinos"]}, "306": {"name": "LATIN CAPITAL LIGATURE IJ", "fonts": ["Sans", "Sans Display", "Sans Mono", "Serif", "Serif Display", "Arimo", "Cousine", "Tinos"]}, "307": {"name": "LATIN SMALL LIGATURE IJ", "fonts": ["Sans", "Sans Display", "Sans Mono", "Serif", "Serif Display", "Arimo", "Cousine", "Tinos"]}, "308": {"name": "LATIN CAPITAL LETTER J WITH CIRCUMFLEX", "fonts": ["Sans", "Sans Display", "Sans Mono", "Serif", "Serif Display", "Arimo", "Cousine", "Tinos"]}, "309": {"name": "LATIN SMALL LETTER J WITH CIRCUMFLEX", "fonts": ["Sans", "Sans Display", "Sans Mono", "Serif", "Serif Display", "Arimo", "Cousine", "Tinos"]}, "310": {"name": "LATIN CAPITAL LETTER K WITH CEDILLA", "fonts": ["Sans", "Sans Display", "Sans Mono", "Serif", "Serif Display", "Arimo", "Cousine", "Tinos"]}, "311": {"name": "LATIN SMALL LETTER K WITH CEDILLA", "fonts": ["Sans", "Sans Display", "Sans Mono", "Serif", "Serif Display", "Arimo", "Cousine", "Tinos"]}, "312": {"name": "LATIN SMALL LETTER KRA", "fonts": ["Sans", "Sans Display", "Sans Mono", "Serif", "Serif Display", "Arimo", "Cousine", "Tinos"]}, "313": {"name": "LATIN CAPITAL LETTER L WITH ACUTE", "fonts": ["Sans", "Sans Display", "Sans Mono", "Serif", "Serif Display", "Arimo", "Cousine", "Tinos"]}, "314": {"name": "LATIN SMALL LETTER L WITH ACUTE", "fonts": ["Sans", "Sans Display", "Sans Mono", "Serif", "Serif Display", "Arimo", "Cousine", "Tinos"]}, "315": {"name": "LATIN CAPITAL LETTER L WITH CEDILLA", "fonts": ["Sans", "Sans Display", "Sans Mono", "Serif", "Serif Display", "Arimo", "Cousine", "Tinos"]}, "316": {"name": "LATIN SMALL LETTER L WITH CEDILLA", "fonts": ["Sans", "Sans Display", "Sans Mono", "Serif", "Serif Display", "Arimo", "Cousine", "Tinos"]}, "317": {"name": "LATIN CAPITAL LETTER L WITH CARON", "fonts": ["Sans", "Sans Display", "Sans Mono", "Serif", "Serif Display", "Arimo", "Cousine", "Tinos"]}, "318": {"name": "LATIN SMALL LETTER L WITH CARON", "fonts": ["Sans", "Sans Display", "Sans Mono", "Serif", "Serif Display", "Arimo", "Cousine", "Tinos"]}, "319": {"name": "LATIN CAPITAL LETTER L WITH MIDDLE DOT", "fonts": ["Sans", "Sans Display", "Sans Mono", "Serif", "Serif Display", "Arimo", "Cousine", "Tinos"]}, "320": {"name": "LATIN SMALL LETTER L WITH MIDDLE DOT", "fonts": ["Sans", "Sans Display", "Sans Mono", "Serif", "Serif Display", "Arimo", "Cousine", "Tinos"]}, "321": {"name": "LATIN CAPITAL LETTER L WITH STROKE", "fonts": ["Sans", "Sans Display", "Sans Mono", "Serif", "Serif Display", "Arimo", "Cousine", "Tinos"]}, "322": {"name": "LATIN SMALL LETTER L WITH STROKE", "fonts": ["Sans", "Sans Display", "Sans Mono", "Serif", "Serif Display", "Arimo", "Cousine", "Tinos"]}, "323": {"name": "LATIN CAPITAL LETTER N WITH ACUTE", "fonts": ["Sans", "Sans CJK HK", "Sans CJK JP", "Sans CJK KR", "Sans CJK SC", "Sans CJK TC", "Sans Display", "Sans Mono", "Serif", "Serif Display", "Arimo", "Cousine", "Tinos"]}, "324": {"name": "LATIN SMALL LETTER N WITH ACUTE", "fonts": ["Sans", "Sans CJK HK", "Sans CJK JP", "Sans CJK KR", "Sans CJK SC", "Sans CJK TC", "Sans Display", "Sans Mono", "Serif", "Serif Display", "Arimo", "Cousine", "Tinos"]}, "325": {"name": "LATIN CAPITAL LETTER N WITH CEDILLA", "fonts": ["Sans", "Sans Display", "Sans Mono", "Serif", "Serif Display", "Arimo", "Cousine", "Tinos"]}, "326": {"name": "LATIN SMALL LETTER N WITH CEDILLA", "fonts": ["Sans", "Sans Display", "Sans Mono", "Serif", "Serif Display", "Arimo", "Cousine", "Tinos"]}, "327": {"name": "LATIN CAPITAL LETTER N WITH CARON", "fonts": ["Sans", "Sans CJK HK", "Sans CJK JP", "Sans CJK KR", "Sans CJK SC", "Sans CJK TC", "Sans Display", "Sans Mono", "Serif", "Serif Display", "Arimo", "Cousine", "Tinos"]}, "328": {"name": "LATIN SMALL LETTER N WITH CARON", "fonts": ["Sans", "Sans CJK HK", "Sans CJK JP", "Sans CJK KR", "Sans CJK SC", "Sans CJK TC", "Sans Display", "Sans Mono", "Serif", "Serif Display", "Arimo", "Cousine", "Tinos"]}, "329": {"name": "LATIN SMALL LETTER N PRECEDED BY APOSTROPHE", "fonts": ["Sans", "Sans Display", "Sans Mono", "Serif", "Serif Display", "Arimo", "Cousine", "Tinos"]}, "330": {"name": "LATIN CAPITAL LETTER ENG", "fonts": ["Sans", "Sans Display", "Sans Mono", "Serif", "Serif Display", "Arimo", "Cousine", "Tinos"]}, "331": {"name": "LATIN SMALL LETTER ENG", "fonts": ["Sans", "Sans Display", "Sans Mono", "Serif", "Serif Display", "Arimo", "Cousine", "Tinos"]}, "332": {"name": "LATIN CAPITAL LETTER O WITH MACRON", "fonts": ["Sans", "Sans CJK HK", "Sans CJK JP", "Sans CJK KR", "Sans CJK SC", "Sans CJK TC", "Sans Display", "Sans Mono", "Serif", "Serif Display", "Arimo", "Cousine", "Tinos"]}, "333": {"name": "LATIN SMALL LETTER O WITH MACRON", "fonts": ["Sans", "Sans CJK HK", "Sans CJK JP", "Sans CJK KR", "Sans CJK SC", "Sans CJK TC", "Sans Display", "Sans Mono", "Serif", "Serif Display", "Arimo", "Cousine", "Tinos"]}, "334": {"name": "LATIN CAPITAL LETTER O WITH BREVE", "fonts": ["Sans", "Sans CJK HK", "Sans CJK JP", "Sans CJK KR", "Sans CJK SC", "Sans CJK TC", "Sans Display", "Sans Mono", "Serif", "Serif Display", "Arimo", "Cousine", "Tinos"]}, "335": {"name": "LATIN SMALL LETTER O WITH BREVE", "fonts": ["Sans", "Sans CJK HK", "Sans CJK JP", "Sans CJK KR", "Sans CJK SC", "Sans CJK TC", "Sans Display", "Sans Mono", "Serif", "Serif Display", "Arimo", "Cousine", "Tinos"]}, "336": {"name": "LATIN CAPITAL LETTER O WITH DOUBLE ACUTE", "fonts": ["Sans", "Sans Display", "Sans Mono", "Serif", "Serif Display", "Arimo", "Cousine", "Tinos"]}, "337": {"name": "LATIN SMALL LETTER O WITH DOUBLE ACUTE", "fonts": ["Sans", "Sans Display", "Sans Mono", "Serif", "Serif Display", "Arimo", "Cousine", "Tinos"]}, "338": {"name": "LATIN CAPITAL LIGATURE OE", "fonts": ["Sans", "Sans CJK HK", "Sans CJK JP", "Sans CJK KR", "Sans CJK SC", "Sans CJK TC", "Sans Display", "Sans Mono", "Serif", "Serif Display", "Arimo", "Cousine", "Tinos"]}, "339": {"name": "LATIN SMALL LIGATURE OE", "fonts": ["Sans", "Sans CJK HK", "Sans CJK JP", "Sans CJK KR", "Sans CJK SC", "Sans CJK TC", "Sans Display", "Sans Mono", "Serif", "Serif Display", "Arimo", "Cousine", "Tinos"]}, "340": {"name": "LATIN CAPITAL LETTER R WITH ACUTE", "fonts": ["Sans", "Sans Display", "Sans Mono", "Serif", "Serif Display", "Arimo", "Cousine", "Tinos"]}, "341": {"name": "LATIN SMALL LETTER R WITH ACUTE", "fonts": ["Sans", "Sans Display", "Sans Mono", "Serif", "Serif Display", "Arimo", "Cousine", "Tinos"]}, "342": {"name": "LATIN CAPITAL LETTER R WITH CEDILLA", "fonts": ["Sans", "Sans Display", "Sans Mono", "Serif", "Serif Display", "Arimo", "Cousine", "Tinos"]}, "343": {"name": "LATIN SMALL LETTER R WITH CEDILLA", "fonts": ["Sans", "Sans Display", "Sans Mono", "Serif", "Serif Display", "Arimo", "Cousine", "Tinos"]}, "344": {"name": "LATIN CAPITAL LETTER R WITH CARON", "fonts": ["Sans", "Sans Display", "Sans Mono", "Serif", "Serif Display", "Arimo", "Cousine", "Tinos"]}, "345": {"name": "LATIN SMALL LETTER R WITH CARON", "fonts": ["Sans", "Sans Display", "Sans Mono", "Serif", "Serif Display", "Arimo", "Cousine", "Tinos"]}, "346": {"name": "LATIN CAPITAL LETTER S WITH ACUTE", "fonts": ["Sans", "Sans Display", "Sans Mono", "Serif", "Serif Display", "Arimo", "Cousine", "Tinos"]}, "347": {"name": "LATIN SMALL LETTER S WITH ACUTE", "fonts": ["Sans", "Sans Display", "Sans Mono", "Serif", "Serif Display", "Arimo", "Cousine", "Tinos"]}, "348": {"name": "LATIN CAPITAL LETTER S WITH CIRCUMFLEX", "fonts": ["Sans", "Sans Display", "Sans Mono", "Serif", "Serif Display", "Arimo", "Cousine", "Tinos"]}, "349": {"name": "LATIN SMALL LETTER S WITH CIRCUMFLEX", "fonts": ["Sans", "Sans Display", "Sans Mono", "Serif", "Serif Display", "Arimo", "Cousine", "Tinos"]}, "350": {"name": "LATIN CAPITAL LETTER S WITH CEDILLA", "fonts": ["Sans", "Sans Display", "Sans Mono", "Serif", "Serif Display", "Arimo", "Cousine", "Tinos"]}, "351": {"name": "LATIN SMALL LETTER S WITH CEDILLA", "fonts": ["Sans", "Sans Display", "Sans Mono", "Serif", "Serif Display", "Arimo", "Cousine", "Tinos"]}, "352": {"name": "LATIN CAPITAL LETTER S WITH CARON", "fonts": ["Sans", "Sans Display", "Sans Mono", "Serif", "Serif Display", "Arimo", "Cousine", "Tinos"]}, "353": {"name": "LATIN SMALL LETTER S WITH CARON", "fonts": ["Sans", "Sans Display", "Sans Mono", "Serif", "Serif Display", "Arimo", "Cousine", "Tinos"]}, "354": {"name": "LATIN CAPITAL LETTER T WITH CEDILLA", "fonts": ["Sans", "Sans Display", "Sans Mono", "Serif", "Serif Display", "Arimo", "Cousine", "Tinos"]}, "355": {"name": "LATIN SMALL LETTER T WITH CEDILLA", "fonts": ["Sans", "Sans Display", "Sans Mono", "Serif", "Serif Display", "Arimo", "Cousine", "Tinos"]}, "356": {"name": "LATIN CAPITAL LETTER T WITH CARON", "fonts": ["Sans", "Sans Display", "Sans Mono", "Serif", "Serif Display", "Arimo", "Cousine", "Tinos"]}, "357": {"name": "LATIN SMALL LETTER T WITH CARON", "fonts": ["Sans", "Sans Display", "Sans Mono", "Serif", "Serif Display", "Arimo", "Cousine", "Tinos"]}, "358": {"name": "LATIN CAPITAL LETTER T WITH STROKE", "fonts": ["Sans", "Sans Display", "Sans Mono", "Serif", "Serif Display", "Arimo", "Cousine", "Tinos"]}, "359": {"name": "LATIN SMALL LETTER T WITH STROKE", "fonts": ["Sans", "Sans Display", "Sans Mono", "Serif", "Serif Display", "Arimo", "Cousine", "Tinos"]}, "360": {"name": "LATIN CAPITAL LETTER U WITH TILDE", "fonts": ["Sans", "Sans CJK HK", "Sans CJK JP", "Sans CJK KR", "Sans CJK SC", "Sans CJK TC", "Sans Display", "Sans Mono", "Serif", "Serif Display", "Arimo", "Cousine", "Tinos"]}, "361": {"name": "LATIN SMALL LETTER U WITH TILDE", "fonts": ["Sans", "Sans CJK HK", "Sans CJK JP", "Sans CJK KR", "Sans CJK SC", "Sans CJK TC", "Sans Display", "Sans Mono", "Serif", "Serif Display", "Arimo", "Cousine", "Tinos"]}, "362": {"name": "LATIN CAPITAL LETTER U WITH MACRON", "fonts": ["Sans", "Sans CJK HK", "Sans CJK JP", "Sans CJK KR", "Sans CJK SC", "Sans CJK TC", "Sans Display", "Sans Mono", "Serif", "Serif Display", "Arimo", "Cousine", "Tinos"]}, "363": {"name": "LATIN SMALL LETTER U WITH MACRON", "fonts": ["Sans", "Sans CJK HK", "Sans CJK JP", "Sans CJK KR", "Sans CJK SC", "Sans CJK TC", "Sans Display", "Sans Mono", "Serif", "Serif Display", "Arimo", "Cousine", "Tinos"]}, "364": {"name": "LATIN CAPITAL LETTER U WITH BREVE", "fonts": ["Sans", "Sans CJK HK", "Sans CJK JP", "Sans CJK KR", "Sans CJK SC", "Sans CJK TC", "Sans Display", "Sans Mono", "Serif", "Serif Display", "Arimo", "Cousine", "Tinos"]}, "365": {"name": "LATIN SMALL LETTER U WITH BREVE", "fonts": ["Sans", "Sans CJK HK", "Sans CJK JP", "Sans CJK KR", "Sans CJK SC", "Sans CJK TC", "Sans Display", "Sans Mono", "Serif", "Serif Display", "Arimo", "Cousine", "Tinos"]}, "366": {"name": "LATIN CAPITAL LETTER U WITH RING ABOVE", "fonts": ["Sans", "Sans Display", "Sans Mono", "Serif", "Serif Display", "Arimo", "Cousine", "Tinos"]}, "367": {"name": "LATIN SMALL LETTER U WITH RING ABOVE", "fonts": ["Sans", "Sans Display", "Sans Mono", "Serif", "Serif Display", "Arimo", "Cousine", "Tinos"]}, "368": {"name": "LATIN CAPITAL LETTER U WITH DOUBLE ACUTE", "fonts": ["Sans", "Sans Display", "Sans Mono", "Serif", "Serif Display", "Arimo", "Cousine", "Tinos"]}, "369": {"name": "LATIN SMALL LETTER U WITH DOUBLE ACUTE", "fonts": ["Sans", "Sans Display", "Sans Mono", "Serif", "Serif Display", "Arimo", "Cousine", "Tinos"]}, "370": {"name": "LATIN CAPITAL LETTER U WITH OGONEK", "fonts": ["Sans", "Sans Display", "Sans Mono", "Serif", "Serif Display", "Arimo", "Cousine", "Tinos"]}, "371": {"name": "LATIN SMALL LETTER U WITH OGONEK", "fonts": ["Sans", "Sans Display", "Sans Mono", "Serif", "Serif Display", "Arimo", "Cousine", "Tinos"]}, "372": {"name": "LATIN CAPITAL LETTER W WITH CIRCUMFLEX", "fonts": ["Sans", "Sans Display", "Sans Mono", "Serif", "Serif Display", "Arimo", "Cousine", "Tinos"]}, "373": {"name": "LATIN SMALL LETTER W WITH CIRCUMFLEX", "fonts": ["Sans", "Sans Display", "Sans Mono", "Serif", "Serif Display", "Arimo", "Cousine", "Tinos"]}, "374": {"name": "LATIN CAPITAL LETTER Y WITH CIRCUMFLEX", "fonts": ["Sans", "Sans Display", "Sans Mono", "Serif", "Serif Display", "Arimo", "Cousine", "Tinos"]}, "375": {"name": "LATIN SMALL LETTER Y WITH CIRCUMFLEX", "fonts": ["Sans", "Sans Display", "Sans Mono", "Serif", "Serif Display", "Arimo", "Cousine", "Tinos"]}, "376": {"name": "LATIN CAPITAL LETTER Y WITH DIAERESIS", "fonts": ["Sans", "Sans Display", "Sans Mono", "Serif", "Serif Display", "Arimo", "Cousine", "Tinos"]}, "377": {"name": "LATIN CAPITAL LETTER Z WITH ACUTE", "fonts": ["Sans", "Sans Display", "Sans Mono", "Serif", "Serif Display", "Arimo", "Cousine", "Tinos"]}, "378": {"name": "LATIN SMALL LETTER Z WITH ACUTE", "fonts": ["Sans", "Sans Display", "Sans Mono", "Serif", "Serif Display", "Arimo", "Cousine", "Tinos"]}, "379": {"name": "LATIN CAPITAL LETTER Z WITH DOT ABOVE", "fonts": ["Sans", "Sans Display", "Sans Mono", "Serif", "Serif Display", "Arimo", "Cousine", "Tinos"]}, "380": {"name": "LATIN SMALL LETTER Z WITH DOT ABOVE", "fonts": ["Sans", "Sans Display", "Sans Mono", "Serif", "Serif Display", "Arimo", "Cousine", "Tinos"]}, "381": {"name": "LATIN CAPITAL LETTER Z WITH CARON", "fonts": ["Sans", "Sans Display", "Sans Mono", "Serif", "Serif Display", "Arimo", "Cousine", "Tinos"]}, "382": {"name": "LATIN SMALL LETTER Z WITH CARON", "fonts": ["Sans", "Sans Display", "Sans Mono", "Serif", "Serif Display", "Arimo", "Cousine", "Tinos"]}, "383": {"name": "LATIN SMALL LETTER LONG S", "fonts": ["Sans", "Sans Display", "Sans Mono", "Serif", "Serif Display", "Arimo", "Cousine", "Tinos"]}}, "age": "1.1"}