{"name": "General Punctuation", "start": 8192, "end": 8303, "coverage": "all", "cps": {"8192": {"age": "1.1", "name": "EN QUAD", "fonts": ["Sans", "Sans Math", "Sans Mono", "Serif", "Serif Display"]}, "8193": {"age": "1.1", "name": "EM QUAD", "fonts": ["Sans", "Sans Duployan", "Sans Math", "Sans Mono", "Serif", "Serif Display"]}, "8194": {"age": "1.1", "name": "EN SPACE", "fonts": ["Sans", "Sans CJK HK", "Sans CJK JP", "Sans CJK KR", "Sans CJK SC", "Sans CJK TC", "Sans Math", "Sans Mono", "Serif", "Serif Display", "Serif Tangut"]}, "8195": {"age": "1.1", "name": "EM SPACE", "fonts": ["Sans", "Sans CJK HK", "Sans CJK JP", "Sans CJK KR", "Sans CJK SC", "Sans CJK TC", "Sans Duployan", "Sans Math", "Sans Mono", "Serif", "Serif Display", "Serif Tangut"]}, "8196": {"age": "1.1", "name": "THREE-PER-EM SPACE", "fonts": ["Sans", "Sans Math", "Sans Mono", "Serif", "Serif Display"]}, "8197": {"age": "1.1", "name": "FOUR-PER-EM SPACE", "fonts": ["Sans", "Sans Math", "Sans Mono", "Serif", "Serif Display"]}, "8198": {"age": "1.1", "name": "SIX-PER-EM SPACE", "fonts": ["Sans", "Sans Math", "Sans Mono", "Serif", "Serif Display"]}, "8199": {"age": "1.1", "name": "FIGURE SPACE", "fonts": ["Sans", "Sans Math", "Sans Mono", "Serif", "Serif Display"]}, "8200": {"age": "1.1", "name": "PUNCTUATION SPACE", "fonts": ["Sans", "Sans Math", "Sans Mono", "Serif", "Serif Display"]}, "8201": {"age": "1.1", "name": "THIN SPACE", "fonts": ["Kufi Arabic", "Naskh Arabic", "Sans", "Sans Arabic", "Sans Math", "Sans Mono", "Serif", "Serif Display"]}, "8202": {"age": "1.1", "name": "HAIR SPACE", "fonts": ["Sans", "Sans Math", "Sans Mono", "Serif", "Serif Display"]}, "8203": {"age": "1.1", "name": "ZERO WIDTH SPACE", "fonts": ["Kufi Arabic", "Naskh Arabic", "Naskh Arabic UI", "Nastaliq Urdu", "Sans", "Sans AnatoHiero", "Sans Arabic", "Sans Balinese", "Sans Batak", "Sans Bengali", "Sans Bengali UI", "Sans Bhaiksuki", "Sans Brahmi", "Sans Buginese", "Sans Buhid", "Sans Devanagari", "Sans Devanagari UI", "Sans Gujarati", "Sans Gujarati UI", "Sans Gurmukhi", "Sans Gurmukhi UI", "Sans Hanunoo", "Sans Javanese", "Sans Kaithi", "Sans Kannada", "Sans Kannada UI", "Sans Kharoshthi", "Sans Khmer", "Sans Lao", "Sans Lao Looped", "Sans Lepcha", "Sans Limbu", "Sans Malayalam", "Sans Malayalam UI", "Sans Math", "Sans Meetei Mayek", "Sans Mono", "Sans Myanmar", "Sans Oriya", "Sans PhagsPa", "Sans Rejang", "Sans Saurashtra", "Sans SignWriting", "Sans Sinhala", "Sans Sinhala UI", "Sans Sundanese", "Sans Syloti Nagri", "Sans Tagalog", "Sans Tagbanwa", "Sans Tai Le", "Sans Tai Tham", "Sans Tai Viet", "Sans Tamil", "Sans Tamil UI", "Sans Telugu", "Sans Telugu UI", "Sans Thaana", "Sans Thai", "Sans Thai Looped Regular", "Serif", "Serif Balinese", "Serif Bengali", "Serif Devanagari", "Serif Display", "Serif Gujarati", "Serif Gurmukhi", "Serif Kannada", "Serif Khmer", "Serif Lao", "Serif Malayalam", "Serif Myanmar", "Serif Oriya", "Serif Sinhala", "Serif Tamil", "Serif Telugu", "Serif Thai", "Serif Tibetan"]}, "8204": {"age": "1.1", "name": "ZERO WIDTH NON-JOINER", "fonts": ["Kufi Arabic", "Naskh Arabic", "Naskh Arabic UI", "Nastaliq Urdu", "Rashi Hebrew", "Sans", "Sans Arabic", "Sans Avestan", "Sans Balinese", "Sans Batak", "Sans Bengali", "Sans Bengali UI", "Sans Brahmi", "Sans Buginese", "Sans Buhid", "Sans Chakma", "Sans Cham", "Sans Chorasmian", "Sans Devanagari", "Sans Devanagari UI", "Sans Duployan", "Sans EgyptHiero", "Sans Grantha", "Sans Gujarati", "Sans Gujarati UI", "Sans Gunjala Gondi", "Sans Gurmukhi", "Sans Gurmukhi UI", "Sans Hanifi Rohingya", "Sans Hanunoo", "Sans Hatran", "Sans Hebrew", "Sans Javanese", "Sans Kaithi", "Sans Kannada", "Sans Kannada UI", "Sans Kayah Li", "Sans Kharoshthi", "Sans Khmer", "Sans Khojki", "Sans Khudawadi", "Sans Lao", "Sans Lao Looped", "Sans Lepcha", "Sans Limbu", "Sans Mahajani", "Sans Malayalam", "Sans Malayalam UI", "Sans Mandaic", "Sans Manichaean", "Sans Meetei Mayek", "Sans Modi", "Sans Mongolian", "Sans Mono", "Sans Myanmar", "Sans NKo", "Sans NKo Unjoined", "Sans Nandinagari", "Sans New Tai Lue", "Sans Newa", "Sans Oriya", "Sans Pahawh Hmong", "Sans PhagsPa", "Sans PsaPahlavi", "Sans Rejang", "Sans Saurashtra", "Sans Sharada", "Sans Siddham", "Sans SignWriting", "Sans Sinhala", "Sans Sinhala UI", "Sans Sogdian", "Sans Sundanese", "Sans Syloti Nagri", "Sans Syriac", "Sans Syriac Eastern", "Sans Syriac Western", "Sans Tagalog", "Sans Tagbanwa", "Sans Tai Le", "Sans Tai Tham", "Sans Tai Viet", "Sans Takri", "Sans Tamil", "Sans Tamil UI", "Sans Telugu", "Sans Telugu UI", "Sans Thaana", "Sans Thai", "Sans Thai Looped Regular", "Sans Tifinagh", "Sans Tifinagh APT", "Sans Tifinagh Adrar", "Sans Tifinagh Agraw Imazighen", "Sans Tifinagh Ahaggar", "Sans Tifinagh Air", "Sans Tifinagh Azawagh", "Sans Tifinagh Ghat", "Sans Tifinagh Hawad", "Sans Tifinagh Rhissa Ixa", "Sans Tifinagh SIL", "Sans Tifinagh Tawellemmet", "Sans Tirhuta", "Sans WarangCiti", "Serif", "Serif Balinese", "Serif Bengali", "Serif Devanagari", "Serif Display", "Serif Dogra", "Serif Grantha", "Serif Gujarati", "Serif Gurmukhi", "Serif Hebrew", "Serif Kannada", "Serif Khmer", "Serif Khojki", "Serif Lao", "Serif Malayalam", "Serif Myanmar", "Serif Old Uyghur", "Serif Oriya", "Serif Sinhala", "Serif Tamil", "Serif Telugu", "Serif Thai", "Serif Tibetan"]}, "8205": {"age": "1.1", "name": "ZERO WIDTH JOINER", "fonts": ["Color Emoji", "Kufi Arabic", "Naskh Arabic", "Naskh Arabic UI", "Nastaliq Urdu", "Rashi Hebrew", "Sans", "Sans Arabic", "Sans Avestan", "Sans Balinese", "Sans Batak", "Sans Bengali", "Sans Bengali UI", "Sans Brahmi", "Sans Buginese", "Sans Buhid", "Sans Chakma", "Sans Cham", "Sans Devanagari", "Sans Devanagari UI", "Sans EgyptHiero", "Sans Grantha", "Sans Gujarati", "Sans Gujarati UI", "Sans Gunjala Gondi", "Sans Gurmukhi", "Sans Gurmukhi UI", "Sans Hanifi Rohingya", "Sans Hanunoo", "Sans Hebrew", "Sans Javanese", "Sans Kaithi", "Sans Kannada", "Sans Kannada UI", "Sans Kayah Li", "Sans Kharoshthi", "Sans Khmer", "Sans Khojki", "Sans Khudawadi", "Sans Lao", "Sans Lao Looped", "Sans Lepcha", "Sans Limbu", "Sans Mahajani", "Sans Malayalam", "Sans Malayalam UI", "Sans Mandaic", "Sans Manichaean", "Sans Meetei Mayek", "Sans Modi", "Sans Mongolian", "Sans Mono", "Sans Myanmar", "Sans NKo", "Sans NKo Unjoined", "Sans Nandinagari", "Sans New Tai Lue", "Sans Newa", "Sans Old Turkic", "Sans OldHung", "Sans Oriya", "Sans Pahawh Hmong", "Sans PhagsPa", "Sans PsaPahlavi", "Sans Rejang", "Sans Saurashtra", "Sans Sharada", "Sans Siddham", "Sans Sinhala", "Sans Sinhala UI", "Sans Sundanese", "Sans Syloti Nagri", "Sans Syriac", "Sans Syriac Eastern", "Sans Syriac Western", "Sans Tagalog", "Sans Tagbanwa", "Sans Tai Le", "Sans Tai Tham", "Sans Tai Viet", "Sans Takri", "Sans Tamil", "Sans Tamil UI", "Sans Telugu", "Sans Telugu UI", "Sans Thaana", "Sans Thai", "Sans Thai Looped Regular", "Sans Tifinagh", "Sans Tifinagh APT", "Sans Tifinagh Adrar", "Sans Tifinagh Agraw Imazighen", "Sans Tifinagh Ahaggar", "Sans Tifinagh Air", "Sans Tifinagh Azawagh", "Sans Tifinagh Ghat", "Sans Tifinagh Hawad", "Sans Tifinagh Rhissa Ixa", "Sans Tifinagh SIL", "Sans Tifinagh Tawellemmet", "Sans Tirhuta", "Sans WarangCiti", "Serif", "Serif Balinese", "Serif Bengali", "Serif Devanagari", "Serif Display", "Serif Dogra", "Serif Grantha", "Serif Gujarati", "Serif Gurmukhi", "Serif Hebrew", "Serif Kannada", "Serif Khmer", "Serif Khojki", "Serif Lao", "Serif Malayalam", "Serif Myanmar", "Serif Oriya", "Serif Sinhala", "Serif Tamil", "Serif Telugu", "Serif Thai", "Serif Tibetan"]}, "8206": {"age": "1.1", "name": "LEFT-TO-RIGHT MARK", "fonts": ["Kufi Arabic", "Naskh Arabic", "Naskh Arabic UI", "Nastaliq Urdu", "Rashi Hebrew", "Sans", "Sans Arabic", "Sans Hebrew", "Sans Mono", "Sans NKo", "Sans NKo Unjoined", "Sans PhagsPa", "Sans Syriac", "Sans Syriac Eastern", "Sans Syriac Western", "Sans Thaana", "Serif", "Serif Display", "Serif Hebrew"]}, "8207": {"age": "1.1", "name": "RIGHT-TO-LEFT MARK", "fonts": ["Kufi Arabic", "Naskh Arabic", "Naskh Arabic UI", "Nastaliq Urdu", "Rashi Hebrew", "Sans", "Sans Arabic", "Sans Hebrew", "Sans Mono", "Sans NKo", "Sans NKo Unjoined", "Sans PhagsPa", "Sans Syriac", "Sans Syriac Eastern", "Sans Syriac Western", "Sans Thaana", "Serif", "Serif Display", "Serif Hebrew"]}, "8208": {"age": "1.1", "name": "HYPHEN", "fonts": ["Naskh Arabic", "Naskh Arabic UI", "Nastaliq Urdu", "Sans", "Sans Arabic", "Sans Armenian", "Sans Bengali", "Sans Bengali UI", "Sans CJK HK", "Sans CJK JP", "Sans CJK KR", "Sans CJK SC", "Sans CJK TC", "Sans Coptic", "Sans Devanagari", "Sans Devanagari UI", "Sans Ethiopic", "Sans Georgian", "Sans Gujarati", "Sans Gujarati UI", "Sans Gurmukhi", "Sans Gurmukhi UI", "Sans Hebrew", "Sans Kaithi", "Sans Kannada", "Sans Kannada UI", "Sans Kayah Li", "Sans Kharoshthi", "Sans Khmer", "Sans Lao Looped", "Sans Lisu", "Sans Malayalam", "Sans Malayalam UI", "Sans Mono", "Sans Oriya", "Sans Sora Sompeng", "Sans Sundanese", "Sans Syloti Nagri", "Sans Tamil", "Sans Tamil UI", "Sans Telugu", "Sans Telugu UI", "Sans Thai", "Sans Thai Looped Regular", "Serif", "Serif Armenian", "Serif Bengali", "Serif Devanagari", "Serif Display", "Serif Ethiopic", "Serif Georgian", "Serif Gujarati", "Serif Gurmukhi", "Serif Hebrew", "Serif Kannada", "Serif Khmer", "Serif Khojki", "Serif Malayalam", "Serif Tamil", "Serif Telugu", "Serif Thai", "Serif Tibetan"]}, "8209": {"age": "1.1", "name": "NON-BREAKING HYPHEN", "fonts": ["Naskh Arabic", "Naskh Arabic UI", "Nastaliq Urdu", "Sans", "Sans Arabic", "Sans CJK HK", "Sans CJK JP", "Sans CJK KR", "Sans CJK SC", "Sans CJK TC", "Sans Mono", "Sans Syloti Nagri", "Serif", "Serif Display"]}, "8210": {"age": "1.1", "name": "FIGURE DASH", "fonts": ["Sans", "Sans CJK HK", "Sans CJK JP", "Sans CJK KR", "Sans CJK SC", "Sans CJK TC", "Sans Lao Looped", "Sans Mono", "Sans Thai Looped Regular", "Serif", "Serif Display"]}, "8211": {"age": "1.1", "name": "EN DASH", "fonts": ["Nastaliq Urdu", "Sans", "Sans Adlam", "Sans Adlam Unjoined", "Sans Bengali", "Sans Bengali UI", "Sans CJK HK", "Sans CJK JP", "Sans CJK KR", "Sans CJK SC", "Sans CJK TC", "Sans Chakma", "Sans Devanagari", "Sans Devanagari UI", "Sans Duployan", "Sans Gurmukhi", "Sans Gurmukhi UI", "Sans Kannada", "Sans Kannada UI", "Sans Khudawadi", "Sans Lao Looped", "Sans Malayalam", "Sans Malayalam UI", "Sans Mono", "Sans Oriya", "Sans Sinhala", "Sans Sinhala UI", "Sans Tamil", "Sans Tamil UI", "Sans Telugu", "Sans Telugu UI", "Sans Thai Looped Regular", "Serif", "Serif Bengali", "Serif Devanagari", "Serif Display", "Serif Gujarati", "Serif Gurmukhi", "Serif Kannada", "Serif Khojki", "Serif Malayalam", "Serif Oriya", "Serif Sinhala", "Serif Tamil", "Serif Telugu"]}, "8212": {"age": "1.1", "name": "EM DASH", "fonts": ["Nastaliq Urdu", "Sans", "Sans Adlam", "Sans Adlam Unjoined", "Sans Bengali", "Sans Bengali UI", "Sans CJK HK", "Sans CJK JP", "Sans CJK KR", "Sans CJK SC", "Sans CJK TC", "Sans Chakma", "Sans Devanagari", "Sans Devanagari UI", "Sans Gurmukhi", "Sans Gurmukhi UI", "Sans Kannada", "Sans Kannada UI", "Sans Khudawadi", "Sans Lao Looped", "Sans Malayalam", "Sans Malayalam UI", "Sans Mono", "Sans Oriya", "Sans Sinhala", "Sans Sinhala UI", "Sans Tamil", "Sans Tamil UI", "Sans Telugu", "Sans Telugu UI", "Sans Thai Looped Regular", "Serif", "Serif Bengali", "Serif Devanagari", "Serif Display", "Serif Gujarati", "Serif Gurmukhi", "Serif Kannada", "Serif Khojki", "Serif Malayalam", "Serif Oriya", "Serif Sinhala", "Serif Tamil", "Serif Telugu"]}, "8213": {"age": "1.1", "name": "HORIZONTAL BAR", "fonts": ["Sans", "Sans Adlam", "Sans Adlam Unjoined", "Sans CJK HK", "Sans CJK JP", "Sans CJK KR", "Sans CJK SC", "Sans CJK TC", "Sans Lao Looped", "Sans Mono", "Sans Thai Looped Regular", "Serif", "Serif Display"]}, "8214": {"age": "1.1", "name": "DOUBLE VERTICAL LINE", "fonts": ["Sans", "Sans CJK HK", "Sans CJK JP", "Sans CJK KR", "Sans CJK SC", "Sans CJK TC", "Sans Math", "Sans Mono", "Serif", "Serif Display"]}, "8215": {"age": "1.1", "name": "DOUBLE LOW LINE", "fonts": ["Sans", "Sans Mono", "Serif", "Serif Display"]}, "8216": {"age": "1.1", "name": "LEFT SINGLE QUOTATION MARK", "fonts": ["Nastaliq Urdu", "Sans", "Sans Adlam", "Sans Adlam Unjoined", "Sans Bengali", "Sans Bengali UI", "Sans CJK HK", "Sans CJK JP", "Sans CJK KR", "Sans CJK SC", "Sans CJK TC", "Sans Devanagari", "Sans Devanagari UI", "Sans Gunjala Gondi", "Sans Gurmukhi", "Sans Gurmukhi UI", "Sans Kannada", "Sans Kannada UI", "Sans Khmer", "Sans Lao Looped", "Sans Malayalam", "Sans Malayalam UI", "Sans Masaram Gondi", "Sans Math", "Sans Mongolian", "Sans Mono", "Sans Myanmar", "Sans Oriya", "Sans Sinhala", "Sans Sinhala UI", "Sans Tamil", "Sans Tamil UI", "Sans Telugu", "Sans Telugu UI", "Sans Thaana", "Sans Thai Looped Regular", "Serif", "Serif Bengali", "Serif Devanagari", "Serif Display", "Serif Gujarati", "Serif Gurmukhi", "Serif Kannada", "Serif Khmer", "Serif Khojki", "Serif Malayalam", "Serif Myanmar", "Serif Oriya", "Serif Sinhala", "Serif Tamil", "Serif Telugu"]}, "8217": {"age": "1.1", "name": "RIGHT SINGLE QUOTATION MARK", "fonts": ["Nastaliq Urdu", "Sans", "Sans Adlam", "Sans Adlam Unjoined", "Sans Armenian", "Sans Bengali", "Sans Bengali UI", "Sans CJK HK", "Sans CJK JP", "Sans CJK KR", "Sans CJK SC", "Sans CJK TC", "Sans Devanagari", "Sans Devanagari UI", "Sans Gunjala Gondi", "Sans Gurmukhi", "Sans Gurmukhi UI", "Sans Kannada", "Sans Kannada UI", "Sans Khmer", "Sans Lao Looped", "Sans Malayalam", "Sans Malayalam UI", "Sans Masaram Gondi", "Sans Math", "Sans Mongolian", "Sans Mono", "Sans Myanmar", "Sans Oriya", "Sans Sinhala", "Sans Sinhala UI", "Sans Tamil", "Sans Tamil UI", "Sans Telugu", "Sans Telugu UI", "Sans Thaana", "Sans Thai Looped Regular", "Serif", "Serif Armenian", "Serif Bengali", "Serif Devanagari", "Serif Display", "Serif Gujarati", "Serif Gurmukhi", "Serif Kannada", "Serif Khmer", "Serif Khojki", "Serif Malayalam", "Serif Myanmar", "Serif Oriya", "Serif Sinhala", "Serif Tamil", "Serif Telugu"]}, "8218": {"age": "1.1", "name": "SINGLE LOW-9 QUOTATION MARK", "fonts": ["Sans", "Sans Adlam", "Sans Adlam Unjoined", "Sans CJK HK", "Sans CJK JP", "Sans CJK KR", "Sans CJK SC", "Sans CJK TC", "Sans Mono", "Serif", "Serif Display"]}, "8219": {"age": "1.1", "name": "SINGLE HIGH-REVERSED-9 QUOTATION MARK", "fonts": ["Sans", "Sans Adlam", "Sans Adlam Unjoined", "Sans Mono", "Serif", "Serif Display"]}, "8220": {"age": "1.1", "name": "LEFT DOUBLE QUOTATION MARK", "fonts": ["Nastaliq Urdu", "Sans", "Sans Adlam", "Sans Adlam Unjoined", "Sans Bengali", "Sans Bengali UI", "Sans CJK HK", "Sans CJK JP", "Sans CJK KR", "Sans CJK SC", "Sans CJK TC", "Sans Devanagari", "Sans Devanagari UI", "Sans Duployan", "Sans Gunjala Gondi", "Sans Gurmukhi", "Sans Gurmukhi UI", "Sans Kannada", "Sans Kannada UI", "Sans Khmer", "Sans Lao Looped", "Sans Malayalam", "Sans Malayalam UI", "Sans Masaram Gondi", "Sans Math", "Sans Mongolian", "Sans Mono", "Sans Myanmar", "Sans Oriya", "Sans Sinhala", "Sans Sinhala UI", "Sans Tamil", "Sans Tamil UI", "Sans Telugu", "Sans Telugu UI", "Sans Thaana", "Sans Thai Looped Regular", "Sans Wancho", "Serif", "Serif Bengali", "Serif Devanagari", "Serif Display", "Serif Gujarati", "Serif Gurmukhi", "Serif Kannada", "Serif Khmer", "Serif Khojki", "Serif Malayalam", "Serif Myanmar", "Serif Oriya", "Serif Sinhala", "Serif Tamil", "Serif Telugu"]}, "8221": {"age": "1.1", "name": "RIGHT DOUBLE QUOTATION MARK", "fonts": ["Nastaliq Urdu", "Sans", "Sans Adlam", "Sans Adlam Unjoined", "Sans Bengali", "Sans Bengali UI", "Sans CJK HK", "Sans CJK JP", "Sans CJK KR", "Sans CJK SC", "Sans CJK TC", "Sans Devanagari", "Sans Devanagari UI", "Sans Duployan", "Sans Gunjala Gondi", "Sans Gurmukhi", "Sans Gurmukhi UI", "Sans Kannada", "Sans Kannada UI", "Sans Khmer", "Sans Lao Looped", "Sans Malayalam", "Sans Malayalam UI", "Sans Masaram Gondi", "Sans Math", "Sans Mongolian", "Sans Mono", "Sans Myanmar", "Sans Oriya", "Sans Sinhala", "Sans Sinhala UI", "Sans Tamil", "Sans Tamil UI", "Sans Telugu", "Sans Telugu UI", "Sans Thaana", "Sans Thai Looped Regular", "Sans Wancho", "Serif", "Serif Bengali", "Serif Devanagari", "Serif Display", "Serif Gujarati", "Serif Gurmukhi", "Serif Kannada", "Serif Khmer", "Serif Khojki", "Serif Malayalam", "Serif Myanmar", "Serif Oriya", "Serif Sinhala", "Serif Tamil", "Serif Telugu"]}, "8222": {"age": "1.1", "name": "DOUBLE LOW-9 QUOTATION MARK", "fonts": ["Sans", "Sans Adlam", "Sans Adlam Unjoined", "Sans CJK HK", "Sans CJK JP", "Sans CJK KR", "Sans CJK SC", "Sans CJK TC", "Sans Duployan", "Sans Mono", "Serif", "Serif Display"]}, "8223": {"age": "1.1", "name": "DOUBLE HIGH-REVERSED-9 QUOTATION MARK", "fonts": ["Sans", "Sans Mono", "Serif", "Serif Display"]}, "8224": {"age": "1.1", "name": "DAGGER", "fonts": ["Sans", "Sans Adlam", "Sans Adlam Unjoined", "Sans CJK HK", "Sans CJK JP", "Sans CJK KR", "Sans CJK SC", "Sans CJK TC", "Sans Math", "Sans Mono", "Serif", "Serif Display"]}, "8225": {"age": "1.1", "name": "DOUBLE DAGGER", "fonts": ["Sans", "Sans Adlam", "Sans Adlam Unjoined", "Sans CJK HK", "Sans CJK JP", "Sans CJK KR", "Sans CJK SC", "Sans CJK TC", "Sans Mono", "Serif", "Serif Display"]}, "8226": {"age": "1.1", "name": "BULLET", "fonts": ["Sans", "Sans Adlam", "Sans Adlam Unjoined", "Sans CJK HK", "Sans CJK JP", "Sans CJK KR", "Sans CJK SC", "Sans CJK TC", "Sans Lao Looped", "Sans Mono", "Sans Symbols 2", "Sans Thai Looped Regular", "Serif", "Serif Display"]}, "8227": {"age": "1.1", "name": "TRIANGULAR BULLET", "fonts": ["Sans", "Sans Mono", "Serif", "Serif Display"]}, "8228": {"age": "1.1", "name": "ONE DOT LEADER", "fonts": ["Sans", "Sans Mono", "Serif", "Serif Display"]}, "8229": {"age": "1.1", "name": "TWO DOT LEADER", "fonts": ["Nastaliq Urdu", "Sans", "Sans CJK HK", "Sans CJK JP", "Sans CJK KR", "Sans CJK SC", "Sans CJK TC", "Sans Mono", "Sans PhagsPa", "Serif", "Serif Display"]}, "8230": {"age": "1.1", "name": "HORIZONTAL ELLIPSIS", "fonts": ["Nastaliq Urdu", "Sans", "Sans Adlam", "Sans Adlam Unjoined", "Sans Bengali", "Sans Bengali UI", "Sans CJK HK", "Sans CJK JP", "Sans CJK KR", "Sans CJK SC", "Sans CJK TC", "Sans Devanagari", "Sans Devanagari UI", "Sans Duployan", "Sans Gunjala Gondi", "Sans Gurmukhi", "Sans Gurmukhi UI", "Sans Kannada", "Sans Kannada UI", "Sans Khmer", "Sans Lao Looped", "Sans Malayalam", "Sans Malayalam UI", "Sans Masaram Gondi", "Sans Math", "Sans Meroitic", "Sans Mono", "Sans Myanmar", "Sans Oriya", "Sans PhagsPa", "Sans Sinhala", "Sans Sinhala UI", "Sans Syriac", "Sans Syriac Eastern", "Sans Syriac Western", "Sans Tamil", "Sans Tamil UI", "Sans Telugu", "Sans Telugu UI", "Sans Thai Looped Regular", "Serif", "Serif Bengali", "Serif Devanagari", "Serif Display", "Serif Gujarati", "Serif Gurmukhi", "Serif Kannada", "Serif Khmer", "Serif Khojki", "Serif Malayalam", "Serif Myanmar", "Serif Oriya", "Serif Sinhala", "Serif Tamil", "Serif Telugu"]}, "8231": {"age": "1.1", "name": "HYPHENATION POINT", "fonts": ["Sans", "Sans CJK HK", "Sans CJK JP", "Sans CJK KR", "Sans CJK SC", "Sans CJK TC", "Sans Mono", "Serif", "Serif Display"]}, "8232": {"age": "1.1", "name": "LINE SEPARATOR", "fonts": ["Sans", "Sans Mono", "Serif", "Serif Display"]}, "8233": {"age": "1.1", "name": "PARAGRAPH SEPARATOR", "fonts": ["Sans", "Sans Mono", "Serif", "Serif Display"]}, "8234": {"age": "1.1", "name": "LEFT-TO-RIGHT EMBEDDING", "fonts": ["Sans", "Sans Mono", "Serif", "Serif Display"]}, "8235": {"age": "1.1", "name": "RIGHT-TO-LEFT EMBEDDING", "fonts": ["Sans", "Sans Mono", "Serif", "Serif Display"]}, "8236": {"age": "1.1", "name": "POP DIRECTIONAL FORMATTING", "fonts": ["Sans", "Sans Mono", "Serif", "Serif Display"]}, "8237": {"age": "1.1", "name": "LEFT-TO-RIGHT OVERRIDE", "fonts": ["Sans", "Sans Mono", "Serif", "Serif Display"]}, "8238": {"age": "1.1", "name": "RIGHT-TO-LEFT OVERRIDE", "fonts": ["Sans", "Sans Mono", "Sans Tifinagh", "Sans Tifinagh APT", "Sans Tifinagh Adrar", "Sans Tifinagh Agraw Imazighen", "Sans Tifinagh Ahaggar", "Sans Tifinagh Air", "Sans Tifinagh Azawagh", "Sans Tifinagh Ghat", "Sans Tifinagh Hawad", "Sans Tifinagh Rhissa Ixa", "Sans Tifinagh SIL", "Sans Tifinagh Tawellemmet", "Serif", "Serif Display"]}, "8239": {"age": "3.0", "name": "NARROW NO-BREAK SPACE", "fonts": ["Kufi Arabic", "Naskh Arabic", "Sans", "Sans Arabic", "Sans Canadian Aboriginal", "Sans Math", "Sans Mongolian", "Sans Mono", "Serif", "Serif Display"]}, "8240": {"age": "1.1", "name": "PER MILLE SIGN", "fonts": ["Sans", "Sans Adlam", "Sans Adlam Unjoined", "Sans CJK HK", "Sans CJK JP", "Sans CJK KR", "Sans CJK SC", "Sans CJK TC", "Sans Mono", "Serif", "Serif Display"]}, "8241": {"age": "1.1", "name": "PER TEN THOUSAND SIGN", "fonts": ["Sans", "Sans Mono", "Serif", "Serif Display"]}, "8242": {"age": "1.1", "name": "PRIME", "fonts": ["Sans", "Sans CJK HK", "Sans CJK JP", "Sans CJK KR", "Sans CJK SC", "Sans CJK TC", "Sans Math", "Sans Mono", "Serif", "Serif Display"]}, "8243": {"age": "1.1", "name": "DOUBLE PRIME", "fonts": ["Sans", "Sans CJK HK", "Sans CJK JP", "Sans CJK KR", "Sans CJK SC", "Sans CJK TC", "Sans Math", "Sans Mono", "Serif", "Serif Display"]}, "8244": {"age": "1.1", "name": "TRIPLE PRIME", "fonts": ["Sans", "Sans Math", "Sans Mono", "Serif", "Serif Display"]}, "8245": {"age": "1.1", "name": "REVERSED PRIME", "fonts": ["Sans", "Sans CJK HK", "Sans CJK JP", "Sans CJK KR", "Sans CJK SC", "Sans CJK TC", "Sans Math", "Sans Mono", "Serif", "Serif Display"]}, "8246": {"age": "1.1", "name": "REVERSED DOUBLE PRIME", "fonts": ["Sans", "Sans Math", "Sans Mono", "Serif", "Serif Display"]}, "8247": {"age": "1.1", "name": "REVERSED TRIPLE PRIME", "fonts": ["Sans", "Sans Math", "Sans Mono", "Serif", "Serif Display"]}, "8248": {"age": "1.1", "name": "CARET", "fonts": ["Sans", "Sans Mono", "Serif", "Serif Display"]}, "8249": {"age": "1.1", "name": "SINGLE LEFT-POINTING ANGLE QUOTATION MARK", "fonts": ["Nastaliq Urdu", "Sans", "Sans Adlam", "Sans Adlam Unjoined", "Sans CJK HK", "Sans CJK JP", "Sans CJK KR", "Sans CJK SC", "Sans CJK TC", "Sans Duployan", "Sans Lao Looped", "Sans Mono", "Sans Thai Looped Regular", "Serif", "Serif Display"]}, "8250": {"age": "1.1", "name": "SINGLE RIGHT-POINTING ANGLE QUOTATION MARK", "fonts": ["Nastaliq Urdu", "Sans", "Sans Adlam", "Sans Adlam Unjoined", "Sans CJK HK", "Sans CJK JP", "Sans CJK KR", "Sans CJK SC", "Sans CJK TC", "Sans Duployan", "Sans Lao Looped", "Sans Mono", "Sans Thai Looped Regular", "Serif", "Serif Display"]}, "8251": {"age": "1.1", "name": "REFERENCE MARK", "fonts": ["Sans", "Sans CJK HK", "Sans CJK JP", "Sans CJK KR", "Sans CJK SC", "Sans CJK TC", "Sans Mono", "Serif", "Serif Display"]}, "8252": {"age": "1.1", "name": "DOUBLE EXCLAMATION MARK", "fonts": ["Color Emoji", "Sans", "Sans CJK HK", "Sans CJK JP", "Sans CJK KR", "Sans CJK SC", "Sans CJK TC", "Sans Mono", "Serif", "Serif Display"]}, "8253": {"age": "1.1", "name": "INTERROBANG", "fonts": ["Sans", "Sans Mono", "Serif", "Serif Display"]}, "8254": {"age": "1.1", "name": "OVERLINE", "fonts": ["Sans", "Sans Mono", "Serif", "Serif Display"]}, "8255": {"age": "1.1", "name": "UNDERTIE", "fonts": ["Sans", "Sans Mono", "Serif", "Serif Display"]}, "8256": {"age": "1.1", "name": "CHARACTER TIE", "fonts": ["Sans", "Sans Mono", "Serif", "Serif Display"]}, "8257": {"age": "1.1", "name": "CARET INSERTION POINT", "fonts": ["Sans", "Sans Mono", "Serif", "Serif Display"]}, "8258": {"age": "1.1", "name": "ASTERISM", "fonts": ["Sans", "Sans CJK HK", "Sans CJK JP", "Sans CJK KR", "Sans CJK SC", "Sans CJK TC", "Sans Mono", "Serif", "Serif Display"]}, "8259": {"age": "1.1", "name": "HYPHEN BULLET", "fonts": ["Sans", "Sans Mono", "Serif", "Serif Display"]}, "8260": {"age": "1.1", "name": "FRACTION SLASH", "fonts": ["Sans", "Sans Duployan", "Sans Math", "Sans Mono", "Sans Syriac", "Sans Syriac Eastern", "Sans Syriac Western", "Serif", "Serif Display"]}, "8261": {"age": "1.1", "name": "LEFT SQUARE BRACKET WITH QUILL", "fonts": ["Sans", "Sans Mono", "Serif", "Serif Display"]}, "8262": {"age": "1.1", "name": "RIGHT SQUARE BRACKET WITH QUILL", "fonts": ["Sans", "Sans Mono", "Serif", "Serif Display"]}, "8263": {"age": "3.2", "name": "DOUBLE QUESTION MARK", "fonts": ["Sans", "Sans CJK HK", "Sans CJK JP", "Sans CJK KR", "Sans CJK SC", "Sans CJK TC", "Sans Mono", "Serif", "Serif Display"]}, "8264": {"age": "3.0", "name": "QUESTION EXCLAMATION MARK", "fonts": ["Sans", "Sans CJK HK", "Sans CJK JP", "Sans CJK KR", "Sans CJK SC", "Sans CJK TC", "Sans Mongolian", "Sans Mono", "Serif", "Serif Display"]}, "8265": {"age": "3.0", "name": "EXCLAMATION QUESTION MARK", "fonts": ["Color Emoji", "Sans", "Sans CJK HK", "Sans CJK JP", "Sans CJK KR", "Sans CJK SC", "Sans CJK TC", "Sans Mongolian", "Sans Mono", "Serif", "Serif Display"]}, "8266": {"age": "3.0", "name": "TIRONIAN SIGN ET", "fonts": ["Sans", "Sans Mono", "Serif", "Serif Display"]}, "8267": {"age": "3.0", "name": "REVERSED PILCROW SIGN", "fonts": ["Sans", "Sans Mono", "Serif", "Serif Display"]}, "8268": {"age": "3.0", "name": "BLACK LEFTWARDS BULLET", "fonts": ["Sans", "Sans Mono", "Serif", "Serif Display"]}, "8269": {"age": "3.0", "name": "BLACK RIGHTWARDS BULLET", "fonts": ["Sans", "Sans Mono", "Serif", "Serif Display"]}, "8270": {"age": "3.2", "name": "LOW ASTERISK", "fonts": ["Sans", "Sans Mono", "Serif", "Serif Display"]}, "8271": {"age": "3.2", "name": "REVERSED SEMICOLON", "fonts": ["Kufi Arabic", "Naskh Arabic", "Naskh Arabic UI", "Sans", "Sans Adlam", "Sans Adlam Unjoined", "Sans Arabic", "Sans Mono", "Serif", "Serif Display"]}, "8272": {"age": "3.2", "name": "CLOSE UP", "fonts": ["Sans", "Sans Mono", "Serif", "Serif Display"]}, "8273": {"age": "3.2", "name": "TWO ASTERISKS ALIGNED VERTICALLY", "fonts": ["Sans", "Sans CJK HK", "Sans CJK JP", "Sans CJK KR", "Sans CJK SC", "Sans CJK TC", "Sans Mono", "Serif", "Serif Display"]}, "8274": {"age": "3.2", "name": "COMMERCIAL MINUS SIGN", "fonts": ["Sans", "Sans Mono", "Serif", "Serif Display"]}, "8275": {"age": "4.0", "name": "SWUNG DASH", "fonts": ["Sans", "Sans Coptic", "Sans Mono", "Serif", "Serif Display"]}, "8276": {"age": "4.0", "name": "INVERTED UNDERTIE", "fonts": ["Sans", "Sans Mono", "Serif", "Serif Display"]}, "8277": {"age": "4.1", "name": "FLOWER PUNCTUATION MARK", "fonts": ["Sans", "Sans Mono", "Sans Syloti Nagri", "Serif", "Serif Display"]}, "8278": {"age": "4.1", "name": "THREE DOT PUNCTUATION", "fonts": ["Sans", "Sans Coptic", "Sans Mono", "Serif", "Serif Display"]}, "8279": {"age": "3.2", "name": "QUADRUPLE PRIME", "fonts": ["Sans", "Sans Math", "Sans Mono", "Serif", "Serif Display"]}, "8280": {"age": "4.1", "name": "FOUR DOT PUNCTUATION", "fonts": ["Sans", "Sans Coptic", "Sans Mono", "Serif", "Serif Display"]}, "8281": {"age": "4.1", "name": "FIVE DOT PUNCTUATION", "fonts": ["Sans", "Sans Coptic", "Sans Mono", "Serif", "Serif Display"]}, "8282": {"age": "4.1", "name": "TWO DOT PUNCTUATION", "fonts": ["Sans", "Sans Mono", "Serif", "Serif Display"]}, "8283": {"age": "4.1", "name": "FOUR DOT MARK", "fonts": ["Sans", "Sans Mono", "Serif", "Serif Display"]}, "8284": {"age": "4.1", "name": "DOTTED CROSS", "fonts": ["Sans", "Sans Mono", "Serif", "Serif Display"]}, "8285": {"age": "4.1", "name": "TRICOLON", "fonts": ["Sans", "Sans Meroitic", "Sans Mono", "Serif", "Serif Display"]}, "8286": {"age": "4.1", "name": "VERTICAL FOUR DOTS", "fonts": ["Sans", "Sans Mono", "Serif", "Serif Display"]}, "8287": {"age": "3.2", "name": "MEDIUM MATHEMATICAL SPACE", "fonts": ["Sans", "Sans Math", "Sans Mono", "Serif", "Serif Display"]}, "8288": {"age": "3.2", "name": "WORD JOINER", "fonts": ["Sans", "Sans Lao Looped", "Sans Mono", "Sans Thai Looped Regular", "Serif", "Serif Display"]}, "8289": {"age": "3.2", "name": "FUNCTION APPLICATION", "fonts": ["Sans", "Sans Mono", "Serif", "Serif Display"]}, "8290": {"age": "3.2", "name": "INVISIBLE TIMES", "fonts": ["Sans", "Sans Mono", "Serif", "Serif Display"]}, "8291": {"age": "3.2", "name": "INVISIBLE SEPARATOR", "fonts": ["Sans", "Sans Mono", "Serif", "Serif Display"]}, "8292": {"age": "5.1", "name": "INVISIBLE PLUS", "fonts": ["Sans", "Sans Mono", "Serif", "Serif Display"]}, "8294": {"age": "6.3", "name": "LEFT-TO-RIGHT ISOLATE", "fonts": ["Sans", "Sans Mono", "Serif", "Serif Display"]}, "8295": {"age": "6.3", "name": "RIGHT-TO-LEFT ISOLATE", "fonts": ["Sans", "Sans Mono", "Serif", "Serif Display"]}, "8296": {"age": "6.3", "name": "FIRST STRONG ISOLATE", "fonts": ["Sans", "Sans Mono", "Serif", "Serif Display"]}, "8297": {"age": "6.3", "name": "POP DIRECTIONAL ISOLATE", "fonts": ["Sans", "Sans Mono", "Serif", "Serif Display"]}, "8298": {"age": "1.1", "name": "INHIBIT SYMMETRIC SWAPPING", "fonts": ["Sans", "Sans Mono", "Serif", "Serif Display"]}, "8299": {"age": "1.1", "name": "ACTIVATE SYMMETRIC SWAPPING", "fonts": ["Sans", "Sans Mono", "Serif", "Serif Display"]}, "8300": {"age": "1.1", "name": "INHIBIT ARABIC FORM SHAPING", "fonts": ["Sans", "Sans Mono", "Serif", "Serif Display"]}, "8301": {"age": "1.1", "name": "ACTIVATE ARABIC FORM SHAPING", "fonts": ["Sans", "Sans Mono", "Serif", "Serif Display"]}, "8302": {"age": "1.1", "name": "NATIONAL DIGIT SHAPES", "fonts": ["Sans", "Sans Mono", "Serif", "Serif Display"]}, "8303": {"age": "1.1", "name": "NOMINAL DIGIT SHAPES", "fonts": ["Sans", "Sans Mono", "Serif", "Serif Display"]}}}