{"name": "Inscriptional Pahlavi", "start": 68448, "end": 68479, "coverage": "none", "cps": {"68448": {"name": "INSCRIPTIONAL PAHLAVI LETTER ALEPH"}, "68449": {"name": "INSCRIPTIONAL PAHLAVI LETTER BETH"}, "68450": {"name": "INSCRIPTIONAL PAHLAVI LETTER GIMEL"}, "68451": {"name": "INSCRIPTIONAL PAHLAVI LETTER DALETH"}, "68452": {"name": "INSCRIPTIONAL PAHLAVI LETTER HE"}, "68453": {"name": "INSCRIPTIONAL PAHLAVI LETTER WAW-AYIN-RESH"}, "68454": {"name": "INSCRIPTIONAL PAHLAVI LETTER ZAYIN"}, "68455": {"name": "INSCRIPTIONAL PAHLAVI LETTER HETH"}, "68456": {"name": "INSCRIPTIONAL PAHLAVI LETTER TETH"}, "68457": {"name": "INSCRIPTIONAL PAHLAVI LETTER YODH"}, "68458": {"name": "INSCRIPTIONAL PAHLAVI LETTER KAPH"}, "68459": {"name": "INSCRIPTIONAL PAHLAVI LETTER LAMEDH"}, "68460": {"name": "INSCRIPTIONAL PAHLAVI LETTER MEM-QOPH"}, "68461": {"name": "INSCRIPTIONAL PAHLAVI LETTER NUN"}, "68462": {"name": "INSCRIPTIONAL PAHLAVI LETTER SAMEKH"}, "68463": {"name": "INSCRIPTIONAL PAHLAVI LETTER PE"}, "68464": {"name": "INSCRIPTIONAL PAHLAVI LETTER SADHE"}, "68465": {"name": "INSCRIPTIONAL PAHLAVI LETTER SHIN"}, "68466": {"name": "INSCRIPTIONAL PAHLAVI LETTER TAW"}, "68472": {"name": "INSCRIPTIONAL PAHLAVI NUMBER ONE"}, "68473": {"name": "INSCRIPTIONAL PAHLAVI NUMBER TWO"}, "68474": {"name": "INSCRIPTIONAL PAHLAVI NUMBER THREE"}, "68475": {"name": "INSCRIPTIONAL PAHLAVI NUMBER FOUR"}, "68476": {"name": "INSCRIPTIONAL PAHLAVI NUMBER TEN"}, "68477": {"name": "INSCRIPTIONAL PAHLAVI NUMBER TWENTY"}, "68478": {"name": "INSCRIPTIONAL PAHLAVI NUMBER ONE HUNDRED"}, "68479": {"name": "INSCRIPTIONAL PAHLAVI NUMBER ONE THOUSAND"}}, "age": "5.2"}