{"name": "Basic Latin", "start": 0, "end": 127, "coverage": "all", "cps": {"0": {"name": "<control>", "special": true}, "1": {"name": "<control>", "special": true}, "2": {"name": "<control>", "special": true}, "3": {"name": "<control>", "special": true}, "4": {"name": "<control>", "special": true}, "5": {"name": "<control>", "special": true}, "6": {"name": "<control>", "special": true}, "7": {"name": "<control>", "special": true}, "8": {"name": "<control>", "special": true}, "9": {"name": "<control>", "special": true}, "10": {"name": "<control>", "special": true}, "11": {"name": "<control>", "special": true}, "12": {"name": "<control>", "special": true}, "13": {"name": "<control>", "special": true}, "14": {"name": "<control>", "special": true}, "15": {"name": "<control>", "special": true}, "16": {"name": "<control>", "special": true}, "17": {"name": "<control>", "special": true}, "18": {"name": "<control>", "special": true}, "19": {"name": "<control>", "special": true}, "20": {"name": "<control>", "special": true}, "21": {"name": "<control>", "special": true}, "22": {"name": "<control>", "special": true}, "23": {"name": "<control>", "special": true}, "24": {"name": "<control>", "special": true}, "25": {"name": "<control>", "special": true}, "26": {"name": "<control>", "special": true}, "27": {"name": "<control>", "special": true}, "28": {"name": "<control>", "special": true}, "29": {"name": "<control>", "special": true}, "30": {"name": "<control>", "special": true}, "31": {"name": "<control>", "special": true}, "32": {"name": "SPACE", "special": true}, "33": {"name": "EXCLAMATION MARK", "fonts": ["Looped Lao Regular", "Looped Lao UI Regular", "Looped Thai Regular", "Looped Thai UI Regular", "Naskh Arabic", "Naskh Arabic UI", "Nastaliq Urdu", "NotoSerifTamilSlanted", "Sans", "Sans Adlam", "Sans Adlam Unjoined", "Sans Arabic", "Sans Arabic UI", "Sans Bengali", "Sans Bengali UI", "Sans CJK HK", "Sans CJK JP", "Sans CJK KR", "Sans CJK SC", "Sans CJK TC", "Sans Chakma", "Sans Cham", "Sans Devanagari", "Sans Devanagari UI", "Sans Display", "Sans Gujarati", "Sans Gujarati UI", "Sans Gunjala Gondi", "Sans Gurmukhi", "Sans Gurmukhi UI", "Sans Kannada", "Sans Kannada UI", "Sans Khmer", "Sans Khmer UI", "Sans Malayalam", "Sans Malayalam UI", "Sans Masaram Gondi", "Sans Math", "Sans Mongolian", "Sans Mono", "Sans Oriya", "Sans Oriya UI", "Sans Sinhala", "Sans Sinhala UI", "Sans Syriac", "Sans Tamil", "Sans Tamil UI", "Sans Telugu", "Sans Telugu UI", "Sans Thaana", "Sans Vithkuqi", "Serif", "Serif Bengali", "Serif Devanagari", "Serif Display", "Serif Gujarati", "Serif Gurmukhi", "Serif Kannada", "Serif Khmer", "Serif Khojki", "Serif Malayalam", "Serif Oriya", "Serif Sinhala", "Serif Tamil", "Serif Tangut", "Serif Telugu", "Serif Vithkuqi", "Arimo", "Cousine", "Tinos"]}, "34": {"name": "QUOTATION MARK", "fonts": ["Looped Lao Regular", "Looped Lao UI Regular", "Looped Thai Regular", "Looped Thai UI Regular", "NotoSerifTamilSlanted", "Sans", "Sans Adlam", "Sans Adlam Unjoined", "Sans Bengali", "Sans Bengali UI", "Sans CJK HK", "Sans CJK JP", "Sans CJK KR", "Sans CJK SC", "Sans CJK TC", "Sans Cham", "Sans Devanagari", "Sans Devanagari UI", "Sans Display", "Sans Gujarati", "Sans Gujarati UI", "Sans Gurmukhi", "Sans Gurmukhi UI", "Sans Kannada", "Sans Kannada UI", "Sans Khmer", "Sans Khmer UI", "Sans Malayalam", "Sans Malayalam UI", "Sans Masaram Gondi", "Sans Math", "Sans Mongolian", "Sans Mono", "Sans Oriya", "Sans Oriya UI", "Sans Sinhala", "Sans Sinhala UI", "Sans Tamil", "Sans Tamil UI", "Sans Telugu", "Sans Telugu UI", "Sans Vithkuqi", "Sans Wancho", "Serif", "Serif Bengali", "Serif Devanagari", "Serif Display", "Serif Gujarati", "Serif Gurmukhi", "Serif Kannada", "Serif Khmer", "Serif Khojki", "Serif Malayalam", "Serif Oriya", "Serif Sinhala", "Serif Tamil", "Serif Tangut", "Serif Telugu", "Serif Vithkuqi", "Arimo", "Cousine", "Tinos"]}, "35": {"name": "NUMBER SIGN", "fonts": ["Color Emoji", "NotoSerifTamilSlanted", "Sans", "Sans Adlam", "Sans Adlam Unjoined", "Sans Bengali", "Sans Bengali UI", "Sans CJK HK", "Sans CJK JP", "Sans CJK KR", "Sans CJK SC", "Sans CJK TC", "Sans Devanagari", "Sans Devanagari UI", "Sans Display", "Sans Gujarati", "Sans Gujarati UI", "Sans Gurmukhi", "Sans Gurmukhi UI", "Sans Kannada", "Sans Kannada UI", "Sans Malayalam", "Sans Malayalam UI", "Sans Math", "Sans Mono", "Sans Oriya", "Sans Oriya UI", "Sans Sinhala", "Sans Sinhala UI", "Sans Symbols2", "Sans Tamil", "Sans Tamil UI", "Sans Telugu", "Sans Telugu UI", "Serif", "Serif Bengali", "Serif Devanagari", "Serif Display", "Serif Gujarati", "Serif Gurmukhi", "Serif Kannada", "Serif Khojki", "Serif Malayalam", "Serif Oriya", "Serif Sinhala", "Serif Tamil", "Serif Tangut", "Serif Telugu", "Arimo", "Cousine", "Tinos"]}, "36": {"name": "DOLLAR SIGN", "fonts": ["Sans", "Sans Adlam", "Sans Adlam Unjoined", "Sans CJK HK", "Sans CJK JP", "Sans CJK KR", "Sans CJK SC", "Sans CJK TC", "Sans Display", "Sans Math", "Sans Mono", "Serif", "Serif Display", "Serif Tangut", "Arimo", "Cousine", "Tinos"]}, "37": {"name": "PERCENT SIGN", "fonts": ["Looped Thai Regular", "Looped Thai UI Regular", "NotoSerifTamilSlanted", "Sans", "Sans Adlam", "Sans Adlam Unjoined", "Sans Bengali", "Sans Bengali UI", "Sans CJK HK", "Sans CJK JP", "Sans CJK KR", "Sans CJK SC", "Sans CJK TC", "Sans Devanagari", "Sans Devanagari UI", "Sans Display", "Sans Gujarati", "Sans Gujarati UI", "Sans Gunjala Gondi", "Sans Gurmukhi", "Sans Gurmukhi UI", "Sans Kannada", "Sans Kannada UI", "Sans Malayalam", "Sans Malayalam UI", "Sans Masaram Gondi", "Sans Math", "Sans Mono", "Sans Oriya", "Sans Oriya UI", "Sans Sinhala", "Sans Sinhala UI", "Sans Tamil", "Sans Tamil UI", "Sans Telugu", "Sans Telugu UI", "Serif", "Serif Bengali", "Serif Devanagari", "Serif Display", "Serif Gujarati", "Serif Gurmukhi", "Serif Kannada", "Serif Khojki", "Serif Malayalam", "Serif Oriya", "Serif Sinhala", "Serif Tamil", "Serif Tangut", "Serif Telugu", "Arimo", "Cousine", "Tinos"]}, "38": {"name": "AMPERSAND", "fonts": ["Looped Lao Regular", "Looped Lao UI Regular", "Looped Thai Regular", "Looped Thai UI Regular", "Sans", "Sans Adlam", "Sans Adlam Unjoined", "Sans CJK HK", "Sans CJK JP", "Sans CJK KR", "Sans CJK SC", "Sans CJK TC", "Sans Display", "Sans Math", "Sans Mono", "Serif", "Serif Display", "Serif Tangut", "Arimo", "Cousine", "Tinos"]}, "39": {"name": "APOSTROPHE", "fonts": ["Looped Lao Regular", "Looped Lao UI Regular", "Looped Thai Regular", "Looped Thai UI Regular", "NotoSerifTamilSlanted", "Sans", "Sans Adlam", "Sans Adlam Unjoined", "Sans Bengali", "Sans Bengali UI", "Sans CJK HK", "Sans CJK JP", "Sans CJK KR", "Sans CJK SC", "Sans CJK TC", "Sans Cham", "Sans Devanagari", "Sans Devanagari UI", "Sans Display", "Sans Gujarati", "Sans Gujarati UI", "Sans Gunjala Gondi", "Sans Gurmukhi", "Sans Gurmukhi UI", "Sans Kannada", "Sans Kannada UI", "Sans Khmer", "Sans Khmer UI", "Sans Malayalam", "Sans Malayalam UI", "Sans Masaram Gondi", "Sans Math", "Sans Mono", "Sans Oriya", "Sans Oriya UI", "Sans Sinhala", "Sans Sinhala UI", "Sans Tamil", "Sans Tamil UI", "Sans Telugu", "Sans Telugu UI", "Sans Vithkuqi", "Sans Wancho", "Sans WarangCiti", "Serif", "Serif Bengali", "Serif Devanagari", "Serif Display", "Serif Gujarati", "Serif Gurmukhi", "Serif Kannada", "Serif Khmer", "Serif Khojki", "Serif Malayalam", "Serif Oriya", "Serif Sinhala", "Serif Tamil", "Serif Tangut", "Serif Telugu", "Serif Vithkuqi", "Arimo", "Cousine", "Tinos"]}, "40": {"name": "LEFT PARENTHESIS", "fonts": ["Looped Lao Regular", "Looped Lao UI Regular", "Looped Thai Regular", "Looped Thai UI Regular", "Nastaliq Urdu", "NotoSerifTamilSlanted", "Sans", "Sans Adlam", "Sans Adlam Unjoined", "Sans Bengali", "Sans Bengali UI", "Sans CJK HK", "Sans CJK JP", "Sans CJK KR", "Sans CJK SC", "Sans CJK TC", "Sans Cham", "Sans Devanagari", "Sans Devanagari UI", "Sans Display", "Sans Gujarati", "Sans Gujarati UI", "Sans Gunjala Gondi", "Sans Gurmukhi", "Sans Gurmukhi UI", "Sans Kannada", "Sans Kannada UI", "Sans Khmer", "Sans Khmer UI", "Sans Malayalam", "Sans Malayalam UI", "Sans Masaram Gondi", "Sans Math", "Sans Mongolian", "Sans Mono", "Sans Oriya", "Sans Oriya UI", "Sans Sinhala", "Sans Sinhala UI", "Sans Syriac", "Sans Tamil", "Sans Tamil UI", "Sans Telugu", "Sans Telugu UI", "Sans Thaana", "Sans Vithkuqi", "Sans Wancho", "Serif", "Serif Bengali", "Serif Devanagari", "Serif Display", "Serif Gujarati", "Serif Gurmukhi", "Serif Kannada", "Serif Khmer", "Serif Khojki", "Serif Malayalam", "Serif Oriya", "Serif Sinhala", "Serif Tamil", "Serif Tangut", "Serif Telugu", "Serif Vithkuqi", "Arimo", "Cousine", "Tinos"]}, "41": {"name": "RIGHT PARENTHESIS", "fonts": ["Looped Lao Regular", "Looped Lao UI Regular", "Looped Thai Regular", "Looped Thai UI Regular", "Nastaliq Urdu", "NotoSerifTamilSlanted", "Sans", "Sans Adlam", "Sans Adlam Unjoined", "Sans Bengali", "Sans Bengali UI", "Sans CJK HK", "Sans CJK JP", "Sans CJK KR", "Sans CJK SC", "Sans CJK TC", "Sans Cham", "Sans Devanagari", "Sans Devanagari UI", "Sans Display", "Sans Gujarati", "Sans Gujarati UI", "Sans Gunjala Gondi", "Sans Gurmukhi", "Sans Gurmukhi UI", "Sans Kannada", "Sans Kannada UI", "Sans Khmer", "Sans Khmer UI", "Sans Malayalam", "Sans Malayalam UI", "Sans Masaram Gondi", "Sans Math", "Sans Mongolian", "Sans Mono", "Sans Oriya", "Sans Oriya UI", "Sans Sinhala", "Sans Sinhala UI", "Sans Syriac", "Sans Tamil", "Sans Tamil UI", "Sans Telugu", "Sans Telugu UI", "Sans Thaana", "Sans Vithkuqi", "Sans Wancho", "Serif", "Serif Bengali", "Serif Devanagari", "Serif Display", "Serif Gujarati", "Serif Gurmukhi", "Serif Kannada", "Serif Khmer", "Serif Khojki", "Serif Malayalam", "Serif Oriya", "Serif Sinhala", "Serif Tamil", "Serif Tangut", "Serif Telugu", "Serif Vithkuqi", "Arimo", "Cousine", "Tinos"]}, "42": {"name": "ASTERISK", "fonts": ["Color Emoji", "Looped Lao Regular", "Looped Lao UI Regular", "Looped Thai Regular", "Looped Thai UI Regular", "NotoSerifTamilSlanted", "Sans", "Sans Adlam", "Sans Adlam Unjoined", "Sans Bengali", "Sans Bengali UI", "Sans CJK HK", "Sans CJK JP", "Sans CJK KR", "Sans CJK SC", "Sans CJK TC", "Sans Devanagari", "Sans Devanagari UI", "Sans Display", "Sans Gujarati", "Sans Gujarati UI", "Sans Gunjala Gondi", "Sans Gurmukhi", "Sans Gurmukhi UI", "Sans Kannada", "Sans Kannada UI", "Sans Malayalam", "Sans Malayalam UI", "Sans Masaram Gondi", "Sans Math", "Sans Mono", "Sans Oriya", "Sans Oriya UI", "Sans Sinhala", "Sans Sinhala UI", "Sans Symbols2", "Sans Syriac", "Sans Tamil", "Sans Tamil UI", "Sans Telugu", "Sans Telugu UI", "Sans Vithkuqi", "Serif", "Serif Bengali", "Serif Devanagari", "Serif Display", "Serif Gujarati", "Serif Gurmukhi", "Serif Kannada", "Serif Khojki", "Serif Malayalam", "Serif Oriya", "Serif Sinhala", "Serif Tamil", "Serif Tangut", "Serif Telugu", "Serif Vithkuqi", "Arimo", "Cousine", "Tinos"]}, "43": {"name": "PLUS SIGN", "fonts": ["Nastaliq Urdu", "NotoSerifTamilSlanted", "Sans", "Sans Adlam", "Sans Adlam Unjoined", "Sans Bengali", "Sans Bengali UI", "Sans CJK HK", "Sans CJK JP", "Sans CJK KR", "Sans CJK SC", "Sans CJK TC", "Sans Devanagari", "Sans Devanagari UI", "Sans Display", "Sans Gujarati", "Sans Gujarati UI", "Sans Gunjala Gondi", "Sans Gurmukhi", "Sans Gurmukhi UI", "Sans Kannada", "Sans Kannada UI", "Sans Malayalam", "Sans Malayalam UI", "Sans Masaram Gondi", "Sans Math", "Sans Mono", "Sans Oriya", "Sans Oriya UI", "Sans Sinhala", "Sans Sinhala UI", "Sans Syriac", "Sans Tamil", "Sans Tamil UI", "Sans Telugu", "Sans Telugu UI", "Sans Vithkuqi", "Serif", "Serif Bengali", "Serif Devanagari", "Serif Display", "Serif Gujarati", "Serif Gurmukhi", "Serif Kannada", "Serif Khojki", "Serif Malayalam", "Serif Oriya", "Serif Sinhala", "Serif Tamil", "Serif Tangut", "Serif Telugu", "Serif Vithkuqi", "Arimo", "Cousine", "Tinos"]}, "44": {"name": "COMMA", "fonts": ["Looped Lao Regular", "Looped Lao UI Regular", "Looped Thai Regular", "Looped Thai UI Regular", "Naskh Arabic", "Naskh Arabic UI", "Nastaliq Urdu", "NotoSerifTamilSlanted", "Sans", "Sans Adlam", "Sans Adlam Unjoined", "Sans Arabic", "Sans Arabic UI", "Sans Bengali", "Sans Bengali UI", "Sans CJK HK", "Sans CJK JP", "Sans CJK KR", "Sans CJK SC", "Sans CJK TC", "Sans Chakma", "Sans Cham", "Sans Coptic", "Sans Devanagari", "Sans Devanagari UI", "Sans Display", "Sans Gujarati", "Sans Gujarati UI", "Sans Gunjala Gondi", "Sans Gurmukhi", "Sans Gurmukhi UI", "Sans Kannada", "Sans Kannada UI", "Sans Khmer", "Sans Khmer UI", "Sans Malayalam", "Sans Malayalam UI", "Sans Masaram Gondi", "Sans Math", "Sans Mono", "Sans Oriya", "Sans Oriya UI", "Sans Sinhala", "Sans Sinhala UI", "Sans Tamil", "Sans Tamil UI", "Sans Telugu", "Sans Telugu UI", "Sans Thaana", "Sans Vithkuqi", "Sans Wancho", "Serif", "Serif Bengali", "Serif Devanagari", "Serif Display", "Serif Gujarati", "Serif Gurmukhi", "Serif Kannada", "Serif Khmer", "Serif Khojki", "Serif Malayalam", "Serif Oriya", "Serif Sinhala", "Serif Tamil", "Serif Tangut", "Serif Telugu", "Serif Vithkuqi", "Traditional Nushu", "Arimo", "Cousine", "Tinos"]}, "45": {"name": "HYPHEN-MINUS", "fonts": ["Looped Lao Regular", "Looped Lao UI Regular", "Looped Thai Regular", "Looped Thai UI Regular", "Nastaliq Urdu", "NotoSerifTamilSlanted", "Rashi Hebrew", "Sans", "Sans Adlam", "Sans Adlam Unjoined", "Sans Arabic", "Sans Arabic UI", "Sans Armenian", "Sans Bengali", "Sans Bengali UI", "Sans CJK HK", "Sans CJK JP", "Sans CJK KR", "Sans CJK SC", "Sans CJK TC", "Sans Chakma", "Sans Cham", "Sans Coptic", "Sans Devanagari", "Sans Devanagari UI", "Sans Display", "Sans Ethiopic", "Sans Georgian", "Sans Gujarati", "Sans Gujarati UI", "Sans Gunjala Gondi", "Sans Gurmukhi", "Sans Gurmukhi UI", "Sans Hebrew", "Sans Hebrew Droid", "Sans Hebrew New", "Sans Kaithi", "Sans Kannada", "Sans Kannada UI", "Sans Kayah Li", "Sans Kharoshthi", "Sans Khmer", "Sans Khmer UI", "Sans Lisu", "Sans Malayalam", "Sans Malayalam UI", "Sans Masaram Gondi", "Sans Math", "Sans Mongolian", "Sans Mono", "Sans Sinhala", "Sans Sinhala UI", "Sans Sora Sompeng", "Sans Sundanese", "Sans Syriac", "Sans Tamil", "Sans Tamil UI", "Sans Telugu", "Sans Telugu UI", "Sans Thai", "Sans Thai UI", "Sans Vithkuqi", "Sans Wancho", "Serif", "Serif Armenian", "Serif Bengali", "Serif Devanagari", "Serif Display", "Serif Ethiopic", "Serif Georgian", "Serif Gujarati", "Serif Gurmukhi", "Serif Hebrew", "Serif Kannada", "Serif Khmer", "Serif Khojki", "Serif Malayalam", "Serif Oriya", "Serif Sinhala", "Serif Tamil", "Serif Tangut", "Serif Telugu", "Serif Thai", "Serif Tibetan", "Serif Vithkuqi", "Traditional Nushu", "Arimo", "Cousine", "Tinos"]}, "46": {"name": "FULL STOP", "fonts": ["Looped Lao Regular", "Looped Lao UI Regular", "Looped Thai Regular", "Looped Thai UI Regular", "Naskh Arabic", "Naskh Arabic UI", "Nastaliq Urdu", "NotoSerifTamilSlanted", "Sans", "Sans Adlam", "Sans Adlam Unjoined", "Sans Arabic", "Sans Arabic UI", "Sans Avestan", "Sans Bengali", "Sans Bengali UI", "Sans CJK HK", "Sans CJK JP", "Sans CJK KR", "Sans CJK SC", "Sans CJK TC", "Sans Cham", "Sans Coptic", "Sans Devanagari", "Sans Devanagari UI", "Sans Display", "Sans Gujarati", "Sans Gujarati UI", "Sans Gunjala Gondi", "Sans Gurmukhi", "Sans Gurmukhi UI", "Sans Kannada", "Sans Kannada UI", "Sans Khmer", "Sans Khmer UI", "Sans Malayalam", "Sans Malayalam UI", "Sans Masaram Gondi", "Sans Math", "Sans Mono", "Sans Oriya", "Sans Oriya UI", "Sans Sinhala", "Sans Sinhala UI", "Sans Syriac", "Sans Tamil", "Sans Tamil UI", "Sans Telugu", "Sans Telugu UI", "Sans Thaana", "Sans Vithkuqi", "Sans Wancho", "Serif", "Serif Bengali", "Serif Devanagari", "Serif Display", "Serif Gujarati", "Serif Gurmukhi", "Serif Kannada", "Serif Khmer", "Serif Khojki", "Serif Malayalam", "Serif Oriya", "Serif Sinhala", "Serif Tamil", "Serif Tangut", "Serif Telugu", "Serif Vithkuqi", "Traditional Nushu", "Arimo", "Cousine", "Tinos"]}, "47": {"name": "SOLIDUS", "fonts": ["Looped Lao Regular", "Looped Lao UI Regular", "Looped Thai Regular", "Looped Thai UI Regular", "Nastaliq Urdu", "NotoSerifTamilSlanted", "Sans", "Sans Adlam", "Sans Adlam Unjoined", "Sans Bengali", "Sans Bengali UI", "Sans CJK HK", "Sans CJK JP", "Sans CJK KR", "Sans CJK SC", "Sans CJK TC", "Sans Cham", "Sans Devanagari", "Sans Devanagari UI", "Sans Display", "Sans Gujarati", "Sans Gujarati UI", "Sans Gunjala Gondi", "Sans Gurmukhi", "Sans Gurmukhi UI", "Sans Kannada", "Sans Kannada UI", "Sans Khmer", "Sans Khmer UI", "Sans Malayalam", "Sans Malayalam UI", "Sans Masaram Gondi", "Sans Math", "Sans Mono", "Sans Oriya", "Sans Oriya UI", "Sans Sinhala", "Sans Sinhala UI", "Sans Syriac", "Sans Tamil", "Sans Tamil UI", "Sans Telugu", "Sans Telugu UI", "Sans Vithkuqi", "Sans Wancho", "Serif", "Serif Bengali", "Serif Devanagari", "Serif Display", "Serif Gujarati", "Serif Gurmukhi", "Serif Kannada", "Serif Khmer", "Serif Khojki", "Serif Malayalam", "Serif Oriya", "Serif Sinhala", "Serif Tamil", "Serif Tangut", "Serif Telugu", "Serif Vithkuqi", "Arimo", "Cousine", "Tinos"]}, "48": {"name": "DIGIT ZERO", "fonts": ["Color Emoji", "Kufi Arabic", "Naskh Arabic", "Naskh Arabic UI", "Nastaliq Urdu", "NotoSerifTamilSlanted", "Sans", "Sans Arabic", "Sans Arabic UI", "Sans Bengali", "Sans Bengali UI", "Sans CJK HK", "Sans CJK JP", "Sans CJK KR", "Sans CJK SC", "Sans CJK TC", "Sans Devanagari", "Sans Devanagari UI", "Sans Display", "Sans Gujarati", "Sans Gujarati UI", "Sans Gurmukhi", "Sans Gurmukhi UI", "Sans Kannada", "Sans Kannada UI", "Sans Malayalam", "Sans Malayalam UI", "Sans Math", "Sans Mono", "Sans Oriya", "Sans Oriya UI", "Sans Sinhala", "Sans Sinhala UI", "Sans Symbols", "Sans Symbols2", "Sans Tamil", "Sans Tamil UI", "Sans Telugu", "Sans Telugu UI", "Sans Vithkuqi", "Serif", "Serif Bengali", "Serif Devanagari", "Serif Display", "Serif Gujarati", "Serif Gurmukhi", "Serif Kannada", "Serif Khojki", "Serif Malayalam", "Serif Oriya", "Serif Sinhala", "Serif Tamil", "Serif Tangut", "Serif Telugu", "Serif Vithkuqi", "Traditional Nushu", "Arimo", "Cousine", "Tinos"]}, "49": {"name": "DIGIT ONE", "fonts": ["Color Emoji", "Kufi Arabic", "Naskh Arabic", "Naskh Arabic UI", "Nastaliq Urdu", "NotoSerifTamilSlanted", "Sans", "Sans Arabic", "Sans Arabic UI", "Sans Bengali", "Sans Bengali UI", "Sans CJK HK", "Sans CJK JP", "Sans CJK KR", "Sans CJK SC", "Sans CJK TC", "Sans Devanagari", "Sans Devanagari UI", "Sans Display", "Sans Gujarati", "Sans Gujarati UI", "Sans Gurmukhi", "Sans Gurmukhi UI", "Sans Kannada", "Sans Kannada UI", "Sans Malayalam", "Sans Malayalam UI", "Sans Math", "Sans Mono", "Sans Oriya", "Sans Oriya UI", "Sans Sinhala", "Sans Sinhala UI", "Sans Symbols", "Sans Symbols2", "Sans Tamil", "Sans Tamil UI", "Sans Telugu", "Sans Telugu UI", "Sans Vithkuqi", "Serif", "Serif Bengali", "Serif Devanagari", "Serif Display", "Serif Gujarati", "Serif Gurmukhi", "Serif Kannada", "Serif Khojki", "Serif Malayalam", "Serif Oriya", "Serif Sinhala", "Serif Tamil", "Serif Tangut", "Serif Telugu", "Serif Vithkuqi", "Traditional Nushu", "Arimo", "Cousine", "Tinos"]}, "50": {"name": "DIGIT TWO", "fonts": ["Color Emoji", "Kufi Arabic", "Naskh Arabic", "Naskh Arabic UI", "Nastaliq Urdu", "NotoSerifTamilSlanted", "Sans", "Sans Arabic", "Sans Arabic UI", "Sans Bengali", "Sans Bengali UI", "Sans CJK HK", "Sans CJK JP", "Sans CJK KR", "Sans CJK SC", "Sans CJK TC", "Sans Devanagari", "Sans Devanagari UI", "Sans Display", "Sans Gujarati", "Sans Gujarati UI", "Sans Gurmukhi", "Sans Gurmukhi UI", "Sans Kannada", "Sans Kannada UI", "Sans Malayalam", "Sans Malayalam UI", "Sans Math", "Sans Mono", "Sans Oriya", "Sans Oriya UI", "Sans Sinhala", "Sans Sinhala UI", "Sans Symbols", "Sans Symbols2", "Sans Tamil", "Sans Tamil UI", "Sans Telugu", "Sans Telugu UI", "Sans Vithkuqi", "Serif", "Serif Bengali", "Serif Devanagari", "Serif Display", "Serif Gujarati", "Serif Gurmukhi", "Serif Kannada", "Serif Khojki", "Serif Malayalam", "Serif Oriya", "Serif Sinhala", "Serif Tamil", "Serif Tangut", "Serif Telugu", "Serif Vithkuqi", "Traditional Nushu", "Arimo", "Cousine", "Tinos"]}, "51": {"name": "DIGIT THREE", "fonts": ["Color Emoji", "Kufi Arabic", "Naskh Arabic", "Naskh Arabic UI", "Nastaliq Urdu", "NotoSerifTamilSlanted", "Sans", "Sans Arabic", "Sans Arabic UI", "Sans Bengali", "Sans Bengali UI", "Sans CJK HK", "Sans CJK JP", "Sans CJK KR", "Sans CJK SC", "Sans CJK TC", "Sans Devanagari", "Sans Devanagari UI", "Sans Display", "Sans Gujarati", "Sans Gujarati UI", "Sans Gurmukhi", "Sans Gurmukhi UI", "Sans Kannada", "Sans Kannada UI", "Sans Malayalam", "Sans Malayalam UI", "Sans Math", "Sans Mono", "Sans Oriya", "Sans Oriya UI", "Sans Sinhala", "Sans Sinhala UI", "Sans Symbols", "Sans Symbols2", "Sans Tamil", "Sans Tamil UI", "Sans Telugu", "Sans Telugu UI", "Sans Vithkuqi", "Serif", "Serif Bengali", "Serif Devanagari", "Serif Display", "Serif Gujarati", "Serif Gurmukhi", "Serif Kannada", "Serif Khojki", "Serif Malayalam", "Serif Oriya", "Serif Sinhala", "Serif Tamil", "Serif Tangut", "Serif Telugu", "Serif Vithkuqi", "Traditional Nushu", "Arimo", "Cousine", "Tinos"]}, "52": {"name": "DIGIT FOUR", "fonts": ["Color Emoji", "Kufi Arabic", "Naskh Arabic", "Naskh Arabic UI", "Nastaliq Urdu", "NotoSerifTamilSlanted", "Sans", "Sans Arabic", "Sans Arabic UI", "Sans Bengali", "Sans Bengali UI", "Sans CJK HK", "Sans CJK JP", "Sans CJK KR", "Sans CJK SC", "Sans CJK TC", "Sans Devanagari", "Sans Devanagari UI", "Sans Display", "Sans Gujarati", "Sans Gujarati UI", "Sans Gurmukhi", "Sans Gurmukhi UI", "Sans Kannada", "Sans Kannada UI", "Sans Malayalam", "Sans Malayalam UI", "Sans Math", "Sans Mono", "Sans Oriya", "Sans Oriya UI", "Sans Sinhala", "Sans Sinhala UI", "Sans Symbols", "Sans Symbols2", "Sans Tamil", "Sans Tamil UI", "Sans Telugu", "Sans Telugu UI", "Sans Vithkuqi", "Serif", "Serif Bengali", "Serif Devanagari", "Serif Display", "Serif Gujarati", "Serif Gurmukhi", "Serif Kannada", "Serif Khojki", "Serif Malayalam", "Serif Oriya", "Serif Sinhala", "Serif Tamil", "Serif Tangut", "Serif Telugu", "Serif Vithkuqi", "Traditional Nushu", "Arimo", "Cousine", "Tinos"]}, "53": {"name": "DIGIT FIVE", "fonts": ["Color Emoji", "Kufi Arabic", "Naskh Arabic", "Naskh Arabic UI", "Nastaliq Urdu", "NotoSerifTamilSlanted", "Sans", "Sans Arabic", "Sans Arabic UI", "Sans Bengali", "Sans Bengali UI", "Sans CJK HK", "Sans CJK JP", "Sans CJK KR", "Sans CJK SC", "Sans CJK TC", "Sans Devanagari", "Sans Devanagari UI", "Sans Display", "Sans Gujarati", "Sans Gujarati UI", "Sans Gurmukhi", "Sans Gurmukhi UI", "Sans Kannada", "Sans Kannada UI", "Sans Malayalam", "Sans Malayalam UI", "Sans Math", "Sans Mono", "Sans Oriya", "Sans Oriya UI", "Sans Sinhala", "Sans Sinhala UI", "Sans Symbols", "Sans Symbols2", "Sans Tamil", "Sans Tamil UI", "Sans Telugu", "Sans Telugu UI", "Sans Vithkuqi", "Serif", "Serif Bengali", "Serif Devanagari", "Serif Display", "Serif Gujarati", "Serif Gurmukhi", "Serif Kannada", "Serif Khojki", "Serif Malayalam", "Serif Oriya", "Serif Sinhala", "Serif Tamil", "Serif Tangut", "Serif Telugu", "Serif Vithkuqi", "Traditional Nushu", "Arimo", "Cousine", "Tinos"]}, "54": {"name": "DIGIT SIX", "fonts": ["Color Emoji", "Kufi Arabic", "Naskh Arabic", "Naskh Arabic UI", "Nastaliq Urdu", "NotoSerifTamilSlanted", "Sans", "Sans Arabic", "Sans Arabic UI", "Sans Bengali", "Sans Bengali UI", "Sans CJK HK", "Sans CJK JP", "Sans CJK KR", "Sans CJK SC", "Sans CJK TC", "Sans Devanagari", "Sans Devanagari UI", "Sans Display", "Sans Gujarati", "Sans Gujarati UI", "Sans Gurmukhi", "Sans Gurmukhi UI", "Sans Kannada", "Sans Kannada UI", "Sans Malayalam", "Sans Malayalam UI", "Sans Math", "Sans Mono", "Sans Oriya", "Sans Oriya UI", "Sans Sinhala", "Sans Sinhala UI", "Sans Symbols", "Sans Symbols2", "Sans Tamil", "Sans Tamil UI", "Sans Telugu", "Sans Telugu UI", "Sans Vithkuqi", "Serif", "Serif Bengali", "Serif Devanagari", "Serif Display", "Serif Gujarati", "Serif Gurmukhi", "Serif Kannada", "Serif Khojki", "Serif Malayalam", "Serif Oriya", "Serif Sinhala", "Serif Tamil", "Serif Tangut", "Serif Telugu", "Serif Vithkuqi", "Traditional Nushu", "Arimo", "Cousine", "Tinos"]}, "55": {"name": "DIGIT SEVEN", "fonts": ["Color Emoji", "Kufi Arabic", "Naskh Arabic", "Naskh Arabic UI", "Nastaliq Urdu", "NotoSerifTamilSlanted", "Sans", "Sans Arabic", "Sans Arabic UI", "Sans Bengali", "Sans Bengali UI", "Sans CJK HK", "Sans CJK JP", "Sans CJK KR", "Sans CJK SC", "Sans CJK TC", "Sans Devanagari", "Sans Devanagari UI", "Sans Display", "Sans Gujarati", "Sans Gujarati UI", "Sans Gurmukhi", "Sans Gurmukhi UI", "Sans Kannada", "Sans Kannada UI", "Sans Malayalam", "Sans Malayalam UI", "Sans Math", "Sans Mono", "Sans Oriya", "Sans Oriya UI", "Sans Sinhala", "Sans Sinhala UI", "Sans Symbols", "Sans Symbols2", "Sans Tamil", "Sans Tamil UI", "Sans Telugu", "Sans Telugu UI", "Sans Vithkuqi", "Serif", "Serif Bengali", "Serif Devanagari", "Serif Display", "Serif Gujarati", "Serif Gurmukhi", "Serif Kannada", "Serif Khojki", "Serif Malayalam", "Serif Oriya", "Serif Sinhala", "Serif Tamil", "Serif Tangut", "Serif Telugu", "Serif Vithkuqi", "Traditional Nushu", "Arimo", "Cousine", "Tinos"]}, "56": {"name": "DIGIT EIGHT", "fonts": ["Color Emoji", "Kufi Arabic", "Naskh Arabic", "Naskh Arabic UI", "Nastaliq Urdu", "NotoSerifTamilSlanted", "Sans", "Sans Arabic", "Sans Arabic UI", "Sans Bengali", "Sans Bengali UI", "Sans CJK HK", "Sans CJK JP", "Sans CJK KR", "Sans CJK SC", "Sans CJK TC", "Sans Devanagari", "Sans Devanagari UI", "Sans Display", "Sans Gujarati", "Sans Gujarati UI", "Sans Gurmukhi", "Sans Gurmukhi UI", "Sans Kannada", "Sans Kannada UI", "Sans Malayalam", "Sans Malayalam UI", "Sans Math", "Sans Mono", "Sans Oriya", "Sans Oriya UI", "Sans Sinhala", "Sans Sinhala UI", "Sans Symbols", "Sans Symbols2", "Sans Tamil", "Sans Tamil UI", "Sans Telugu", "Sans Telugu UI", "Sans Vithkuqi", "Serif", "Serif Bengali", "Serif Devanagari", "Serif Display", "Serif Gujarati", "Serif Gurmukhi", "Serif Kannada", "Serif Khojki", "Serif Malayalam", "Serif Oriya", "Serif Sinhala", "Serif Tamil", "Serif Tangut", "Serif Telugu", "Serif Vithkuqi", "Traditional Nushu", "Arimo", "Cousine", "Tinos"]}, "57": {"name": "DIGIT NINE", "fonts": ["Color Emoji", "Kufi Arabic", "Naskh Arabic", "Naskh Arabic UI", "Nastaliq Urdu", "NotoSerifTamilSlanted", "Sans", "Sans Arabic", "Sans Arabic UI", "Sans Bengali", "Sans Bengali UI", "Sans CJK HK", "Sans CJK JP", "Sans CJK KR", "Sans CJK SC", "Sans CJK TC", "Sans Devanagari", "Sans Devanagari UI", "Sans Display", "Sans Gujarati", "Sans Gujarati UI", "Sans Gurmukhi", "Sans Gurmukhi UI", "Sans Kannada", "Sans Kannada UI", "Sans Malayalam", "Sans Malayalam UI", "Sans Math", "Sans Mono", "Sans Oriya", "Sans Oriya UI", "Sans Sinhala", "Sans Sinhala UI", "Sans Symbols", "Sans Symbols2", "Sans Tamil", "Sans Tamil UI", "Sans Telugu", "Sans Telugu UI", "Sans Vithkuqi", "Serif", "Serif Bengali", "Serif Devanagari", "Serif Display", "Serif Gujarati", "Serif Gurmukhi", "Serif Kannada", "Serif Khojki", "Serif Malayalam", "Serif Oriya", "Serif Sinhala", "Serif Tamil", "Serif Tangut", "Serif Telugu", "Serif Vithkuqi", "Traditional Nushu", "Arimo", "Cousine", "Tinos"]}, "58": {"name": "COLON", "fonts": ["Looped Lao Regular", "Looped Lao UI Regular", "Looped Thai Regular", "Looped Thai UI Regular", "Naskh Arabic", "Naskh Arabic UI", "Nastaliq Urdu", "NotoSerifTamilSlanted", "Sans", "Sans Adlam", "Sans Adlam Unjoined", "Sans Arabic", "Sans Arabic UI", "Sans Bengali", "Sans Bengali UI", "Sans CJK HK", "Sans CJK JP", "Sans CJK KR", "Sans CJK SC", "Sans CJK TC", "Sans Cham", "Sans Coptic", "Sans Devanagari", "Sans Devanagari UI", "Sans Display", "Sans Gujarati", "Sans Gujarati UI", "Sans Gunjala Gondi", "Sans Gurmukhi", "Sans Gurmukhi UI", "Sans Kannada", "Sans Kannada UI", "Sans Khmer", "Sans Khmer UI", "Sans Malayalam", "Sans Malayalam UI", "Sans Masaram Gondi", "Sans Math", "Sans Meroitic", "Sans Mono", "Sans Oriya", "Sans Oriya UI", "Sans Sinhala", "Sans Sinhala UI", "Sans Syriac", "Sans Tamil", "Sans Tamil UI", "Sans Telugu", "Sans Telugu UI", "Sans Thaana", "Sans Vithkuqi", "Serif", "Serif Bengali", "Serif Devanagari", "Serif Display", "Serif Gujarati", "Serif Gurmukhi", "Serif Kannada", "Serif Khmer", "Serif Khojki", "Serif Malayalam", "Serif Oriya", "Serif Sinhala", "Serif Tamil", "Serif Tangut", "Serif Telugu", "Serif Vithkuqi", "Arimo", "Cousine", "Tinos"]}, "59": {"name": "SEMICOLON", "fonts": ["Looped Lao Regular", "Looped Lao UI Regular", "Looped Thai Regular", "Looped Thai UI Regular", "NotoSerifTamilSlanted", "Sans", "Sans Adlam", "Sans Adlam Unjoined", "Sans Bengali", "Sans Bengali UI", "Sans CJK HK", "Sans CJK JP", "Sans CJK KR", "Sans CJK SC", "Sans CJK TC", "Sans Cham", "Sans Coptic", "Sans Devanagari", "Sans Devanagari UI", "Sans Display", "Sans Gujarati", "Sans Gujarati UI", "Sans Gurmukhi", "Sans Gurmukhi UI", "Sans Kannada", "Sans Kannada UI", "Sans Khmer", "Sans Khmer UI", "Sans Malayalam", "Sans Malayalam UI", "Sans Masaram Gondi", "Sans Math", "Sans Mono", "Sans Oriya", "Sans Oriya UI", "Sans Sinhala", "Sans Sinhala UI", "Sans Tamil", "Sans Tamil UI", "Sans Telugu", "Sans Telugu UI", "Sans Thaana", "Sans Vithkuqi", "Serif", "Serif Bengali", "Serif Devanagari", "Serif Display", "Serif Gujarati", "Serif Gurmukhi", "Serif Kannada", "Serif Khmer", "Serif Khojki", "Serif Malayalam", "Serif Oriya", "Serif Sinhala", "Serif Tamil", "Serif Tangut", "Serif Telugu", "Serif Vithkuqi", "Arimo", "Cousine", "Tinos"]}, "60": {"name": "LESS-THAN SIGN", "fonts": ["NotoSerifTamilSlanted", "Sans", "Sans Adlam", "Sans Adlam Unjoined", "Sans Bengali", "Sans Bengali UI", "Sans CJK HK", "Sans CJK JP", "Sans CJK KR", "Sans CJK SC", "Sans CJK TC", "Sans Devanagari", "Sans Devanagari UI", "Sans Display", "Sans Gujarati", "Sans Gujarati UI", "Sans Gunjala Gondi", "Sans Gurmukhi", "Sans Gurmukhi UI", "Sans Kannada", "Sans Kannada UI", "Sans Malayalam", "Sans Malayalam UI", "Sans Masaram Gondi", "Sans Math", "Sans Mono", "Sans Oriya", "Sans Oriya UI", "Sans Sinhala", "Sans Sinhala UI", "Sans Tamil", "Sans Tamil UI", "Sans Telugu", "Sans Telugu UI", "Sans Vithkuqi", "Serif", "Serif Bengali", "Serif Devanagari", "Serif Display", "Serif Gujarati", "Serif Gurmukhi", "Serif Kannada", "Serif Khojki", "Serif Malayalam", "Serif Oriya", "Serif Sinhala", "Serif Tamil", "Serif Tangut", "Serif Telugu", "Serif Vithkuqi", "Arimo", "Cousine", "Tinos"]}, "61": {"name": "EQUALS SIGN", "fonts": ["Nastaliq Urdu", "NotoSerifTamilSlanted", "Sans", "Sans Adlam", "Sans Adlam Unjoined", "Sans Bengali", "Sans Bengali UI", "Sans CJK HK", "Sans CJK JP", "Sans CJK KR", "Sans CJK SC", "Sans CJK TC", "Sans Devanagari", "Sans Devanagari UI", "Sans Display", "Sans Gujarati", "Sans Gujarati UI", "Sans Gunjala Gondi", "Sans Gurmukhi", "Sans Gurmukhi UI", "Sans Kannada", "Sans Kannada UI", "Sans Malayalam", "Sans Malayalam UI", "Sans Masaram Gondi", "Sans Math", "Sans Mono", "Sans Oriya", "Sans Oriya UI", "Sans Sinhala", "Sans Sinhala UI", "Sans Syriac", "Sans Tamil", "Sans Tamil UI", "Sans Telugu", "Sans Telugu UI", "Sans Vithkuqi", "Serif", "Serif Bengali", "Serif Devanagari", "Serif Display", "Serif Gujarati", "Serif Gurmukhi", "Serif Kannada", "Serif Khojki", "Serif Malayalam", "Serif Oriya", "Serif Sinhala", "Serif Tamil", "Serif Tangut", "Serif Telugu", "Serif Vithkuqi", "Arimo", "Cousine", "Tinos"]}, "62": {"name": "GREATER-THAN SIGN", "fonts": ["NotoSerifTamilSlanted", "Sans", "Sans Adlam", "Sans Adlam Unjoined", "Sans Bengali", "Sans Bengali UI", "Sans CJK HK", "Sans CJK JP", "Sans CJK KR", "Sans CJK SC", "Sans CJK TC", "Sans Devanagari", "Sans Devanagari UI", "Sans Display", "Sans Gujarati", "Sans Gujarati UI", "Sans Gunjala Gondi", "Sans Gurmukhi", "Sans Gurmukhi UI", "Sans Kannada", "Sans Kannada UI", "Sans Malayalam", "Sans Malayalam UI", "Sans Masaram Gondi", "Sans Math", "Sans Mono", "Sans Oriya", "Sans Oriya UI", "Sans Sinhala", "Sans Sinhala UI", "Sans Tamil", "Sans Tamil UI", "Sans Telugu", "Sans Telugu UI", "Sans Vithkuqi", "Serif", "Serif Bengali", "Serif Devanagari", "Serif Display", "Serif Gujarati", "Serif Gurmukhi", "Serif Kannada", "Serif Khojki", "Serif Malayalam", "Serif Oriya", "Serif Sinhala", "Serif Tamil", "Serif Tangut", "Serif Telugu", "Serif Vithkuqi", "Arimo", "Cousine", "Tinos"]}, "63": {"name": "QUESTION MARK", "fonts": ["Looped Lao Regular", "Looped Lao UI Regular", "Looped Thai Regular", "Looped Thai UI Regular", "NotoSerifTamilSlanted", "Sans", "Sans Adlam", "Sans Adlam Unjoined", "Sans Balinese", "Sans Bengali", "Sans Bengali UI", "Sans CJK HK", "Sans CJK JP", "Sans CJK KR", "Sans CJK SC", "Sans CJK TC", "Sans Cham", "Sans Devanagari", "Sans Devanagari UI", "Sans Display", "Sans Gujarati", "Sans Gujarati UI", "Sans Gunjala Gondi", "Sans Gurmukhi", "Sans Gurmukhi UI", "Sans Kannada", "Sans Kannada UI", "Sans Khmer", "Sans Khmer UI", "Sans Malayalam", "Sans Malayalam UI", "Sans Masaram Gondi", "Sans Math", "Sans Mongolian", "Sans Mono", "Sans Myanmar", "Sans Myanmar UI", "Sans Oriya", "Sans Oriya UI", "Sans Sinhala", "Sans Sinhala UI", "Sans Tamil", "Sans Tamil UI", "Sans Telugu", "Sans Telugu UI", "Sans Vithkuqi", "Serif", "Serif Bengali", "Serif Devanagari", "Serif Display", "Serif Gujarati", "Serif Gurmukhi", "Serif Kannada", "Serif Khmer", "Serif Khojki", "Serif Malayalam", "Serif Myanmar", "Serif Oriya", "Serif Sinhala", "Serif Tamil", "Serif Tangut", "Serif Telugu", "Serif Vithkuqi", "Arimo", "Cousine", "Tinos"]}, "64": {"name": "COMMERCIAL AT", "fonts": ["Sans", "Sans Adlam", "Sans Adlam Unjoined", "Sans CJK HK", "Sans CJK JP", "Sans CJK KR", "Sans CJK SC", "Sans CJK TC", "Sans Display", "Sans Math", "Sans Mono", "Serif", "Serif Display", "Serif Tangut", "Arimo", "Cousine", "Tinos"]}, "65": {"name": "LATIN CAPITAL LETTER A", "fonts": ["Sans", "Sans CJK HK", "Sans CJK JP", "Sans CJK KR", "Sans CJK SC", "Sans CJK TC", "Sans Display", "Sans Math", "Sans Mono", "Sans Symbols", "Serif", "Serif Display", "Serif Tangut", "Traditional Nushu", "Arimo", "Cousine", "Tinos"]}, "66": {"name": "LATIN CAPITAL LETTER B", "fonts": ["Sans", "Sans CJK HK", "Sans CJK JP", "Sans CJK KR", "Sans CJK SC", "Sans CJK TC", "Sans Display", "Sans Math", "Sans Mono", "Sans Symbols", "Serif", "Serif Display", "Serif Tangut", "Traditional Nushu", "Arimo", "Cousine", "Tinos"]}, "67": {"name": "LATIN CAPITAL LETTER C", "fonts": ["Sans", "Sans CJK HK", "Sans CJK JP", "Sans CJK KR", "Sans CJK SC", "Sans CJK TC", "Sans Display", "Sans Math", "Sans Mono", "Sans Symbols", "Serif", "Serif Display", "Serif Tangut", "Traditional Nushu", "Arimo", "Cousine", "Tinos"]}, "68": {"name": "LATIN CAPITAL LETTER D", "fonts": ["Sans", "Sans CJK HK", "Sans CJK JP", "Sans CJK KR", "Sans CJK SC", "Sans CJK TC", "Sans Display", "Sans Math", "Sans Mono", "Sans Symbols", "Serif", "Serif Display", "Serif Tangut", "Traditional Nushu", "Arimo", "Cousine", "Tinos"]}, "69": {"name": "LATIN CAPITAL LETTER E", "fonts": ["Sans", "Sans CJK HK", "Sans CJK JP", "Sans CJK KR", "Sans CJK SC", "Sans CJK TC", "Sans Display", "Sans Math", "Sans Mono", "Sans Symbols", "Serif", "Serif Display", "Serif Tangut", "Traditional Nushu", "Arimo", "Cousine", "Tinos"]}, "70": {"name": "LATIN CAPITAL LETTER F", "fonts": ["Sans", "Sans CJK HK", "Sans CJK JP", "Sans CJK KR", "Sans CJK SC", "Sans CJK TC", "Sans Display", "Sans Math", "Sans Mono", "Sans Symbols", "Serif", "Serif Display", "Serif Tangut", "Traditional Nushu", "Arimo", "Cousine", "Tinos"]}, "71": {"name": "LATIN CAPITAL LETTER G", "fonts": ["Sans", "Sans CJK HK", "Sans CJK JP", "Sans CJK KR", "Sans CJK SC", "Sans CJK TC", "Sans Display", "Sans Math", "Sans Mono", "Sans Symbols", "Serif", "Serif Display", "Serif Tangut", "Traditional Nushu", "Arimo", "Cousine", "Tinos"]}, "72": {"name": "LATIN CAPITAL LETTER H", "fonts": ["Sans", "Sans CJK HK", "Sans CJK JP", "Sans CJK KR", "Sans CJK SC", "Sans CJK TC", "Sans Display", "Sans Math", "Sans Mono", "Sans Symbols", "Serif", "Serif Display", "Serif Tangut", "Traditional Nushu", "Arimo", "Cousine", "Tinos"]}, "73": {"name": "LATIN CAPITAL LETTER I", "fonts": ["Sans", "Sans CJK HK", "Sans CJK JP", "Sans CJK KR", "Sans CJK SC", "Sans CJK TC", "Sans Display", "Sans Math", "Sans Mono", "Sans Symbols", "Serif", "Serif Display", "Serif Tangut", "Traditional Nushu", "Arimo", "Cousine", "Tinos"]}, "74": {"name": "LATIN CAPITAL LETTER J", "fonts": ["Sans", "Sans CJK HK", "Sans CJK JP", "Sans CJK KR", "Sans CJK SC", "Sans CJK TC", "Sans Display", "Sans Math", "Sans Mono", "Sans Symbols", "Serif", "Serif Display", "Serif Tangut", "Traditional Nushu", "Arimo", "Cousine", "Tinos"]}, "75": {"name": "LATIN CAPITAL LETTER K", "fonts": ["Sans", "Sans CJK HK", "Sans CJK JP", "Sans CJK KR", "Sans CJK SC", "Sans CJK TC", "Sans Display", "Sans Math", "Sans Mono", "Sans Symbols", "Serif", "Serif Display", "Serif Tangut", "Traditional Nushu", "Arimo", "Cousine", "Tinos"]}, "76": {"name": "LATIN CAPITAL LETTER L", "fonts": ["Sans", "Sans CJK HK", "Sans CJK JP", "Sans CJK KR", "Sans CJK SC", "Sans CJK TC", "Sans Display", "Sans Math", "Sans Mono", "Sans Symbols", "Serif", "Serif Display", "Serif Tangut", "Traditional Nushu", "Arimo", "Cousine", "Tinos"]}, "77": {"name": "LATIN CAPITAL LETTER M", "fonts": ["Sans", "Sans CJK HK", "Sans CJK JP", "Sans CJK KR", "Sans CJK SC", "Sans CJK TC", "Sans Display", "Sans Math", "Sans Mono", "Sans Symbols", "Serif", "Serif Display", "Serif Tangut", "Traditional Nushu", "Arimo", "Cousine", "Tinos"]}, "78": {"name": "LATIN CAPITAL LETTER N", "fonts": ["Sans", "Sans CJK HK", "Sans CJK JP", "Sans CJK KR", "Sans CJK SC", "Sans CJK TC", "Sans Display", "Sans Math", "Sans Mono", "Sans Symbols", "Serif", "Serif Display", "Serif Tangut", "Traditional Nushu", "Arimo", "Cousine", "Tinos"]}, "79": {"name": "LATIN CAPITAL LETTER O", "fonts": ["Sans", "Sans CJK HK", "Sans CJK JP", "Sans CJK KR", "Sans CJK SC", "Sans CJK TC", "Sans Display", "Sans Math", "Sans Mono", "Sans Symbols", "Serif", "Serif Display", "Serif Tangut", "Traditional Nushu", "Arimo", "Cousine", "Tinos"]}, "80": {"name": "LATIN CAPITAL LETTER P", "fonts": ["Sans", "Sans CJK HK", "Sans CJK JP", "Sans CJK KR", "Sans CJK SC", "Sans CJK TC", "Sans Display", "Sans Math", "Sans Mono", "Sans Symbols", "Serif", "Serif Display", "Serif Tangut", "Traditional Nushu", "Arimo", "Cousine", "Tinos"]}, "81": {"name": "LATIN CAPITAL LETTER Q", "fonts": ["Sans", "Sans CJK HK", "Sans CJK JP", "Sans CJK KR", "Sans CJK SC", "Sans CJK TC", "Sans Display", "Sans Math", "Sans Mono", "Sans Symbols", "Serif", "Serif Display", "Serif Tangut", "Traditional Nushu", "Arimo", "Cousine", "Tinos"]}, "82": {"name": "LATIN CAPITAL LETTER R", "fonts": ["Sans", "Sans CJK HK", "Sans CJK JP", "Sans CJK KR", "Sans CJK SC", "Sans CJK TC", "Sans Display", "Sans Math", "Sans Mono", "Sans Symbols", "Serif", "Serif Display", "Serif Tangut", "Traditional Nushu", "Arimo", "Cousine", "Tinos"]}, "83": {"name": "LATIN CAPITAL LETTER S", "fonts": ["Sans", "Sans CJK HK", "Sans CJK JP", "Sans CJK KR", "Sans CJK SC", "Sans CJK TC", "Sans Display", "Sans Math", "Sans Mono", "Sans Symbols", "Serif", "Serif Display", "Serif Tangut", "Traditional Nushu", "Arimo", "Cousine", "Tinos"]}, "84": {"name": "LATIN CAPITAL LETTER T", "fonts": ["Sans", "Sans CJK HK", "Sans CJK JP", "Sans CJK KR", "Sans CJK SC", "Sans CJK TC", "Sans Display", "Sans Math", "Sans Mono", "Sans Symbols", "Serif", "Serif Display", "Serif Tangut", "Traditional Nushu", "Arimo", "Cousine", "Tinos"]}, "85": {"name": "LATIN CAPITAL LETTER U", "fonts": ["Sans", "Sans CJK HK", "Sans CJK JP", "Sans CJK KR", "Sans CJK SC", "Sans CJK TC", "Sans Display", "Sans Math", "Sans Mono", "Sans Symbols", "Serif", "Serif Display", "Serif Tangut", "Traditional Nushu", "Arimo", "Cousine", "Tinos"]}, "86": {"name": "LATIN CAPITAL LETTER V", "fonts": ["Sans", "Sans CJK HK", "Sans CJK JP", "Sans CJK KR", "Sans CJK SC", "Sans CJK TC", "Sans Display", "Sans Math", "Sans Mono", "Sans Symbols", "Serif", "Serif Display", "Serif Tangut", "Traditional Nushu", "Arimo", "Cousine", "Tinos"]}, "87": {"name": "LATIN CAPITAL LETTER W", "fonts": ["Sans", "Sans CJK HK", "Sans CJK JP", "Sans CJK KR", "Sans CJK SC", "Sans CJK TC", "Sans Display", "Sans Math", "Sans Mono", "Sans Symbols", "Serif", "Serif Display", "Serif Tangut", "Traditional Nushu", "Arimo", "Cousine", "Tinos"]}, "88": {"name": "LATIN CAPITAL LETTER X", "fonts": ["Sans", "Sans CJK HK", "Sans CJK JP", "Sans CJK KR", "Sans CJK SC", "Sans CJK TC", "Sans Display", "Sans Math", "Sans Mono", "Sans Symbols", "Serif", "Serif Display", "Serif Tangut", "Traditional Nushu", "Arimo", "Cousine", "Tinos"]}, "89": {"name": "LATIN CAPITAL LETTER Y", "fonts": ["Sans", "Sans CJK HK", "Sans CJK JP", "Sans CJK KR", "Sans CJK SC", "Sans CJK TC", "Sans Display", "Sans Math", "Sans Mono", "Sans Symbols", "Serif", "Serif Display", "Serif Tangut", "Traditional Nushu", "Arimo", "Cousine", "Tinos"]}, "90": {"name": "LATIN CAPITAL LETTER Z", "fonts": ["Sans", "Sans CJK HK", "Sans CJK JP", "Sans CJK KR", "Sans CJK SC", "Sans CJK TC", "Sans Display", "Sans Math", "Sans Mono", "Sans Symbols", "Serif", "Serif Display", "Serif Tangut", "Traditional Nushu", "Arimo", "Cousine", "Tinos"]}, "91": {"name": "LEFT SQUARE BRACKET", "fonts": ["Looped Thai Regular", "Looped Thai UI Regular", "Nastaliq Urdu", "NotoSerifTamilSlanted", "Sans", "Sans Adlam", "Sans Adlam Unjoined", "Sans Bengali", "Sans Bengali UI", "Sans CJK HK", "Sans CJK JP", "Sans CJK KR", "Sans CJK SC", "Sans CJK TC", "Sans Devanagari", "Sans Devanagari UI", "Sans Display", "Sans Gujarati", "Sans Gujarati UI", "Sans Gurmukhi", "Sans Gurmukhi UI", "Sans Kannada", "Sans Kannada UI", "Sans Malayalam", "Sans Malayalam UI", "Sans Math", "Sans Mono", "Sans Oriya", "Sans Oriya UI", "Sans Sinhala", "Sans Sinhala UI", "Sans Syriac", "Sans Tamil", "Sans Tamil UI", "Sans Telugu", "Sans Telugu UI", "Sans Wancho", "Serif", "Serif Bengali", "Serif Devanagari", "Serif Display", "Serif Gujarati", "Serif Gurmukhi", "Serif Kannada", "Serif Khojki", "Serif Malayalam", "Serif Oriya", "Serif Sinhala", "Serif Tamil", "Serif Tangut", "Serif Telugu", "Arimo", "Cousine", "Tinos"]}, "92": {"name": "REVERSE SOLIDUS", "fonts": ["Nastaliq Urdu", "NotoSerifTamilSlanted", "Sans", "Sans Adlam", "Sans Adlam Unjoined", "Sans Bengali", "Sans Bengali UI", "Sans CJK HK", "Sans CJK JP", "Sans CJK KR", "Sans CJK SC", "Sans CJK TC", "Sans Devanagari", "Sans Devanagari UI", "Sans Display", "Sans Gujarati", "Sans Gujarati UI", "Sans Gurmukhi", "Sans Gurmukhi UI", "Sans Kannada", "Sans Kannada UI", "Sans Malayalam", "Sans Malayalam UI", "Sans Math", "Sans Mono", "Sans Oriya", "Sans Oriya UI", "Sans Sinhala", "Sans Sinhala UI", "Sans Syriac", "Sans Tamil", "Sans Tamil UI", "Sans Telugu", "Sans Telugu UI", "Sans Wancho", "Serif", "Serif Bengali", "Serif Devanagari", "Serif Display", "Serif Gujarati", "Serif Gurmukhi", "Serif Kannada", "Serif Khojki", "Serif Malayalam", "Serif Oriya", "Serif Sinhala", "Serif Tamil", "Serif Tangut", "Serif Telugu", "Arimo", "Cousine", "Tinos"]}, "93": {"name": "RIGHT SQUARE BRACKET", "fonts": ["Looped Thai Regular", "Looped Thai UI Regular", "Nastaliq Urdu", "NotoSerifTamilSlanted", "Sans", "Sans Adlam", "Sans Adlam Unjoined", "Sans Bengali", "Sans Bengali UI", "Sans CJK HK", "Sans CJK JP", "Sans CJK KR", "Sans CJK SC", "Sans CJK TC", "Sans Devanagari", "Sans Devanagari UI", "Sans Display", "Sans Gujarati", "Sans Gujarati UI", "Sans Gurmukhi", "Sans Gurmukhi UI", "Sans Kannada", "Sans Kannada UI", "Sans Malayalam", "Sans Malayalam UI", "Sans Math", "Sans Mono", "Sans Oriya", "Sans Oriya UI", "Sans Sinhala", "Sans Sinhala UI", "Sans Syriac", "Sans Tamil", "Sans Tamil UI", "Sans Telugu", "Sans Telugu UI", "Sans Wancho", "Serif", "Serif Bengali", "Serif Devanagari", "Serif Display", "Serif Gujarati", "Serif Gurmukhi", "Serif Kannada", "Serif Khojki", "Serif Malayalam", "Serif Oriya", "Serif Sinhala", "Serif Tamil", "Serif Tangut", "Serif Telugu", "Arimo", "Cousine", "Tinos"]}, "94": {"name": "CIRCUMFLEX ACCENT", "fonts": ["NotoSerifTamilSlanted", "Sans", "Sans Adlam", "Sans Adlam Unjoined", "Sans Bengali", "Sans Bengali UI", "Sans CJK HK", "Sans CJK JP", "Sans CJK KR", "Sans CJK SC", "Sans CJK TC", "Sans Devanagari", "Sans Devanagari UI", "Sans Display", "Sans Gujarati", "Sans Gujarati UI", "Sans Gurmukhi", "Sans Gurmukhi UI", "Sans Kannada", "Sans Kannada UI", "Sans Malayalam", "Sans Malayalam UI", "Sans Math", "Sans Mono", "Sans Oriya", "Sans Oriya UI", "Sans Sinhala", "Sans Sinhala UI", "Sans Tamil", "Sans Tamil UI", "Sans Telugu", "Sans Telugu UI", "Sans Vithkuqi", "Serif", "Serif Bengali", "Serif Devanagari", "Serif Display", "Serif Gujarati", "Serif Gurmukhi", "Serif Kannada", "Serif Khojki", "Serif Malayalam", "Serif Oriya", "Serif Sinhala", "Serif Tamil", "Serif Tangut", "Serif Telugu", "Serif Vithkuqi", "Arimo", "Cousine", "Tinos"]}, "95": {"name": "LOW LINE", "fonts": ["NotoSerifTamilSlanted", "Sans", "Sans Adlam", "Sans Adlam Unjoined", "Sans Bengali", "Sans Bengali UI", "Sans CJK HK", "Sans CJK JP", "Sans CJK KR", "Sans CJK SC", "Sans CJK TC", "Sans Devanagari", "Sans Devanagari UI", "Sans Display", "Sans Gujarati", "Sans Gujarati UI", "Sans Gurmukhi", "Sans Gurmukhi UI", "Sans Kannada", "Sans Kannada UI", "Sans Malayalam", "Sans Malayalam UI", "Sans Math", "Sans Mono", "Sans Oriya", "Sans Oriya UI", "Sans Sinhala", "Sans Sinhala UI", "Sans Tamil", "Sans Tamil UI", "Sans Telugu", "Sans Telugu UI", "Serif", "Serif Bengali", "Serif Devanagari", "Serif Display", "Serif Gujarati", "Serif Gurmukhi", "Serif Kannada", "Serif Khojki", "Serif Malayalam", "Serif Oriya", "Serif Sinhala", "Serif Tamil", "Serif Tangut", "Serif Telugu", "Arimo", "Cousine", "Tinos"]}, "96": {"name": "GRAVE ACCENT", "fonts": ["Sans", "Sans CJK HK", "Sans CJK JP", "Sans CJK KR", "Sans CJK SC", "Sans CJK TC", "Sans Display", "Sans Math", "Sans Mono", "Serif", "Serif Display", "Serif Tangut", "Arimo", "Cousine", "Tinos"]}, "97": {"name": "LATIN SMALL LETTER A", "fonts": ["Sans", "Sans CJK HK", "Sans CJK JP", "Sans CJK KR", "Sans CJK SC", "Sans CJK TC", "Sans Display", "Sans Math", "Sans Mono", "Sans Symbols", "Serif", "Serif Display", "Serif Tangut", "Traditional Nushu", "Arimo", "Cousine", "Tinos"]}, "98": {"name": "LATIN SMALL LETTER B", "fonts": ["Sans", "Sans CJK HK", "Sans CJK JP", "Sans CJK KR", "Sans CJK SC", "Sans CJK TC", "Sans Display", "Sans Math", "Sans Mono", "Sans Symbols", "Serif", "Serif Display", "Serif Tangut", "Traditional Nushu", "Arimo", "Cousine", "Tinos"]}, "99": {"name": "LATIN SMALL LETTER C", "fonts": ["Sans", "Sans CJK HK", "Sans CJK JP", "Sans CJK KR", "Sans CJK SC", "Sans CJK TC", "Sans Display", "Sans Math", "Sans Mono", "Sans Symbols", "Serif", "Serif Display", "Serif Tangut", "Traditional Nushu", "Arimo", "Cousine", "Tinos"]}, "100": {"name": "LATIN SMALL LETTER D", "fonts": ["Sans", "Sans CJK HK", "Sans CJK JP", "Sans CJK KR", "Sans CJK SC", "Sans CJK TC", "Sans Display", "Sans Math", "Sans Mono", "Sans Symbols", "Serif", "Serif Display", "Serif Tangut", "Traditional Nushu", "Arimo", "Cousine", "Tinos"]}, "101": {"name": "LATIN SMALL LETTER E", "fonts": ["Sans", "Sans CJK HK", "Sans CJK JP", "Sans CJK KR", "Sans CJK SC", "Sans CJK TC", "Sans Display", "Sans Math", "Sans Mono", "Sans Symbols", "Serif", "Serif Display", "Serif Tangut", "Traditional Nushu", "Arimo", "Cousine", "Tinos"]}, "102": {"name": "LATIN SMALL LETTER F", "fonts": ["Sans", "Sans CJK HK", "Sans CJK JP", "Sans CJK KR", "Sans CJK SC", "Sans CJK TC", "Sans Display", "Sans Math", "Sans Mono", "Sans Symbols", "Serif", "Serif Display", "Serif Tangut", "Traditional Nushu", "Arimo", "Cousine", "Tinos"]}, "103": {"name": "LATIN SMALL LETTER G", "fonts": ["Sans", "Sans CJK HK", "Sans CJK JP", "Sans CJK KR", "Sans CJK SC", "Sans CJK TC", "Sans Display", "Sans Math", "Sans Mono", "Sans Symbols", "Serif", "Serif Display", "Serif Tangut", "Traditional Nushu", "Arimo", "Cousine", "Tinos"]}, "104": {"name": "LATIN SMALL LETTER H", "fonts": ["Sans", "Sans CJK HK", "Sans CJK JP", "Sans CJK KR", "Sans CJK SC", "Sans CJK TC", "Sans Display", "Sans Math", "Sans Mono", "Sans Symbols", "Serif", "Serif Display", "Serif Tangut", "Traditional Nushu", "Arimo", "Cousine", "Tinos"]}, "105": {"name": "LATIN SMALL LETTER I", "fonts": ["Sans", "Sans CJK HK", "Sans CJK JP", "Sans CJK KR", "Sans CJK SC", "Sans CJK TC", "Sans Display", "Sans Math", "Sans Mono", "Sans Symbols", "Serif", "Serif Display", "Serif Tangut", "Traditional Nushu", "Arimo", "Cousine", "Tinos"]}, "106": {"name": "LATIN SMALL LETTER J", "fonts": ["Sans", "Sans CJK HK", "Sans CJK JP", "Sans CJK KR", "Sans CJK SC", "Sans CJK TC", "Sans Display", "Sans Math", "Sans Mono", "Sans Symbols", "Serif", "Serif Display", "Serif Tangut", "Traditional Nushu", "Arimo", "Cousine", "Tinos"]}, "107": {"name": "LATIN SMALL LETTER K", "fonts": ["Sans", "Sans CJK HK", "Sans CJK JP", "Sans CJK KR", "Sans CJK SC", "Sans CJK TC", "Sans Display", "Sans Math", "Sans Mono", "Sans Symbols", "Serif", "Serif Display", "Serif Tangut", "Traditional Nushu", "Arimo", "Cousine", "Tinos"]}, "108": {"name": "LATIN SMALL LETTER L", "fonts": ["Sans", "Sans CJK HK", "Sans CJK JP", "Sans CJK KR", "Sans CJK SC", "Sans CJK TC", "Sans Display", "Sans Math", "Sans Mono", "Sans Symbols", "Serif", "Serif Display", "Serif Tangut", "Traditional Nushu", "Arimo", "Cousine", "Tinos"]}, "109": {"name": "LATIN SMALL LETTER M", "fonts": ["Sans", "Sans CJK HK", "Sans CJK JP", "Sans CJK KR", "Sans CJK SC", "Sans CJK TC", "Sans Display", "Sans Math", "Sans Mono", "Sans Symbols", "Serif", "Serif Display", "Serif Tangut", "Traditional Nushu", "Arimo", "Cousine", "Tinos"]}, "110": {"name": "LATIN SMALL LETTER N", "fonts": ["Sans", "Sans CJK HK", "Sans CJK JP", "Sans CJK KR", "Sans CJK SC", "Sans CJK TC", "Sans Display", "Sans Math", "Sans Mono", "Sans Symbols", "Serif", "Serif Display", "Serif Tangut", "Traditional Nushu", "Arimo", "Cousine", "Tinos"]}, "111": {"name": "LATIN SMALL LETTER O", "fonts": ["Sans", "Sans CJK HK", "Sans CJK JP", "Sans CJK KR", "Sans CJK SC", "Sans CJK TC", "Sans Display", "Sans Math", "Sans Mono", "Sans Symbols", "Serif", "Serif Display", "Serif Tangut", "Traditional Nushu", "Arimo", "Cousine", "Tinos"]}, "112": {"name": "LATIN SMALL LETTER P", "fonts": ["Sans", "Sans CJK HK", "Sans CJK JP", "Sans CJK KR", "Sans CJK SC", "Sans CJK TC", "Sans Display", "Sans Math", "Sans Mono", "Sans Symbols", "Serif", "Serif Display", "Serif Tangut", "Traditional Nushu", "Arimo", "Cousine", "Tinos"]}, "113": {"name": "LATIN SMALL LETTER Q", "fonts": ["Sans", "Sans CJK HK", "Sans CJK JP", "Sans CJK KR", "Sans CJK SC", "Sans CJK TC", "Sans Display", "Sans Math", "Sans Mono", "Sans Symbols", "Serif", "Serif Display", "Serif Tangut", "Traditional Nushu", "Arimo", "Cousine", "Tinos"]}, "114": {"name": "LATIN SMALL LETTER R", "fonts": ["Sans", "Sans CJK HK", "Sans CJK JP", "Sans CJK KR", "Sans CJK SC", "Sans CJK TC", "Sans Display", "Sans Math", "Sans Mono", "Sans Symbols", "Serif", "Serif Display", "Serif Tangut", "Traditional Nushu", "Arimo", "Cousine", "Tinos"]}, "115": {"name": "LATIN SMALL LETTER S", "fonts": ["Sans", "Sans CJK HK", "Sans CJK JP", "Sans CJK KR", "Sans CJK SC", "Sans CJK TC", "Sans Display", "Sans Math", "Sans Mono", "Sans Symbols", "Serif", "Serif Display", "Serif Tangut", "Traditional Nushu", "Arimo", "Cousine", "Tinos"]}, "116": {"name": "LATIN SMALL LETTER T", "fonts": ["Sans", "Sans CJK HK", "Sans CJK JP", "Sans CJK KR", "Sans CJK SC", "Sans CJK TC", "Sans Display", "Sans Math", "Sans Mono", "Sans Symbols", "Serif", "Serif Display", "Serif Tangut", "Traditional Nushu", "Arimo", "Cousine", "Tinos"]}, "117": {"name": "LATIN SMALL LETTER U", "fonts": ["Sans", "Sans CJK HK", "Sans CJK JP", "Sans CJK KR", "Sans CJK SC", "Sans CJK TC", "Sans Display", "Sans Math", "Sans Mono", "Sans Symbols", "Serif", "Serif Display", "Serif Tangut", "Traditional Nushu", "Arimo", "Cousine", "Tinos"]}, "118": {"name": "LATIN SMALL LETTER V", "fonts": ["Sans", "Sans CJK HK", "Sans CJK JP", "Sans CJK KR", "Sans CJK SC", "Sans CJK TC", "Sans Display", "Sans Math", "Sans Mono", "Sans Symbols", "Serif", "Serif Display", "Serif Tangut", "Traditional Nushu", "Arimo", "Cousine", "Tinos"]}, "119": {"name": "LATIN SMALL LETTER W", "fonts": ["Sans", "Sans CJK HK", "Sans CJK JP", "Sans CJK KR", "Sans CJK SC", "Sans CJK TC", "Sans Display", "Sans Math", "Sans Mono", "Sans Symbols", "Serif", "Serif Display", "Serif Tangut", "Traditional Nushu", "Arimo", "Cousine", "Tinos"]}, "120": {"name": "LATIN SMALL LETTER X", "fonts": ["Sans", "Sans CJK HK", "Sans CJK JP", "Sans CJK KR", "Sans CJK SC", "Sans CJK TC", "Sans Display", "Sans Math", "Sans Mono", "Sans Symbols", "Serif", "Serif Display", "Serif Tangut", "Traditional Nushu", "Arimo", "Cousine", "Tinos"]}, "121": {"name": "LATIN SMALL LETTER Y", "fonts": ["Sans", "Sans CJK HK", "Sans CJK JP", "Sans CJK KR", "Sans CJK SC", "Sans CJK TC", "Sans Display", "Sans Math", "Sans Mono", "Sans Symbols", "Serif", "Serif Display", "Serif Tangut", "Traditional Nushu", "Arimo", "Cousine", "Tinos"]}, "122": {"name": "LATIN SMALL LETTER Z", "fonts": ["Sans", "Sans CJK HK", "Sans CJK JP", "Sans CJK KR", "Sans CJK SC", "Sans CJK TC", "Sans Display", "Sans Math", "Sans Mono", "Sans Symbols", "Serif", "Serif Display", "Serif Tangut", "Traditional Nushu", "Arimo", "Cousine", "Tinos"]}, "123": {"name": "LEFT CURLY BRACKET", "fonts": ["Nastaliq Urdu", "NotoSerifTamilSlanted", "Sans", "Sans Adlam", "Sans Adlam Unjoined", "Sans Bengali", "Sans Bengali UI", "Sans CJK HK", "Sans CJK JP", "Sans CJK KR", "Sans CJK SC", "Sans CJK TC", "Sans Devanagari", "Sans Devanagari UI", "Sans Display", "Sans Gujarati", "Sans Gujarati UI", "Sans Gurmukhi", "Sans Gurmukhi UI", "Sans Kannada", "Sans Kannada UI", "Sans Malayalam", "Sans Malayalam UI", "Sans Math", "Sans Mono", "Sans Oriya", "Sans Oriya UI", "Sans Sinhala", "Sans Sinhala UI", "Sans Tamil", "Sans Tamil UI", "Sans Telugu", "Sans Telugu UI", "Sans Wancho", "Serif", "Serif Bengali", "Serif Devanagari", "Serif Display", "Serif Gujarati", "Serif Gurmukhi", "Serif Kannada", "Serif Khojki", "Serif Malayalam", "Serif Oriya", "Serif Sinhala", "Serif Tamil", "Serif Tangut", "Serif Telugu", "Arimo", "Cousine", "Tinos"]}, "124": {"name": "VERTICAL LINE", "fonts": ["Nastaliq Urdu", "NotoSerifTamilSlanted", "Sans", "Sans Adlam", "Sans Adlam Unjoined", "Sans Bengali", "Sans Bengali UI", "Sans CJK HK", "Sans CJK JP", "Sans CJK KR", "Sans CJK SC", "Sans CJK TC", "Sans Devanagari", "Sans Devanagari UI", "Sans Display", "Sans Gujarati", "Sans Gujarati UI", "Sans Gurmukhi", "Sans Gurmukhi UI", "Sans Kannada", "Sans Kannada UI", "Sans Malayalam", "Sans Malayalam UI", "Sans Math", "Sans Mono", "Sans Oriya", "Sans Oriya UI", "Sans Sinhala", "Sans Sinhala UI", "Sans Tamil", "Sans Tamil UI", "Sans Telugu", "Sans Telugu UI", "Serif", "Serif Bengali", "Serif Devanagari", "Serif Display", "Serif Gujarati", "Serif Gurmukhi", "Serif Kannada", "Serif Khojki", "Serif Malayalam", "Serif Oriya", "Serif Sinhala", "Serif Tamil", "Serif Tangut", "Serif Telugu", "Serif Tibetan", "Arimo", "Cousine", "Tinos"]}, "125": {"name": "RIGHT CURLY BRACKET", "fonts": ["Nastaliq Urdu", "NotoSerifTamilSlanted", "Sans", "Sans Adlam", "Sans Adlam Unjoined", "Sans Bengali", "Sans Bengali UI", "Sans CJK HK", "Sans CJK JP", "Sans CJK KR", "Sans CJK SC", "Sans CJK TC", "Sans Devanagari", "Sans Devanagari UI", "Sans Display", "Sans Gujarati", "Sans Gujarati UI", "Sans Gurmukhi", "Sans Gurmukhi UI", "Sans Kannada", "Sans Kannada UI", "Sans Malayalam", "Sans Malayalam UI", "Sans Math", "Sans Mono", "Sans Oriya", "Sans Oriya UI", "Sans Sinhala", "Sans Sinhala UI", "Sans Tamil", "Sans Tamil UI", "Sans Telugu", "Sans Telugu UI", "Sans Wancho", "Serif", "Serif Bengali", "Serif Devanagari", "Serif Display", "Serif Gujarati", "Serif Gurmukhi", "Serif Kannada", "Serif Khojki", "Serif Malayalam", "Serif Oriya", "Serif Sinhala", "Serif Tamil", "Serif Tangut", "Serif Telugu", "Arimo", "Cousine", "Tinos"]}, "126": {"name": "TILDE", "fonts": ["NotoSerifTamilSlanted", "Sans", "Sans Bengali", "Sans Bengali UI", "Sans CJK HK", "Sans CJK JP", "Sans CJK KR", "Sans CJK SC", "Sans CJK TC", "Sans Devanagari", "Sans Devanagari UI", "Sans Display", "Sans Gujarati", "Sans Gujarati UI", "Sans Gurmukhi", "Sans Gurmukhi UI", "Sans Kannada", "Sans Kannada UI", "Sans Malayalam", "Sans Malayalam UI", "Sans Math", "Sans Mono", "Sans Oriya", "Sans Oriya UI", "Sans Sinhala", "Sans Sinhala UI", "Sans Tamil", "Sans Tamil UI", "Sans Telugu", "Sans Telugu UI", "Serif", "Serif Bengali", "Serif Devanagari", "Serif Display", "Serif Gujarati", "Serif Gurmukhi", "Serif Kannada", "Serif Khojki", "Serif Malayalam", "Serif Oriya", "Serif Sinhala", "Serif Tamil", "Serif Tangut", "Serif Telugu", "Arimo", "Cousine", "Tinos"]}, "127": {"name": "<control>", "special": true}}, "age": "1.1"}